Workbook

Sheet Inicio

Sheet Risco por Cooperativa
F4: PAPEL DE TRABALHO RSAC (Risco Social Ambiental e Climático) | O4: Retorno
C9: Elaborado por: Gleibson Carreiro de Sousa | F9: Data Base: | G9: 46023 | H9: Periodicadade: Mensal
C10: Revisado por: | F10: Data da Revisão
C13: RESULTADO
O14: Retorno
D15: ANÁLISE 01: Relatório de Risco por Cooperativa - Quantitativo
D17: QUANTITATIVO RSAC | F17: RELATÓRIO DE RISCO POR COOPERATIVA
F18: =EOMONTH(G9,-1)+1 -> 46023 | G18: a | H18: =EOMONTH(G9,0) -> 46053
D19: COOEPRATIVA | E19: AGÊNCIA | F19: BAIXO RISCO | G19: MÉDIO RISCO | H19: ALTO RISCO | I19: TOTAL
D20: Sicoob nova Central | E20: 1004 | F20: =SUMIFS('A1004'!L:L,'A1004'!$K:$K,">="&'Risco por Cooperativa'!$F$18,'A1004'!$K:$K,"<="&'Risco por Cooperativa'!$H$18) -> 0 | G20: =SUMIFS('A1004'!M:M,'A1004'!$K:$K,">="&'Risco por Cooperativa'!$F$18,'A1004'!$K:$K,"<="&'Risco por Cooperativa'!$H$18) -> 0 | H20: =SUMIFS('A1004'!N:N,'A1004'!$K:$K,">="&'Risco por Cooperativa'!$F$18,'A1004'!$K:$K,"<="&'Risco por Cooperativa'!$H$18) -> 0 | I20: =SUM(F20:H20) -> 0
D21: Sicoob Agrorural | E21: 3042 | F21: =SUMIFS('A3042'!L:L,'A3042'!$K:$K,">="&'Risco por Cooperativa'!$F$18,'A3042'!$K:$K,"<="&'Risco por Cooperativa'!$H$18) -> 18 | G21: =SUMIFS('A3042'!M:M,'A3042'!$K:$K,">="&'Risco por Cooperativa'!$F$18,'A3042'!$K:$K,"<="&'Risco por Cooperativa'!$H$18) -> 1 | H21: =SUMIFS('A3042'!N:N,'A3042'!$K:$K,">="&'Risco por Cooperativa'!$F$18,'A3042'!$K:$K,"<="&'Risco por Cooperativa'!$H$18) -> 1 | I21: =SUM(F21:H21) -> 20
D22: Sicoob Centro-Sul | E22: 3043 | F22: =SUMIFS('A3043'!L:L,'A3043'!$K:$K,">="&'Risco por Cooperativa'!$F$18,'A3043'!$K:$K,"<="&'Risco por Cooperativa'!$H$18) -> 10 | G22: =SUMIFS('A3043'!M:M,'A3043'!$K:$K,">="&'Risco por Cooperativa'!$F$18,'A3043'!$K:$K,"<="&'Risco por Cooperativa'!$H$18) -> 6 | H22: =SUMIFS('A3043'!N:N,'A3043'!$K:$K,">="&'Risco por Cooperativa'!$F$18,'A3043'!$K:$K,"<="&'Risco por Cooperativa'!$H$18) -> 2 | I22: =SUM(F22:H22) -> 18
D23: Sicoob Credi-Rural | E23: 3054 | F23: =SUMIFS('A3054'!L:L,'A3054'!$K:$K,">="&'Risco por Cooperativa'!$F$18,'A3054'!$K:$K,"<="&'Risco por Cooperativa'!$H$18) -> 70 | G23: =SUMIFS('A3054'!M:M,'A3054'!$K:$K,">="&'Risco por Cooperativa'!$F$18,'A3054'!$K:$K,"<="&'Risco por Cooperativa'!$H$18) -> 9 | H23: =SUMIFS('A3054'!N:N,'A3054'!$K:$K,">="&'Risco por Cooperativa'!$F$18,'A3054'!$K:$K,"<="&'Risco por Cooperativa'!$H$18) -> 9 | I23: =SUM(F23:H23) -> 88
D24: Siccob do Vale | E24: 3059 | F24: =SUMIFS('A3059'!L:L,'A3059'!$K:$K,">="&'Risco por Cooperativa'!$F$18,'A3059'!$K:$K,"<="&'Risco por Cooperativa'!$H$18) -> 27 | G24: =SUMIFS('A3059'!M:M,'A3059'!$K:$K,">="&'Risco por Cooperativa'!$F$18,'A3059'!$K:$K,"<="&'Risco por Cooperativa'!$H$18) -> 4 | H24: =SUMIFS('A3059'!N:N,'A3059'!$K:$K,">="&'Risco por Cooperativa'!$F$18,'A3059'!$K:$K,"<="&'Risco por Cooperativa'!$H$18) -> 1 | I24: =SUM(F24:H24) -> 32
D25: Sicoob Palmeiras | E25: 3060 | F25: =SUMIFS('A3060'!L:L,'A3060'!$K:$K,">="&'Risco por Cooperativa'!$F$18,'A3060'!$K:$K,"<="&'Risco por Cooperativa'!$H$18) -> 16 | G25: =SUMIFS('A3060'!M:M,'A3060'!$K:$K,">="&'Risco por Cooperativa'!$F$18,'A3060'!$K:$K,"<="&'Risco por Cooperativa'!$H$18) -> 0 | H25: =SUMIFS('A3060'!N:N,'A3060'!$K:$K,">="&'Risco por Cooperativa'!$F$18,'A3060'!$K:$K,"<="&'Risco por Cooperativa'!$H$18) -> 1 | I25: =SUM(F25:H25) -> 17
D26: Sicoob Credijur | E26: 3233 | F26: =SUMIFS('A3233'!L:L,'A3233'!$K:$K,">="&'Risco por Cooperativa'!$F$18,'A3233'!$K:$K,"<="&'Risco por Cooperativa'!$H$18) -> 2 | G26: =SUMIFS('A3233'!M:M,'A3233'!$K:$K,">="&'Risco por Cooperativa'!$F$18,'A3233'!$K:$K,"<="&'Risco por Cooperativa'!$H$18) -> 0 | H26: =SUMIFS('A3233'!N:N,'A3233'!$K:$K,">="&'Risco por Cooperativa'!$F$18,'A3233'!$K:$K,"<="&'Risco por Cooperativa'!$H$18) -> 0 | I26: =SUM(F26:H26) -> 2
D27: Sicoob Credicapa | E27: 3261 | F27: =SUMIFS('A3261'!L:L,'A3261'!$K:$K,">="&'Risco por Cooperativa'!$F$18,'A3261'!$K:$K,"<="&'Risco por Cooperativa'!$H$18) -> 7 | G27: =SUMIFS('A3261'!M:M,'A3261'!$K:$K,">="&'Risco por Cooperativa'!$F$18,'A3261'!$K:$K,"<="&'Risco por Cooperativa'!$H$18) -> 0 | H27: =SUMIFS('A3261'!N:N,'A3261'!$K:$K,">="&'Risco por Cooperativa'!$F$18,'A3261'!$K:$K,"<="&'Risco por Cooperativa'!$H$18) -> 1 | I27: =SUM(F27:H27) -> 8
D28: Sicoob Tocantins | E28: 3263 | F28: =SUMIFS('A3263'!L:L,'A3263'!$K:$K,">="&'Risco por Cooperativa'!$F$18,'A3263'!$K:$K,"<="&'Risco por Cooperativa'!$H$18) -> 10 | G28: =SUMIFS('A3263'!M:M,'A3263'!$K:$K,">="&'Risco por Cooperativa'!$F$18,'A3263'!$K:$K,"<="&'Risco por Cooperativa'!$H$18) -> 0 | H28: =SUMIFS('A3263'!N:N,'A3263'!$K:$K,">="&'Risco por Cooperativa'!$F$18,'A3263'!$K:$K,"<="&'Risco por Cooperativa'!$H$18) -> 2 | I28: =SUM(F28:H28) -> 12
D29: Sicoob Cerrado | E29: 3320 | F29: =SUMIFS('A3320'!L:L,'A3320'!$K:$K,">="&'Risco por Cooperativa'!$F$18,'A3320'!$K:$K,"<="&'Risco por Cooperativa'!$H$18) -> 8 | G29: =SUMIFS('A3320'!M:M,'A3320'!$K:$K,">="&'Risco por Cooperativa'!$F$18,'A3320'!$K:$K,"<="&'Risco por Cooperativa'!$H$18) -> 1 | H29: =SUMIFS('A3320'!N:N,'A3320'!$K:$K,">="&'Risco por Cooperativa'!$F$18,'A3320'!$K:$K,"<="&'Risco por Cooperativa'!$H$18) -> 2 | I29: =SUM(F29:H29) -> 11
D30: Sicoob Emprecred | E30: 3332 | F30: =SUMIFS('A3332'!L:L,'A3332'!$K:$K,">="&'Risco por Cooperativa'!$F$18,'A3332'!$K:$K,"<="&'Risco por Cooperativa'!$H$18) -> 8 | G30: =SUMIFS('A3332'!M:M,'A3332'!$K:$K,">="&'Risco por Cooperativa'!$F$18,'A3332'!$K:$K,"<="&'Risco por Cooperativa'!$H$18) -> 0 | H30: =SUMIFS('A3332'!N:N,'A3332'!$K:$K,">="&'Risco por Cooperativa'!$F$18,'A3332'!$K:$K,"<="&'Risco por Cooperativa'!$H$18) -> 4 | I30: =SUM(F30:H30) -> 12
D31: Sicob Secovicred | E31: 3333 | F31: =SUMIFS('A3333'!L:L,'A3333'!$K:$K,">="&'Risco por Cooperativa'!$F$18,'A3333'!$K:$K,"<="&'Risco por Cooperativa'!$H$18) -> 22 | G31: =SUMIFS('A3333'!M:M,'A3333'!$K:$K,">="&'Risco por Cooperativa'!$F$18,'A3333'!$K:$K,"<="&'Risco por Cooperativa'!$H$18) -> 1 | H31: =SUMIFS('A3333'!N:N,'A3333'!$K:$K,">="&'Risco por Cooperativa'!$F$18,'A3333'!$K:$K,"<="&'Risco por Cooperativa'!$H$18) -> 4 | I31: =SUM(F31:H31) -> 27
D32: Sicoob Juriscred | E32: 3348 | F32: =SUMIFS('A3348'!L:L,'A3348'!$K:$K,">="&'Risco por Cooperativa'!$F$18,'A3348'!$K:$K,"<="&'Risco por Cooperativa'!$H$18) -> 2 | G32: =SUMIFS('A3348'!M:M,'A3348'!$K:$K,">="&'Risco por Cooperativa'!$F$18,'A3348'!$K:$K,"<="&'Risco por Cooperativa'!$H$18) -> 0 | H32: =SUMIFS('A3348'!N:N,'A3348'!$K:$K,">="&'Risco por Cooperativa'!$F$18,'A3348'!$K:$K,"<="&'Risco por Cooperativa'!$H$18) -> 0 | I32: =SUM(F32:H32) -> 2
D33: Sicoob Credicer | E33: 3349 | F33: =SUMIFS('A3349'!L:L,'A3349'!$K:$K,">="&'Risco por Cooperativa'!$F$18,'A3349'!$K:$K,"<="&'Risco por Cooperativa'!$H$18) -> 3 | G33: =SUMIFS('A3349'!M:M,'A3349'!$K:$K,">="&'Risco por Cooperativa'!$F$18,'A3349'!$K:$K,"<="&'Risco por Cooperativa'!$H$18) -> 0 | H33: =SUMIFS('A3349'!N:N,'A3349'!$K:$K,">="&'Risco por Cooperativa'!$F$18,'A3349'!$K:$K,"<="&'Risco por Cooperativa'!$H$18) -> 1 | I33: =SUM(F33:H33) -> 4
D34: Sicoob Crediadag | E34: 3351 | F34: =SUMIFS('A3351'!L:L,'A3351'!$K:$K,">="&'Risco por Cooperativa'!$F$18,'A3351'!$K:$K,"<="&'Risco por Cooperativa'!$H$18) -> 5 | G34: =SUMIFS('A3351'!M:M,'A3351'!$K:$K,">="&'Risco por Cooperativa'!$F$18,'A3351'!$K:$K,"<="&'Risco por Cooperativa'!$H$18) -> 0 | H34: =SUMIFS('A3351'!N:N,'A3351'!$K:$K,">="&'Risco por Cooperativa'!$F$18,'A3351'!$K:$K,"<="&'Risco por Cooperativa'!$H$18) -> 1 | I34: =SUM(F34:H34) -> 6
D35: Sicoob Empresarial GO | E35: 3343 | F35: =SUMIFS('A3343'!L:L,'A3343'!$K:$K,">="&'Risco por Cooperativa'!$F$18,'A3343'!$K:$K,"<="&'Risco por Cooperativa'!$H$18) -> 9 | G35: =SUMIFS('A3343'!M:M,'A3343'!$K:$K,">="&'Risco por Cooperativa'!$F$18,'A3343'!$K:$K,"<="&'Risco por Cooperativa'!$H$18) -> 1 | H35: =SUMIFS('A3343'!N:N,'A3343'!$K:$K,">="&'Risco por Cooperativa'!$F$18,'A3343'!$K:$K,"<="&'Risco por Cooperativa'!$H$18) -> 0 | I35: =SUM(F35:H35) -> 10
D36: Sicoob Cooprem | E36: 3350 | F36: =SUMIFS('A3350'!L:L,'A3350'!$K:$K,">="&'Risco por Cooperativa'!$F$18,'A3350'!$K:$K,"<="&'Risco por Cooperativa'!$H$18) -> 10 | G36: =SUMIFS('A3350'!M:M,'A3350'!$K:$K,">="&'Risco por Cooperativa'!$F$18,'A3350'!$K:$K,"<="&'Risco por Cooperativa'!$H$18) -> 1 | H36: =SUMIFS('A3350'!N:N,'A3350'!$K:$K,">="&'Risco por Cooperativa'!$F$18,'A3350'!$K:$K,"<="&'Risco por Cooperativa'!$H$18) -> 1 | I36: =SUM(F36:H36) -> 12
D37: Sicoob Credi-Comigo | E37: 3336 | F37: =SUMIFS('A3336'!L:L,'A3336'!$K:$K,">="&'Risco por Cooperativa'!$F$18,'A3336'!$K:$K,"<="&'Risco por Cooperativa'!$H$18) -> 0 | G37: =SUMIFS('A3336'!M:M,'A3336'!$K:$K,">="&'Risco por Cooperativa'!$F$18,'A3336'!$K:$K,"<="&'Risco por Cooperativa'!$H$18) -> 0 | H37: =SUMIFS('A3336'!N:N,'A3336'!$K:$K,">="&'Risco por Cooperativa'!$F$18,'A3336'!$K:$K,"<="&'Risco por Cooperativa'!$H$18) -> 0 | I37: =SUM(F37:H37) -> 0
D38: Sicoob Credigóias | E38: 3058 | F38: =SUMIFS('A3058'!L:L,'A3058'!$K:$K,">="&'Risco por Cooperativa'!$F$18,'A3058'!$K:$K,"<="&'Risco por Cooperativa'!$H$18) -> 3 | G38: =SUMIFS('A3058'!M:M,'A3058'!$K:$K,">="&'Risco por Cooperativa'!$F$18,'A3058'!$K:$K,"<="&'Risco por Cooperativa'!$H$18) -> 2 | H38: =SUMIFS('A3058'!N:N,'A3058'!$K:$K,">="&'Risco por Cooperativa'!$F$18,'A3058'!$K:$K,"<="&'Risco por Cooperativa'!$H$18) -> 1 | I38: =SUM(F38:H38) -> 6
D39: Sicoob Coopercred | E39: 3055 | F39: =SUMIFS('A3055'!L:L,'A3055'!$K:$K,">="&'Risco por Cooperativa'!$F$18,'A3055'!$K:$K,"<="&'Risco por Cooperativa'!$H$18) -> 7 | G39: =SUMIFS('A3055'!M:M,'A3055'!$K:$K,">="&'Risco por Cooperativa'!$F$18,'A3055'!$K:$K,"<="&'Risco por Cooperativa'!$H$18) -> 0 | H39: =SUMIFS('A3055'!N:N,'A3055'!$K:$K,">="&'Risco por Cooperativa'!$F$18,'A3055'!$K:$K,"<="&'Risco por Cooperativa'!$H$18) -> 0 | I39: =SUM(F39:H39) -> 7
D40: Sicoob Unicidades | E40: 5014 | F40: =SUMIFS('A5014'!L:L,'A5014'!$K:$K,">="&'Risco por Cooperativa'!$F$18,'A5014'!$K:$K,"<="&'Risco por Cooperativa'!$H$18) -> 25 | G40: =SUMIFS('A5014'!M:M,'A5014'!$K:$K,">="&'Risco por Cooperativa'!$F$18,'A5014'!$K:$K,"<="&'Risco por Cooperativa'!$H$18) -> 1 | H40: =SUMIFS('A5014'!N:N,'A5014'!$K:$K,">="&'Risco por Cooperativa'!$F$18,'A5014'!$K:$K,"<="&'Risco por Cooperativa'!$H$18) -> 1 | I40: =SUM(F40:H40) -> 27
D41: Sicoob Mineiros | E41: 3056 | F41: =SUMIFS('A3056'!L:L,'A3056'!$K:$K,">="&'Risco por Cooperativa'!$F$18,'A3056'!$K:$K,"<="&'Risco por Cooperativa'!$H$18) -> 12 | G41: =SUMIFS('A3056'!M:M,'A3056'!$K:$K,">="&'Risco por Cooperativa'!$F$18,'A3056'!$K:$K,"<="&'Risco por Cooperativa'!$H$18) -> 0 | H41: =SUMIFS('A3056'!N:N,'A3056'!$K:$K,">="&'Risco por Cooperativa'!$F$18,'A3056'!$K:$K,"<="&'Risco por Cooperativa'!$H$18) -> 2 | I41: =SUM(F41:H41) -> 14
D42: Sicoob Centro Oeste BR | E42: 3300 | F42: =SUMIFS('A3300'!L:L,'A3300'!$K:$K,">="&'Risco por Cooperativa'!$F$18,'A3300'!$K:$K,"<="&'Risco por Cooperativa'!$H$18) -> 2 | G42: =SUMIFS('A3300'!M:M,'A3300'!$K:$K,">="&'Risco por Cooperativa'!$F$18,'A3300'!$K:$K,"<="&'Risco por Cooperativa'!$H$18) -> 1 | H42: =SUMIFS('A3300'!N:N,'A3300'!$K:$K,">="&'Risco por Cooperativa'!$F$18,'A3300'!$K:$K,"<="&'Risco por Cooperativa'!$H$18) -> 2 | I42: =SUM(F42:H42) -> 5
D43: Sicoob Executivo | E43: 4001 | F43: =SUMIFS('A4001'!L:L,'A4001'!$K:$K,">="&'Risco por Cooperativa'!$F$18,'A4001'!$K:$K,"<="&'Risco por Cooperativa'!$H$18) -> 0 | G43: =SUMIFS('A4001'!M:M,'A4001'!$K:$K,">="&'Risco por Cooperativa'!$F$18,'A4001'!$K:$K,"<="&'Risco por Cooperativa'!$H$18) -> 0 | H43: =SUMIFS('A4001'!N:N,'A4001'!$K:$K,">="&'Risco por Cooperativa'!$F$18,'A4001'!$K:$K,"<="&'Risco por Cooperativa'!$H$18) -> 0 | I43: =SUM(F43:H43) -> 0
D44: Sicoob Judiciário | E44: 4002 | F44: =SUMIFS('A4002'!L:L,'A4002'!$K:$K,">="&'Risco por Cooperativa'!$F$18,'A4002'!$K:$K,"<="&'Risco por Cooperativa'!$H$18) -> 0 | G44: =SUMIFS('A4002'!M:M,'A4002'!$K:$K,">="&'Risco por Cooperativa'!$F$18,'A4002'!$K:$K,"<="&'Risco por Cooperativa'!$H$18) -> 0 | H44: =SUMIFS('A4002'!N:N,'A4002'!$K:$K,">="&'Risco por Cooperativa'!$F$18,'A4002'!$K:$K,"<="&'Risco por Cooperativa'!$H$18) -> 0 | I44: =SUM(F44:H44) -> 0
D45: Sicoob Credijustra | E45: 4041 | F45: =SUMIFS('A4041'!L:L,'A4041'!$K:$K,">="&'Risco por Cooperativa'!$F$18,'A4041'!$K:$K,"<="&'Risco por Cooperativa'!$H$18) -> 0 | G45: =SUMIFS('A4041'!M:M,'A4041'!$K:$K,">="&'Risco por Cooperativa'!$F$18,'A4041'!$K:$K,"<="&'Risco por Cooperativa'!$H$18) -> 0 | H45: =SUMIFS('A4041'!N:N,'A4041'!$K:$K,">="&'Risco por Cooperativa'!$F$18,'A4041'!$K:$K,"<="&'Risco por Cooperativa'!$H$18) -> 0 | I45: =SUM(F45:H45) -> 0
D46: Sicoob Credibrasília | E46: 4155 | F46: =SUMIFS('A4155'!L:L,'A4155'!$K:$K,">="&'Risco por Cooperativa'!$F$18,'A4155'!$K:$K,"<="&'Risco por Cooperativa'!$H$18) -> 6 | G46: =SUMIFS('A4155'!M:M,'A4155'!$K:$K,">="&'Risco por Cooperativa'!$F$18,'A4155'!$K:$K,"<="&'Risco por Cooperativa'!$H$18) -> 5 | H46: =SUMIFS('A4155'!N:N,'A4155'!$K:$K,">="&'Risco por Cooperativa'!$F$18,'A4155'!$K:$K,"<="&'Risco por Cooperativa'!$H$18) -> 0 | I46: =SUM(F46:H46) -> 11
D47: Sicoob Crediembrapa | E47: 4198 | F47: =SUMIFS('A4198'!L:L,'A4198'!$K:$K,">="&'Risco por Cooperativa'!$F$18,'A4198'!$K:$K,"<="&'Risco por Cooperativa'!$H$18) -> 11 | G47: =SUMIFS('A4198'!M:M,'A4198'!$K:$K,">="&'Risco por Cooperativa'!$F$18,'A4198'!$K:$K,"<="&'Risco por Cooperativa'!$H$18) -> 0 | H47: =SUMIFS('A4198'!N:N,'A4198'!$K:$K,">="&'Risco por Cooperativa'!$F$18,'A4198'!$K:$K,"<="&'Risco por Cooperativa'!$H$18) -> 0 | I47: =SUM(F47:H47) -> 11
D48: Sicoob Credfaz | E48: 4221 | F48: =SUMIFS('A4221'!L:L,'A4221'!$K:$K,">="&'Risco por Cooperativa'!$F$18,'A4221'!$K:$K,"<="&'Risco por Cooperativa'!$H$18) -> 2 | G48: =SUMIFS('A4221'!M:M,'A4221'!$K:$K,">="&'Risco por Cooperativa'!$F$18,'A4221'!$K:$K,"<="&'Risco por Cooperativa'!$H$18) -> 0 | H48: =SUMIFS('A4221'!N:N,'A4221'!$K:$K,">="&'Risco por Cooperativa'!$F$18,'A4221'!$K:$K,"<="&'Risco por Cooperativa'!$H$18) -> 0 | I48: =SUM(F48:H48) -> 2
D49: Sicoob Cooperplan Credsef | E49: 4278 | F49: =SUMIFS('A4278'!L:L,'A4278'!$K:$K,">="&'Risco por Cooperativa'!$F$18,'A4278'!$K:$K,"<="&'Risco por Cooperativa'!$H$18) -> 0 | G49: =SUMIFS('A4278'!M:M,'A4278'!$K:$K,">="&'Risco por Cooperativa'!$F$18,'A4278'!$K:$K,"<="&'Risco por Cooperativa'!$H$18) -> 0 | H49: =SUMIFS('A4278'!N:N,'A4278'!$K:$K,">="&'Risco por Cooperativa'!$F$18,'A4278'!$K:$K,"<="&'Risco por Cooperativa'!$H$18) -> 1 | I49: =SUM(F49:H49) -> 1
D50: Sicoob BRMil | E50: 4332 | F50: =SUMIFS('A4332'!L:L,'A4332'!$K:$K,">="&'Risco por Cooperativa'!$F$18,'A4332'!$K:$K,"<="&'Risco por Cooperativa'!$H$18) -> 1 | G50: =SUMIFS('A4332'!M:M,'A4332'!$K:$K,">="&'Risco por Cooperativa'!$F$18,'A4332'!$K:$K,"<="&'Risco por Cooperativa'!$H$18) -> 0 | H50: =SUMIFS('A4332'!N:N,'A4332'!$K:$K,">="&'Risco por Cooperativa'!$F$18,'A4332'!$K:$K,"<="&'Risco por Cooperativa'!$H$18) -> 0 | I50: =SUM(F50:H50) -> 1
D51: Sicoob Empresarial DF | E51: 4364 | F51: =SUMIFS('A4364'!L:L,'A4364'!$K:$K,">="&'Risco por Cooperativa'!$F$18,'A4364'!$K:$K,"<="&'Risco por Cooperativa'!$H$18) -> 0 | G51: =SUMIFS('A4364'!M:M,'A4364'!$K:$K,">="&'Risco por Cooperativa'!$F$18,'A4364'!$K:$K,"<="&'Risco por Cooperativa'!$H$18) -> 0 | H51: =SUMIFS('A4364'!N:N,'A4364'!$K:$K,">="&'Risco por Cooperativa'!$F$18,'A4364'!$K:$K,"<="&'Risco por Cooperativa'!$H$18) -> 0 | I51: =SUM(F51:H51) -> 0
D52: Nota: Dados de acordo com o "RELATÓRIO DE RISCO POR COOPERATIVA", disponibilizado na Plataforma de Risco Social Ambiental e Climático do Sisbr 3.0. | I52: =SUM(I20:I51) -> 366

Sheet Resposta do quest. Cooperados
F4: PAPEL DE TRABALHO RSAC (Risco Social Ambiental e Climático) | O4: Retorno
C9: Elaborado por: Gleibson Carreiro de Sousa | F9: Data Base: | G9: 46023 | H9: Periodicadade: Mensal
C10: Revisado por: | F10: Data da Revisão
C13: RESULTADO
D14: ANÁLISE 02: Análise das respostas fornecidas no questionário de RSAC.
D16: QUANTITATIVO DA AMOSTRA | F16: RELATÓRIO DE ANÁLISE DAS RESPOSTAS DO QUESTIONÁRIO POR COOPERATIVA
D17: COOEPRATIVA | E17: AGÊNCIA | F17: =EOMONTH(G9,-1)+1 -> 46023 | G17: a | H17: =EOMONTH(G9,0) -> 46053 | O17: Retorno
D18: COOEPRATIVA | E18: AGÊNCIA | F18: Cooperados analisados | G18: Quantos NÃO apresentaram pendências? | H18: Quantos apresentaram pendências? | I18: % de pendência
D19: Sicoob nova Central | E19: 1004 | F19: =SUM('A1004'!$C$4:$E$4) -> 0 | G19: =IFERROR((F19-H19),F19) -> 0 | H19: =COUNTIF('A1004'!$AO:$AO,"Cooperado COM perguntas a serem evidenciadas") -> 0 | I19: =IFERROR((H19/F19),0) -> 0
D20: Sicoob Agrorural | E20: 3042 | F20: =SUM('A3042'!$C$4:$E$4) -> 20 | G20: =IFERROR((F20-H20),F20) -> 20 | H20: =COUNTIF('A3042'!$AO:$AO,"Cooperado COM perguntas a serem evidenciadas") -> 0 | I20: =IFERROR((H20/F20),0) -> 0
D21: Sicoob Centro-Sul | E21: 3043 | F21: =SUM('A3043'!$C$4:$E$4) -> 18 | G21: =IFERROR((F21-H21),F21) -> 13 | H21: =COUNTIF('A3043'!$AO:$AO,"Cooperado COM perguntas a serem evidenciadas") -> 5 | I21: =IFERROR((H21/F21),0) -> 0.27777778
D22: Sicoob Credi-Rural | E22: 3054 | F22: =SUM('A3054'!$C$4:$E$4) -> 88 | G22: =IFERROR((F22-H22),F22) -> 83 | H22: =COUNTIF('A3054'!$AO:$AO,"Cooperado COM perguntas a serem evidenciadas") -> 5 | I22: =IFERROR((H22/F22),0) -> 0.056818182
D23: Siccob do Vale | E23: 3059 | F23: =SUM('A3059'!$C$4:$E$4) -> 32 | G23: =IFERROR((F23-H23),F23) -> 15 | H23: =COUNTIF('A3059'!$AO:$AO,"Cooperado COM perguntas a serem evidenciadas") -> 17 | I23: =IFERROR((H23/F23),0) -> 0.53125
D24: Sicoob Palmeiras | E24: 3060 | F24: =SUM('A3060'!$C$4:$E$4) -> 17 | G24: =IFERROR((F24-H24),F24) -> 15 | H24: =COUNTIF('A3060'!$AO:$AO,"Cooperado COM perguntas a serem evidenciadas") -> 2 | I24: =IFERROR((H24/F24),0) -> 0.11764706
D25: Sicoob Credijur | E25: 3233 | F25: =SUM('A3233'!$C$4:$E$4) -> 2 | G25: =IFERROR((F25-H25),F25) -> 2 | H25: =COUNTIF('A3233'!$AO:$AO,"Cooperado COM perguntas a serem evidenciadas") -> 0 | I25: =IFERROR((H25/F25),0) -> 0
D26: Sicoob Credicapa | E26: 3261 | F26: =SUM('A3261'!$C$4:$E$4) -> 8 | G26: =IFERROR((F26-H26),F26) -> 5 | H26: =COUNTIF('A3261'!$AO:$AO,"Cooperado COM perguntas a serem evidenciadas") -> 3 | I26: =IFERROR((H26/F26),0) -> 0.375
D27: Sicoob Tocantins | E27: 3263 | F27: =SUM('A3263'!$C$4:$E$4) -> 12 | G27: =IFERROR((F27-H27),F27) -> 6 | H27: =COUNTIF('A3263'!$AO:$AO,"Cooperado COM perguntas a serem evidenciadas") -> 6 | I27: =IFERROR((H27/F27),0) -> 0.5
D28: Sicoob Cerrado | E28: 3320 | F28: =SUM('A3320'!$C$4:$E$4) -> 11 | G28: =IFERROR((F28-H28),F28) -> 10 | H28: =COUNTIF('A3320'!$AO:$AO,"Cooperado COM perguntas a serem evidenciadas") -> 1 | I28: =IFERROR((H28/F28),0) -> 0.090909091
D29: Sicoob Emprecred | E29: 3332 | F29: =SUM('A3332'!$C$4:$E$4) -> 12 | G29: =IFERROR((F29-H29),F29) -> 12 | H29: =COUNTIF('A3332'!$AO:$AO,"Cooperado COM perguntas a serem evidenciadas") -> 0 | I29: =IFERROR((H29/F29),0) -> 0
D30: Sicob Secovicred | E30: 3333 | F30: =SUM('A3333'!$C$4:$E$4) -> 27 | G30: =IFERROR((F30-H30),F30) -> 26 | H30: =COUNTIF('A3333'!$AO:$AO,"Cooperado COM perguntas a serem evidenciadas") -> 1 | I30: =IFERROR((H30/F30),0) -> 0.037037037
D31: Sicoob Juriscredcelg | E31: 3348 | F31: =SUM('A3348'!$C$4:$E$4) -> 2 | G31: =IFERROR((F31-H31),F31) -> 1 | H31: =COUNTIF('A3348'!$AO:$AO,"Cooperado COM perguntas a serem evidenciadas") -> 1 | I31: =IFERROR((H31/F31),0) -> 0.5
D32: Sicoob Credicer | E32: 3349 | F32: =SUM('A3349'!$C$4:$E$4) -> 4 | G32: =IFERROR((F32-H32),F32) -> 2 | H32: =COUNTIF('A3349'!$AO:$AO,"Cooperado COM perguntas a serem evidenciadas") -> 2 | I32: =IFERROR((H32/F32),0) -> 0.5
D33: Sicoob Crediadag | E33: 3351 | F33: =SUM('A3351'!$C$4:$E$4) -> 6 | G33: =IFERROR((F33-H33),F33) -> 5 | H33: =COUNTIF('A3351'!$AO:$AO,"Cooperado COM perguntas a serem evidenciadas") -> 1 | I33: =IFERROR((H33/F33),0) -> 0.16666667
D34: Sicoob Executivo | E34: 4001 | F34: =SUM('A4001'!$C$4:$E$4) -> 0 | G34: =IFERROR((F34-H34),F34) -> 0 | H34: =COUNTIF('A4001'!$AO:$AO,"Cooperado COM perguntas a serem evidenciadas") -> 0 | I34: =IFERROR((H34/F34),0) -> 0
D35: Sicoob Judiciário | E35: 4002 | F35: =SUM('A4002'!$C$4:$E$4) -> 0 | G35: =IFERROR((F35-H35),F35) -> 0 | H35: =COUNTIF('A4002'!$AO:$AO,"Cooperado COM perguntas a serem evidenciadas") -> 0 | I35: =IFERROR((H35/F35),0) -> 0
D36: Sicoob Credijustra | E36: 4041 | F36: =SUM('A4041'!$C$4:$E$4) -> 0 | G36: =IFERROR((F36-H36),F36) -> 0 | H36: =COUNTIF('A4041'!$AO:$AO,"Cooperado COM perguntas a serem evidenciadas") -> 0 | I36: =IFERROR((H36/F36),0) -> 0
D37: Sicoob Credibrasília | E37: 4155 | F37: =SUM('A4155'!$C$4:$E$4) -> 11 | G37: =IFERROR((F37-H37),F37) -> 8 | H37: =COUNTIF('A4155'!$AO:$AO,"Cooperado COM perguntas a serem evidenciadas") -> 3 | I37: =IFERROR((H37/F37),0) -> 0.27272727
D38: Sicoob Crediembrapa | E38: 4198 | F38: =SUM('A4198'!$C$4:$E$4) -> 11 | G38: =IFERROR((F38-H38),F38) -> 10 | H38: =COUNTIF('A4198'!$AO:$AO,"Cooperado COM perguntas a serem evidenciadas") -> 1 | I38: =IFERROR((H38/F38),0) -> 0.090909091
D39: Sicoob Credfaz | E39: 4221 | F39: =SUM('A4221'!$C$4:$E$4) -> 2 | G39: =IFERROR((F39-H39),F39) -> 2 | H39: =COUNTIF('A4221'!$AO:$AO,"Cooperado COM perguntas a serem evidenciadas") -> 0 | I39: =IFERROR((H39/F39),0) -> 0
D40: Sicoob Cooperplan Credsef | E40: 4278 | F40: =SUM('A4278'!$C$4:$E$4) -> 1 | G40: =IFERROR((F40-H40),F40) -> 1 | H40: =COUNTIF('A4278'!$AO:$AO,"Cooperado COM perguntas a serem evidenciadas") -> 0 | I40: =IFERROR((H40/F40),0) -> 0
D41: Sicoob Dfmil | E41: 4332 | F41: =SUM('A4332'!$C$4:$E$4) -> 1 | G41: =IFERROR((F41-H41),F41) -> 1 | H41: =COUNTIF('A4332'!$AO:$AO,"Cooperado COM perguntas a serem evidenciadas") -> 0 | I41: =IFERROR((H41/F41),0) -> 0
D42: Sicoob Empresarial | E42: 4364 | F42: =SUM('A4364'!$C$4:$E$4) -> 0 | G42: =IFERROR((F42-H42),F42) -> 0 | H42: =COUNTIF('A4364'!$AO:$AO,"Cooperado COM perguntas a serem evidenciadas") -> 0 | I42: =IFERROR((H42/F42),0) -> 0
D44: TOTAL | H44: =SUM(H19:H43) -> 48
B48: Apresentamos abaixo as perguntas que são avaliadas quanto à conformidade do preenchimento do questionário, assim como a inclusão de evidências referentes a elas na plataforma de Atendimento. Apresentamos abaixo, as perguntas que são avaliadas quanto a conformidade do preenchimento do questionário, bem como a inclusão de evidências quanto a elas na plataforma de Atendimento.
B51: Pergunta 01: A atividade está sujeita ao licenciamento ambiental conforme Resolução CONAMA n° 237/1997 ou normativo estadual / Municipal, se houver? Se sim, declara possuir o licenciamento necessário vigente?
C54: Para atestar a conformidade da resposta, checamos o CNAE da empresa com a resposta fornecida.
B56: Pergunta 02: Declara que há a compensação da Reserva Legal em outra Propriedade?
C59: Verificamos no Sistema AGROTOUS, se há compensação de Reserva Legal cruzando a informação com a resposta fornecida.
B61: Pergunta 03: O uso da água na área de produção e/ou construção está em conformidade com as normas de utilização de recursos hídricos (Lei n° 9.433/1997?)?
C64: A Lei n° 9.433/1997, apresenta as atividades que necessitam ou podem optar pela dispensa da outorga de água. Fazemos a verificação.
B66: Pergunta 04: Possui débitos trabalhistas inadimplidos perante a Justiça do Trabalho?
C69: Verficamos se a empresa apresenta débitos trabalhistas no Cadastro Nacional de Pessoas Júridicas.
B71: Pergunta 05: Quanto há infrações ou embargos de ordem ambiental e/ou social, o infrator poderá firmar o TAC (Termo de Ajustamento de Conduta) para regularização. Nos últimos 5 anos, as atividades da empresa/produtor rural foram objeto de inquérito, multa, auto de infração ou TAC em decorrência de questões sociais ou ambientais?
C74: Verificamos no Sistema AGROTOUS, se há TAC, comparando com a resposta fornecida.
B76: Pergunta 06: O questionário está datado e assinado de forma adequada e anexado na plataforma de atendimento?
C79: Verificamos a conformidade do questionário quanto a data e assinatura.
B81: Pergunta 07: Foi feito o cadastro do Plano de ação na PGPC?
C84: Verificamos se as operações de Alto Risco, possuem planos cadastrados na PGPC, e validamos a conformidade dos planos.

Sheet Análise Fornecedores
F4: PAPEL DE TRABALHO RSAC (Risco Social Ambiental e Climático) | R4: Retorno
C9: Elaborado por: Gleibson Carreiro de Sousa | F9: Data Base: | G9: 46023 | K9: Periodicadade: Mensal
C10: Revisado por: | F10: Data da Revisão
C13: RESULTADO
D14: ANÁLISE 03 e 04: Análise dos fornecedores e prestadores de serviços de RSAC e enquadramento dos setores sensíveis.
D16: QUANTITATIVO | F16: RELATÓRIO DE ANÁLISE DOS FORNECEDORES E DOS SETORES SENSÍVEIS
D17: COOEPRATIVA | E17: AGÊNCIA | F17: =EOMONTH(G9,-1)+1 -> 46023 | J17: a | K17: =EOMONTH(G9,0) -> 46053
F18: Análise dos fornecedores e prestadores de serviços | K18: Análise de enquadramento nos setores sensíveis de RSAC - Limite 15%
G19: RISCO
D20: COOEPRATIVA | E20: AGÊNCIA | F20: Quantitativo de Fornecedores Cadastrados | G20: Baixo | H20: Médio | I20: Alto | J20: Qtde enquadrada na Lista Suja do (MTE) | K20: Resultado de sensibilidade | L20: situação
D21: Sicoob nova Central | E21: 1004 | F21: {=IFERROR(SUMPRODUCT((FREQUENCY(IF(For_1004!D4:D33<>"",MATCH(For_1004!D4:D33,For_1004!D4:D33,0)),ROW(For_1004!D4:D33)-ROW(For_1004!D4)+1)>0)*1),0)} -> 0 | G21: =COUNTIF(For_1004!$B$4:$B$33,'Análise Fornecedores'!G20) -> 0 | H21: =COUNTIF(For_1004!$B$4:$B$33,'Análise Fornecedores'!H20) -> 0 | I21: =COUNTIF(For_1004!$B$4:$B$33,'Análise Fornecedores'!I20) -> 0 | J21: =COUNTIF(For_1004!$J$4:$J$33,"Sim") -> 0 | K21: ='A1004'!$B$7 -> 0 | L21: ='A1004'!$D$7 -> ENQUADRADO
D22: Sicoob Agrorural | E22: 3042 | F22: {=IFERROR(SUMPRODUCT((FREQUENCY(IF(For_3042!D4:D33<>"",MATCH(For_3042!D4:D33,For_3042!D4:D33,0)),ROW(For_3042!D4:D33)-ROW(For_3042!D4)+1)>0)*1),0)} -> 0 | G22: =COUNTIF(For_3042!$B$4:$B$33,'Análise Fornecedores'!G20) -> 0 | H22: =COUNTIF(For_3042!$B$4:$B$33,'Análise Fornecedores'!H20) -> 0 | I22: =COUNTIF(For_3042!$B$4:$B$33,'Análise Fornecedores'!I20) -> 0 | J22: =COUNTIF(For_3042!$J$4:$J$33,"Sim") -> 0 | K22: ='A3042'!$B$7 -> 0.00013757353 | L22: ='A3042'!$D$7 -> ENQUADRADO
D23: Sicoob Centro-Sul | E23: 3043 | F23: {=IFERROR(SUMPRODUCT((FREQUENCY(IF(For_3043!D4:D33<>"",MATCH(For_3043!D4:D33,For_3043!D4:D33,0)),ROW(For_3043!D4:D33)-ROW(For_3043!D4)+1)>0)*1),0)} -> 0 | G23: =COUNTIF(For_3043!$B$4:$B$33,'Análise Fornecedores'!G20) -> 0 | H23: =COUNTIF(For_3043!$B$4:$B$33,'Análise Fornecedores'!H20) -> 0 | I23: =COUNTIF(For_3043!$B$4:$B$33,'Análise Fornecedores'!I20) -> 0 | J23: =COUNTIF(For_3043!$J$4:$J$33,"Sim") -> 0 | K23: ='A3043'!$B$7 -> 0 | L23: ='A3043'!$D$7 -> ENQUADRADO
D24: Sicoob Credi-Rural | E24: 3054 | F24: {=IFERROR(SUMPRODUCT((FREQUENCY(IF(For_3054!D4:D33<>"",MATCH(For_3054!D4:D33,For_3054!D4:D33,0)),ROW(For_3054!D4:D33)-ROW(For_3054!D4)+1)>0)*1),0)} -> 3 | G24: =COUNTIF(For_3054!$B$4:$B$33,'Análise Fornecedores'!G20) -> 3 | H24: =COUNTIF(For_3054!$B$4:$B$33,'Análise Fornecedores'!H20) -> 0 | I24: =COUNTIF(For_3054!$B$4:$B$33,'Análise Fornecedores'!I20) -> 0 | J24: =COUNTIF(For_3054!$J$4:$J$33,"Sim") -> 0 | K24: ='A3054'!$B$7 -> 0.00093732831 | L24: ='A3054'!$D$7 -> ENQUADRADO
D25: Siccob do Vale | E25: 3059 | F25: {=IFERROR(SUMPRODUCT((FREQUENCY(IF(For_3059!D4:D33<>"",MATCH(For_3059!D4:D33,For_3059!D4:D33,0)),ROW(For_3059!D4:D33)-ROW(For_3059!D4)+1)>0)*1),0)} -> 0 | G25: =COUNTIF(For_3059!$B$4:$B$33,'Análise Fornecedores'!G20) -> 0 | H25: =COUNTIF(For_3059!$B$4:$B$33,'Análise Fornecedores'!H20) -> 0 | I25: =COUNTIF(For_3059!$B$4:$B$33,'Análise Fornecedores'!I20) -> 0 | J25: =COUNTIF(For_3059!$J$4:$J$33,"Sim") -> 0 | K25: ='A3059'!$B$7 -> 0.0025731036 | L25: ='A3059'!$D$7 -> ENQUADRADO
D26: Sicoob Palmeiras | E26: 3060 | F26: {=IFERROR(SUMPRODUCT((FREQUENCY(IF(For_3060!D4:D33<>"",MATCH(For_3060!D4:D33,For_3060!D4:D33,0)),ROW(For_3060!D4:D33)-ROW(For_3060!D4)+1)>0)*1),0)} -> 0 | G26: =COUNTIF(For_3060!$B$4:$B$33,'Análise Fornecedores'!G20) -> 0 | H26: =COUNTIF(For_3060!$B$4:$B$33,'Análise Fornecedores'!H20) -> 0 | I26: =COUNTIF(For_3060!$B$4:$B$33,'Análise Fornecedores'!I20) -> 0 | J26: =COUNTIF(For_3060!$J$4:$J$33,"Sim") -> 0 | K26: ='A3060'!$B$7 -> 0.001130204 | L26: ='A3060'!$D$7 -> ENQUADRADO
D27: Sicoob Credijur | E27: 3233 | F27: {=IFERROR(SUMPRODUCT((FREQUENCY(IF(For_3233!D4:D33<>"",MATCH(For_3233!D4:D33,For_3233!D4:D33,0)),ROW(For_3233!D4:D33)-ROW(For_3233!D4)+1)>0)*1),0)} -> 0 | G27: =COUNTIF(For_3233!$B$4:$B$33,'Análise Fornecedores'!G20) -> 0 | H27: =COUNTIF(For_3233!$B$4:$B$33,'Análise Fornecedores'!H20) -> 0 | I27: =COUNTIF(For_3233!$B$4:$B$33,'Análise Fornecedores'!I20) -> 0 | J27: =COUNTIF(For_3233!$J$4:$J$33,"Sim") -> 0 | K27: ='A3233'!$B$7 -> 9.0400554e-05 | L27: ='A3233'!$D$7 -> ENQUADRADO
D28: Sicoob Credicapa | E28: 3261 | F28: {=IFERROR(SUMPRODUCT((FREQUENCY(IF(For_3261!D4:D33<>"",MATCH(For_3261!D4:D33,For_3261!D4:D33,0)),ROW(For_3261!D4:D33)-ROW(For_3261!D4)+1)>0)*1),0)} -> 0 | G28: =COUNTIF(For_3261!$B$4:$B$33,'Análise Fornecedores'!G20) -> 0 | H28: =COUNTIF(For_3261!$B$4:$B$33,'Análise Fornecedores'!H20) -> 0 | I28: =COUNTIF(For_3261!$B$4:$B$33,'Análise Fornecedores'!I20) -> 0 | J28: =COUNTIF(For_3261!$J$4:$J$33,"Sim") -> 0 | K28: ='A3261'!$B$7 -> 0.00021348374 | L28: ='A3261'!$D$7 -> ENQUADRADO
D29: Sicoob Tocantins | E29: 3263 | F29: {=IFERROR(SUMPRODUCT((FREQUENCY(IF(For_3263!D4:D33<>"",MATCH(For_3263!D4:D33,For_3263!D4:D33,0)),ROW(For_3263!D4:D33)-ROW(For_3263!D4)+1)>0)*1),0)} -> 0 | G29: =COUNTIF(For_3263!$B$4:$B$33,'Análise Fornecedores'!G20) -> 0 | H29: =COUNTIF(For_3263!$B$4:$B$33,'Análise Fornecedores'!H20) -> 0 | I29: =COUNTIF(For_3263!$B$4:$B$33,'Análise Fornecedores'!I20) -> 0 | J29: =COUNTIF(For_3263!$J$4:$J$33,"Sim") -> 0 | K29: ='A3263'!$B$7 -> 0.0027366321 | L29: ='A3263'!$D$7 -> ENQUADRADO
D30: Sicoob Cerrado | E30: 3320 | F30: {=IFERROR(SUMPRODUCT((FREQUENCY(IF(For_3320!D4:D33<>"",MATCH(For_3320!D4:D33,For_3320!D4:D33,0)),ROW(For_3320!D4:D33)-ROW(For_3320!D4)+1)>0)*1),0)} -> 0 | G30: =COUNTIF(For_3320!$B$4:$B$33,'Análise Fornecedores'!G20) -> 0 | H30: =COUNTIF(For_3320!$B$4:$B$33,'Análise Fornecedores'!H20) -> 0 | I30: =COUNTIF(For_3320!$B$4:$B$33,'Análise Fornecedores'!I20) -> 0 | J30: =COUNTIF(For_3320!$J$4:$J$33,"Sim") -> 0 | K30: ='A3320'!$B$7 -> 0.00016578276 | L30: ='A3320'!$D$7 -> ENQUADRADO
D31: Sicoob Emprecred | E31: 3332 | F31: {=IFERROR(SUMPRODUCT((FREQUENCY(IF(For_3332!D4:D33<>"",MATCH(For_3332!D4:D33,For_3332!D4:D33,0)),ROW(For_3332!D4:D33)-ROW(For_3332!D4)+1)>0)*1),0)} -> 0 | G31: =COUNTIF(For_3332!$B$4:$B$33,'Análise Fornecedores'!G20) -> 0 | H31: =COUNTIF(For_3332!$B$4:$B$33,'Análise Fornecedores'!H20) -> 0 | I31: =COUNTIF(For_3332!$B$4:$B$33,'Análise Fornecedores'!I20) -> 0 | J31: =COUNTIF(For_3332!$J$4:$J$33,"Sim") -> 0 | K31: ='A3332'!$B$7 -> 0.0042429209 | L31: ='A3332'!$D$7 -> ENQUADRADO
D32: Sicob Secovicred | E32: 3333 | F32: {=IFERROR(SUMPRODUCT((FREQUENCY(IF(For_3333!D4:D33<>"",MATCH(For_3333!D4:D33,For_3333!D4:D33,0)),ROW(For_3333!D4:D33)-ROW(For_3333!D4)+1)>0)*1),0)} -> 0 | G32: =COUNTIF(For_3333!$B$4:$B$33,'Análise Fornecedores'!G20) -> 0 | H32: =COUNTIF(For_3333!$B$4:$B$33,'Análise Fornecedores'!H20) -> 0 | I32: =COUNTIF(For_3333!$B$4:$B$33,'Análise Fornecedores'!I20) -> 0 | J32: =COUNTIF(For_3333!$J$4:$J$33,"Sim") -> 0 | K32: ='A3333'!$B$7 -> 0.00022086738 | L32: ='A3333'!$D$7 -> ENQUADRADO
D33: Sicoob Juriscredcelg | E33: 3348 | F33: {=IFERROR(SUMPRODUCT((FREQUENCY(IF(For_3348!D4:D33<>"",MATCH(For_3348!D4:D33,For_3348!D4:D33,0)),ROW(For_3348!D4:D33)-ROW(For_3348!D4)+1)>0)*1),0)} -> 0 | G33: =COUNTIF(For_3348!$B$4:$B$33,'Análise Fornecedores'!G20) -> 0 | H33: =COUNTIF(For_3348!$B$4:$B$33,'Análise Fornecedores'!H20) -> 0 | I33: =COUNTIF(For_3348!$B$4:$B$33,'Análise Fornecedores'!I20) -> 0 | J33: =COUNTIF(For_3348!$J$4:$J$33,"Sim") -> 0 | K33: ='A3348'!$B$7 -> 0.0021647808 | L33: ='A3348'!$D$7 -> ENQUADRADO
D34: Sicoob Credicer | E34: 3349 | F34: {=IFERROR(SUMPRODUCT((FREQUENCY(IF(For_3349!D4:D33<>"",MATCH(For_3349!D4:D33,For_3349!D4:D33,0)),ROW(For_3349!D4:D33)-ROW(For_3349!D4)+1)>0)*1),0)} -> 0 | G34: =COUNTIF(For_3349!$B$4:$B$33,'Análise Fornecedores'!G20) -> 0 | H34: =COUNTIF(For_3349!$B$4:$B$33,'Análise Fornecedores'!H20) -> 0 | I34: =COUNTIF(For_3349!$B$4:$B$33,'Análise Fornecedores'!I20) -> 0 | J34: =COUNTIF(For_3349!$J$4:$J$33,"Sim") -> 0 | K34: ='A3349'!$B$7 -> 0.00050162307 | L34: ='A3349'!$D$7 -> ENQUADRADO
D35: Sicoob Crediadag | E35: 3351 | F35: {=IFERROR(SUMPRODUCT((FREQUENCY(IF(For_3351!D4:D33<>"",MATCH(For_3351!D4:D33,For_3351!D4:D33,0)),ROW(For_3351!D4:D33)-ROW(For_3351!D4)+1)>0)*1),0)} -> 0 | G35: =COUNTIF(For_3351!$B$4:$B$33,'Análise Fornecedores'!G20) -> 0 | H35: =COUNTIF(For_3351!$B$4:$B$33,'Análise Fornecedores'!H20) -> 0 | I35: =COUNTIF(For_3351!$B$4:$B$33,'Análise Fornecedores'!I20) -> 0 | J35: =COUNTIF(For_3351!$J$4:$J$33,"Sim") -> 0 | K35: ='A3351'!$B$7 -> 0.00017615884 | L35: ='A3351'!$D$7 -> ENQUADRADO
D36: Sicoob Empresarial | E36: 3343 | F36: {=IFERROR(SUMPRODUCT((FREQUENCY(IF(For_3343!D5:D34<>"",MATCH(For_3343!D5:D34,For_3343!D5:D34,0)),ROW(For_3343!D5:D34)-ROW(For_3343!D5)+1)>0)*1),0)} -> 0 | G36: =COUNTIF(For_3343!$B$4:$B$33,'Análise Fornecedores'!G21) -> 0 | H36: =COUNTIF(For_3343!$B$4:$B$33,'Análise Fornecedores'!H21) -> 0 | I36: =COUNTIF(For_3343!$B$4:$B$33,'Análise Fornecedores'!I21) -> 0 | J36: =COUNTIF(For_3343!$J$4:$J$33,"Sim") -> 0 | K36: ='A3343'!$B$7 -> 0.00059554088 | L36: ='A3343'!$D$7 -> ENQUADRADO
D37: Sicoob Cooprem | E37: 3350 | F37: {=IFERROR(SUMPRODUCT((FREQUENCY(IF(For_3350!D6:D35<>"",MATCH(For_3350!D6:D35,For_3350!D6:D35,0)),ROW(For_3350!D6:D35)-ROW(For_3350!D6)+1)>0)*1),0)} -> 0 | G37: =COUNTIF(For_3350!$B$4:$B$33,'Análise Fornecedores'!G22) -> 0 | H37: =COUNTIF(For_3350!$B$4:$B$33,'Análise Fornecedores'!H22) -> 0 | I37: =COUNTIF(For_3350!$B$4:$B$33,'Análise Fornecedores'!I22) -> 0 | J37: =COUNTIF(For_3350!$J$4:$J$33,"Sim") -> 0 | K37: ='A3350'!$B$7 -> 0.0007974932 | L37: ='A3350'!$D$7 -> ENQUADRADO
D38: Sicoob Credi-Comigo | E38: 3336 | F38: {=IFERROR(SUMPRODUCT((FREQUENCY(IF(For_3336!D7:D36<>"",MATCH(For_3336!D7:D36,For_3336!D7:D36,0)),ROW(For_3336!D7:D36)-ROW(For_3336!D7)+1)>0)*1),0)} -> 0 | G38: =COUNTIF(For_3336!$B$4:$B$33,'Análise Fornecedores'!G23) -> 0 | H38: =COUNTIF(For_3336!$B$4:$B$33,'Análise Fornecedores'!H23) -> 0 | I38: =COUNTIF(For_3336!$B$4:$B$33,'Análise Fornecedores'!I23) -> 0 | J38: =COUNTIF(For_3336!$J$4:$J$33,"Sim") -> 0 | K38: ='A3336'!$B$7 -> 0.0037773558 | L38: ='A3336'!$D$7 -> ENQUADRADO
D39: Sicoob Credigóias | E39: 3058 | F39: {=IFERROR(SUMPRODUCT((FREQUENCY(IF(For_3058!D8:D37<>"",MATCH(For_3058!D8:D37,For_3058!D8:D37,0)),ROW(For_3058!D8:D37)-ROW(For_3058!D8)+1)>0)*1),0)} -> 0 | G39: =COUNTIF(For_3058!$B$4:$B$33,'Análise Fornecedores'!G24) -> 0 | H39: =COUNTIF(For_3058!$B$4:$B$33,'Análise Fornecedores'!H24) -> 0 | I39: =COUNTIF(For_3058!$B$4:$B$33,'Análise Fornecedores'!I24) -> 0 | J39: =COUNTIF(For_3058!$J$4:$J$33,"Sim") -> 0 | K39: ='A3058'!$B$7 -> 0 | L39: ='A3058'!$D$7 -> ENQUADRADO
D40: Sicoob Coopercred | E40: 3055 | F40: {=IFERROR(SUMPRODUCT((FREQUENCY(IF(For_3055!D9:D38<>"",MATCH(For_3055!D9:D38,For_3055!D9:D38,0)),ROW(For_3055!D9:D38)-ROW(For_3055!D9)+1)>0)*1),0)} -> 0 | G40: =COUNTIF(For_3055!$B$4:$B$33,'Análise Fornecedores'!G25) -> 0 | H40: =COUNTIF(For_3055!$B$4:$B$33,'Análise Fornecedores'!H25) -> 0 | I40: =COUNTIF(For_3055!$B$4:$B$33,'Análise Fornecedores'!I25) -> 0 | J40: =COUNTIF(For_3055!$J$4:$J$33,"Sim") -> 0 | K40: ='A3055'!$B$7 -> 2.5282051e-05 | L40: ='A3055'!$D$7 -> ENQUADRADO
D41: Sicoob Unicidades | E41: 5014 | F41: {=IFERROR(SUMPRODUCT((FREQUENCY(IF(For_5014!D10:D39<>"",MATCH(For_5014!D10:D39,For_5014!D10:D39,0)),ROW(For_5014!D10:D39)-ROW(For_5014!D10)+1)>0)*1),0)} -> 0 | G41: =COUNTIF(For_5014!$B$4:$B$33,'Análise Fornecedores'!G26) -> 0 | H41: =COUNTIF(For_5014!$B$4:$B$33,'Análise Fornecedores'!H26) -> 0 | I41: =COUNTIF(For_5014!$B$4:$B$33,'Análise Fornecedores'!I26) -> 0 | J41: =COUNTIF(For_5014!$J$4:$J$33,"Sim") -> 0 | K41: ='A5014'!$B$7 -> 0.0012800826 | L41: ='A5014'!$D$7 -> ENQUADRADO
D42: Sicoob Mineiros | E42: 3056 | F42: {=IFERROR(SUMPRODUCT((FREQUENCY(IF(For_3056!D11:D40<>"",MATCH(For_3056!D11:D40,For_3056!D11:D40,0)),ROW(For_3056!D11:D40)-ROW(For_3056!D11)+1)>0)*1),0)} -> 0 | G42: =COUNTIF(For_3056!$B$4:$B$33,'Análise Fornecedores'!G27) -> 0 | H42: =COUNTIF(For_3056!$B$4:$B$33,'Análise Fornecedores'!H27) -> 0 | I42: =COUNTIF(For_3056!$B$4:$B$33,'Análise Fornecedores'!I27) -> 0 | J42: =COUNTIF(For_3056!$J$4:$J$33,"Sim") -> 0 | K42: ='A3056'!$B$7 -> 0.00019725333 | L42: ='A3056'!$D$7 -> ENQUADRADO
D43: Sicoob Centro Oeste BR | E43: 3300 | F43: {=IFERROR(SUMPRODUCT((FREQUENCY(IF(For_3300!D12:D41<>"",MATCH(For_3300!D12:D41,For_3300!D12:D41,0)),ROW(For_3300!D12:D41)-ROW(For_3300!D12)+1)>0)*1),0)} -> 0 | G43: =COUNTIF(For_3300!$B$4:$B$33,'Análise Fornecedores'!G28) -> 0 | H43: =COUNTIF(For_3300!$B$4:$B$33,'Análise Fornecedores'!H28) -> 0 | I43: =COUNTIF(For_3300!$B$4:$B$33,'Análise Fornecedores'!I28) -> 0 | J43: =COUNTIF(For_3300!$J$4:$J$33,"Sim") -> 0 | K43: ='A3300'!$B$7 -> 0.0014007534 | L43: ='A3300'!$D$7 -> ENQUADRADO
D44: Sicoob Executivo | E44: 4001 | F44: {=IFERROR(SUMPRODUCT((FREQUENCY(IF(For_4001!D4:D33<>"",MATCH(For_4001!D4:D33,For_4001!D4:D33,0)),ROW(For_4001!D4:D33)-ROW(For_4001!D4)+1)>0)*1),0)} -> 0 | G44: =COUNTIF(For_4001!$B$4:$B$33,'Análise Fornecedores'!G20) -> 0 | H44: =COUNTIF(For_4001!$B$4:$B$33,'Análise Fornecedores'!H20) -> 0 | I44: =COUNTIF(For_4001!$B$4:$B$33,'Análise Fornecedores'!I20) -> 0 | J44: =COUNTIF(For_4001!$J$4:$J$33,"Sim") -> 0 | K44: ='A4001'!$B$7 -> 0.0035291857 | L44: ='A4001'!$D$7 -> ENQUADRADO
D45: Sicoob Judiciário | E45: 4002 | F45: {=IFERROR(SUMPRODUCT((FREQUENCY(IF(For_4002!D4:D33<>"",MATCH(For_4002!D4:D33,For_4002!D4:D33,0)),ROW(For_4002!D4:D33)-ROW(For_4002!D4)+1)>0)*1),0)} -> 0 | G45: =COUNTIF(For_4002!$B$4:$B$33,'Análise Fornecedores'!G20) -> 0 | H45: =COUNTIF(For_4002!$B$4:$B$33,'Análise Fornecedores'!H20) -> 0 | I45: =COUNTIF(For_4002!$B$4:$B$33,'Análise Fornecedores'!I20) -> 0 | J45: =COUNTIF(For_4002!$J$4:$J$33,"Sim") -> 0 | K45: ='A4002'!$B$7 -> 0.0076650377 | L45: ='A4002'!$D$7 -> ENQUADRADO
D46: Sicoob Credijustra | E46: 4041 | F46: {=IFERROR(SUMPRODUCT((FREQUENCY(IF(For_4041!D4:D33<>"",MATCH(For_4041!D4:D33,For_4041!D4:D33,0)),ROW(For_4041!D4:D33)-ROW(For_4041!D4)+1)>0)*1),0)} -> 0 | G46: =COUNTIF(For_4041!$B$4:$B$33,'Análise Fornecedores'!G20) -> 0 | H46: =COUNTIF(For_4041!$B$4:$B$33,'Análise Fornecedores'!H20) -> 0 | I46: =COUNTIF(For_4041!$B$4:$B$33,'Análise Fornecedores'!I20) -> 0 | J46: =COUNTIF(For_4041!$J$4:$J$33,"Sim") -> 0 | K46: ='A4041'!$B$7 -> 0.00062994522 | L46: ='A4041'!$D$7 -> ENQUADRADO
D47: Sicoob Credibrasília | E47: 4155 | F47: {=IFERROR(SUMPRODUCT((FREQUENCY(IF(For_4155!D4:D33<>"",MATCH(For_4155!D4:D33,For_4155!D4:D33,0)),ROW(For_4155!D4:D33)-ROW(For_4155!D4)+1)>0)*1),0)} -> 0 | G47: =COUNTIF(For_4155!$B$4:$B$33,'Análise Fornecedores'!G20) -> 0 | H47: =COUNTIF(For_4155!$B$4:$B$33,'Análise Fornecedores'!H20) -> 0 | I47: =COUNTIF(For_4155!$B$4:$B$33,'Análise Fornecedores'!I20) -> 0 | J47: =COUNTIF(For_4155!$J$4:$J$33,"Sim") -> 0 | K47: ='A4155'!$B$7 -> 9.5332976e-05 | L47: ='A4155'!$D$7 -> ENQUADRADO
D48: Sicoob Crediembrapa | E48: 4198 | F48: {=IFERROR(SUMPRODUCT((FREQUENCY(IF(For_4198!D4:D33<>"",MATCH(For_4198!D4:D33,For_4198!D4:D33,0)),ROW(For_4198!D4:D33)-ROW(For_4198!D4)+1)>0)*1),0)} -> 0 | G48: =COUNTIF(For_4198!$B$4:$B$33,'Análise Fornecedores'!G20) -> 0 | H48: =COUNTIF(For_4198!$B$4:$B$33,'Análise Fornecedores'!H20) -> 0 | I48: =COUNTIF(For_4198!$B$4:$B$33,'Análise Fornecedores'!I20) -> 0 | J48: =COUNTIF(For_4198!$J$4:$J$33,"Sim") -> 0 | K48: ='A4198'!$B$7 -> 0.00096319199 | L48: ='A4198'!$D$7 -> ENQUADRADO
D49: Sicoob Credfaz | E49: 4221 | F49: {=IFERROR(SUMPRODUCT((FREQUENCY(IF(For_4221!D4:D33<>"",MATCH(For_4221!D4:D33,For_4221!D4:D33,0)),ROW(For_4221!D4:D33)-ROW(For_4221!D4)+1)>0)*1),0)} -> 0 | G49: =COUNTIF(For_4221!$B$4:$B$33,'Análise Fornecedores'!G20) -> 0 | H49: =COUNTIF(For_4221!$B$4:$B$33,'Análise Fornecedores'!H20) -> 0 | I49: =COUNTIF(For_4221!$B$4:$B$33,'Análise Fornecedores'!I20) -> 0 | J49: =COUNTIF(For_4221!$J$4:$J$33,"Sim") -> 0 | K49: ='A4221'!$B$7 -> 4.2772302e-05 | L49: ='A4221'!$D$7 -> ENQUADRADO
D50: Sicoob Cooperplan Credsef | E50: 4278 | F50: {=IFERROR(SUMPRODUCT((FREQUENCY(IF(For_4278!D4:D33<>"",MATCH(For_4278!D4:D33,For_4278!D4:D33,0)),ROW(For_4278!D4:D33)-ROW(For_4278!D4)+1)>0)*1),0)} -> 0 | G50: =COUNTIF(For_4278!$B$4:$B$33,'Análise Fornecedores'!G20) -> 0 | H50: =COUNTIF(For_4278!$B$4:$B$33,'Análise Fornecedores'!H20) -> 0 | I50: =COUNTIF(For_4278!$B$4:$B$33,'Análise Fornecedores'!I20) -> 0 | J50: =COUNTIF(For_4278!$J$4:$J$33,"Sim") -> 0 | K50: ='A4278'!$B$7 -> 0 | L50: ='A4278'!$D$7 -> ENQUADRADO
D51: Sicoob Dfmil | E51: 4332 | F51: {=IFERROR(SUMPRODUCT((FREQUENCY(IF(For_4332!D4:D33<>"",MATCH(For_4332!D4:D33,For_4332!D4:D33,0)),ROW(For_4332!D4:D33)-ROW(For_4332!D4)+1)>0)*1),0)} -> 0 | G51: =COUNTIF(For_4332!$B$4:$B$33,'Análise Fornecedores'!G20) -> 0 | H51: =COUNTIF(For_4332!$B$4:$B$33,'Análise Fornecedores'!H20) -> 0 | I51: =COUNTIF(For_4332!$B$4:$B$33,'Análise Fornecedores'!I20) -> 0 | J51: =COUNTIF(For_4332!$J$4:$J$33,"Sim") -> 0 | K51: ='A4332'!$B$7 -> 0.0021036255 | L51: ='A4332'!$D$7 -> ENQUADRADO
D52: Sicoob Empresarial | E52: 4364 | F52: {=IFERROR(SUMPRODUCT((FREQUENCY(IF(For_4364!D4:D33<>"",MATCH(For_4364!D4:D33,For_4364!D4:D33,0)),ROW(For_4364!D4:D33)-ROW(For_4364!D4)+1)>0)*1),0)} -> 0 | G52: =COUNTIF(For_4364!$B$4:$B$33,'Análise Fornecedores'!G20) -> 0 | H52: =COUNTIF(For_4364!$B$4:$B$33,'Análise Fornecedores'!H20) -> 0 | I52: =COUNTIF(For_4364!$B$4:$B$33,'Análise Fornecedores'!I20) -> 0 | J52: =COUNTIF(For_4364!$J$4:$J$33,"Sim") -> 0 | K52: ='A4364'!$B$7 -> 0.00017551024 | L52: ='A4364'!$D$7 -> ENQUADRADO

Sheet Cooperados Alto Risco
F4: PAPEL DE TRABALHO RSAC (Risco Social Ambiental e Climático) | O4: Retorno
C9: Elaborado por: Gleibson Carreiro de Sousa | F9: Data Base: | G9: 46023 | H9: Periodicadade: Mensal
C10: Revisado por: | F10: Data da Revisão
C13: RESULTADO
D15: ANÁLISE 05: Relatório de Alto Risco por Cooperativa - Quantitativo | S15: Quantidade de Planos de Ações PENDENTES de Cadastro
T16: =_xlfn.XLOOKUP(S18,D20:D51,I20:I51," ",0) -> 5
D17: CCONTROLE DOS PLANOS DE AÇÕES | F17: PGPC | S17: Escolha a cooperativa
F18: =EOMONTH(G9,-1)+1 -> 46023 | G18: a | H18: =EOMONTH(G9,0) -> 46053 | N18: Possibilidades | S18: TODAS as singulares | T18: Sicoob Agrorural | U18: Sicoob Centro-Sul | V18: Sicoob Credi-Rural | W18: Siccob do Vale | X18: Sicoob Palmeiras | Y18: Sicoob Credijur | Z18: Sicoob Credicapa | AA18: Sicoob Tocantins | AB18: Sicoob Cerrado | AC18: Sicoob Emprecred | AD18: Sicob Secovicred | AE18: Sicoob Juriscredcelg | AF18: Sicoob Credicer | AG18: Sicoob Crediadag | AH18: Sicoob Executivo | AI18: Sicoob Judiciário | AJ18: Sicoob Credijustra | AK18: Sicoob Credibrasília | AL18: Sicoob Crediembrapa | AM18: Sicoob Credfaz | AN18: Sicoob Cooperplan Credsef | AO18: Sicoob Dfmil | AP18: Sicoob Empresarial | AQ18: TODAS as singulares
D19: COOEPRATIVA | E19: AGÊNCIA | F19: ALTO RISCO | G19: % de planos de ações cadastrados na PGPC | H19: Quant. Planos Cadastrados | I19: Quant. de PLANOS PENDENTES DE CADASTRO | N19: Possíveis Causas do Plano de ação | T19: 3042 | U19: 3043 | V19: 3054 | W19: 3059 | X19: 3060 | Y19: 3233 | Z19: 3261 | AA19: 3263 | AB19: 3320 | AC19: 3332 | AD19: 3333 | AE19: 3348 | AF19: 3349 | AG19: 3351 | AH19: 4001 | AI19: 4002 | AJ19: 4041 | AK19: 4155 | AL19: 4198 | AM19: 4221 | AN19: 4278 | AO19: 4332 | AP19: 4364
D20: Sicoob Agrorural | E20: 3042 | F20: ='Risco por Cooperativa'!H21 -> 1 | G20: =IFERROR((COUNTIF('A3042'!$AL:$AL,"Sim"))/F20,0) -> 1 | H20: =COUNTIF('A3042'!$AL:$AL,"Sim") -> 1 | I20: =COUNTIF('A3042'!AM:AM,"Verificar") -> 0 | N20: Embargo | S20: =HLOOKUP($S$18,$T$18:$AQ$28,3,0) -> 0 | T20: =COUNTIFS('A3042'!$AK:$AK,'Cooperados Alto Risco'!N20) -> 0 | U20: =COUNTIFS('A3043'!$AK:$AK,'Cooperados Alto Risco'!N20) -> 0 | V20: =COUNTIFS('A3054'!$AK:$AK,'Cooperados Alto Risco'!N20) -> 0 | W20: =COUNTIFS('A3059'!$AK:$AK,'Cooperados Alto Risco'!N20) -> 0 | X20: =COUNTIFS('A3060'!$AK:$AK,'Cooperados Alto Risco'!N20) -> 0 | Y20: =COUNTIFS('A3233'!$AK:$AK,'Cooperados Alto Risco'!N20) -> 0 | Z20: =COUNTIFS('A3261'!$AK:$AK,'Cooperados Alto Risco'!N20) -> 0 | AA20: =COUNTIFS('A3263'!$AK:$AK,'Cooperados Alto Risco'!N20) -> 0 | AB20: =COUNTIFS('A3320'!$AK:$AK,'Cooperados Alto Risco'!N20) -> 0 | AC20: =COUNTIFS('A3332'!$AK:$AK,'Cooperados Alto Risco'!N20) -> 0 | AD20: =COUNTIFS('A3333'!$AK:$AK,'Cooperados Alto Risco'!N20) -> 0 | AE20: =COUNTIFS('A3348'!$AK:$AK,'Cooperados Alto Risco'!N20) -> 0 | AF20: =COUNTIFS('A3349'!$AK:$AK,'Cooperados Alto Risco'!N20) -> 0 | AG20: =COUNTIFS('A3351'!$AK:$AK,'Cooperados Alto Risco'!N20) -> 0 | AH20: =COUNTIFS('A4001'!$AK:$AK,'Cooperados Alto Risco'!N20) -> 0 | AI20: =COUNTIFS('A4002'!$AK:$AK,'Cooperados Alto Risco'!N20) -> 0 | AJ20: =COUNTIFS('A4041'!$AK:$AK,'Cooperados Alto Risco'!N20) -> 0 | AK20: =COUNTIFS('A4155'!$AK:$AK,'Cooperados Alto Risco'!N20) -> 0 | AL20: =COUNTIFS('A4198'!$AK:$AK,'Cooperados Alto Risco'!N20) -> 0 | AM20: =COUNTIFS('A4221'!$AK:$AK,'Cooperados Alto Risco'!N20) -> 0 | AN20: =COUNTIFS('A4278'!$AK:$AK,'Cooperados Alto Risco'!N20) -> 0 | AO20: =COUNTIFS('A4332'!$AK:$AK,'Cooperados Alto Risco'!N20) -> 0 | AP20: =COUNTIFS('A4364'!$AK:$AK,'Cooperados Alto Risco'!N20) -> 0 | AQ20: =SUM(T20:AP20) -> 0
D21: Sicoob Centro-Sul | E21: 3043 | F21: ='Risco por Cooperativa'!H22 -> 2 | G21: =IFERROR((COUNTIF('A3043'!$AL:$AL,"Sim"))/F21,0) -> 1 | H21: =COUNTIF('A3043'!$AL:$AL,"Sim") -> 2 | I21: =COUNTIF('A3043'!AM:AM,"Verificar") -> 0 | N21: Contraparte Conectada | S21: =HLOOKUP($S$18,$T$18:$AQ$28,4,0) -> 0 | T21: =COUNTIFS('A3042'!$AK:$AK,'Cooperados Alto Risco'!N21) -> 0 | U21: =COUNTIFS('A3043'!$AK:$AK,'Cooperados Alto Risco'!N21) -> 0 | V21: =COUNTIFS('A3054'!$AK:$AK,'Cooperados Alto Risco'!N21) -> 0 | W21: =COUNTIFS('A3059'!$AK:$AK,'Cooperados Alto Risco'!N21) -> 0 | X21: =COUNTIFS('A3060'!$AK:$AK,'Cooperados Alto Risco'!N21) -> 0 | Y21: =COUNTIFS('A3233'!$AK:$AK,'Cooperados Alto Risco'!N21) -> 0 | Z21: =COUNTIFS('A3261'!$AK:$AK,'Cooperados Alto Risco'!N21) -> 0 | AA21: =COUNTIFS('A3263'!$AK:$AK,'Cooperados Alto Risco'!N21) -> 0 | AB21: =COUNTIFS('A3320'!$AK:$AK,'Cooperados Alto Risco'!N21) -> 0 | AC21: =COUNTIFS('A3332'!$AK:$AK,'Cooperados Alto Risco'!N21) -> 0 | AD21: =COUNTIFS('A3333'!$AK:$AK,'Cooperados Alto Risco'!N21) -> 0 | AE21: =COUNTIFS('A3348'!$AK:$AK,'Cooperados Alto Risco'!N21) -> 0 | AF21: =COUNTIFS('A3349'!$AK:$AK,'Cooperados Alto Risco'!N21) -> 0 | AG21: =COUNTIFS('A3351'!$AK:$AK,'Cooperados Alto Risco'!N21) -> 0 | AH21: =COUNTIFS('A4001'!$AK:$AK,'Cooperados Alto Risco'!N21) -> 0 | AI21: =COUNTIFS('A4002'!$AK:$AK,'Cooperados Alto Risco'!N21) -> 0 | AJ21: =COUNTIFS('A4041'!$AK:$AK,'Cooperados Alto Risco'!N21) -> 0 | AK21: =COUNTIFS('A4155'!$AK:$AK,'Cooperados Alto Risco'!N21) -> 0 | AL21: =COUNTIFS('A4198'!$AK:$AK,'Cooperados Alto Risco'!N21) -> 0 | AM21: =COUNTIFS('A4221'!$AK:$AK,'Cooperados Alto Risco'!N21) -> 0 | AN21: =COUNTIFS('A4278'!$AK:$AK,'Cooperados Alto Risco'!N21) -> 0 | AO21: =COUNTIFS('A4332'!$AK:$AK,'Cooperados Alto Risco'!N21) -> 0 | AP21: =COUNTIFS('A4364'!$AK:$AK,'Cooperados Alto Risco'!N21) -> 0 | AQ21: =SUM(T21:AP21) -> 0
D22: Sicoob Credi-Rural | E22: 3054 | F22: ='Risco por Cooperativa'!H23 -> 9 | G22: =IFERROR((COUNTIF('A3054'!$AL:$AL,"Sim"))/F22,0) -> 0.88888889 | H22: =COUNTIF('A3054'!$AL:$AL,"Sim") -> 8 | I22: =COUNTIF('A3054'!AM:AM,"Verificar") -> 1 | N22: Licenciamento Ambiental | S22: =HLOOKUP($S$18,$T$18:$AQ$28,5,0) -> 0 | T22: =COUNTIFS('A3042'!$AK:$AK,'Cooperados Alto Risco'!N22) -> 0 | U22: =COUNTIFS('A3043'!$AK:$AK,'Cooperados Alto Risco'!N22) -> 0 | V22: =COUNTIFS('A3054'!$AK:$AK,'Cooperados Alto Risco'!N22) -> 0 | W22: =COUNTIFS('A3059'!$AK:$AK,'Cooperados Alto Risco'!N22) -> 0 | X22: =COUNTIFS('A3060'!$AK:$AK,'Cooperados Alto Risco'!N22) -> 0 | Y22: =COUNTIFS('A3233'!$AK:$AK,'Cooperados Alto Risco'!N22) -> 0 | Z22: =COUNTIFS('A3261'!$AK:$AK,'Cooperados Alto Risco'!N22) -> 0 | AA22: =COUNTIFS('A3263'!$AK:$AK,'Cooperados Alto Risco'!N22) -> 0 | AB22: =COUNTIFS('A3320'!$AK:$AK,'Cooperados Alto Risco'!N22) -> 0 | AC22: =COUNTIFS('A3332'!$AK:$AK,'Cooperados Alto Risco'!N22) -> 0 | AD22: =COUNTIFS('A3333'!$AK:$AK,'Cooperados Alto Risco'!N22) -> 0 | AE22: =COUNTIFS('A3348'!$AK:$AK,'Cooperados Alto Risco'!N22) -> 0 | AF22: =COUNTIFS('A3349'!$AK:$AK,'Cooperados Alto Risco'!N22) -> 0 | AG22: =COUNTIFS('A3351'!$AK:$AK,'Cooperados Alto Risco'!N22) -> 0 | AH22: =COUNTIFS('A4001'!$AK:$AK,'Cooperados Alto Risco'!N22) -> 0 | AI22: =COUNTIFS('A4002'!$AK:$AK,'Cooperados Alto Risco'!N22) -> 0 | AJ22: =COUNTIFS('A4041'!$AK:$AK,'Cooperados Alto Risco'!N22) -> 0 | AK22: =COUNTIFS('A4155'!$AK:$AK,'Cooperados Alto Risco'!N22) -> 0 | AL22: =COUNTIFS('A4198'!$AK:$AK,'Cooperados Alto Risco'!N22) -> 0 | AM22: =COUNTIFS('A4221'!$AK:$AK,'Cooperados Alto Risco'!N22) -> 0 | AN22: =COUNTIFS('A4278'!$AK:$AK,'Cooperados Alto Risco'!N22) -> 0 | AO22: =COUNTIFS('A4332'!$AK:$AK,'Cooperados Alto Risco'!N22) -> 0 | AP22: =COUNTIFS('A4364'!$AK:$AK,'Cooperados Alto Risco'!N22) -> 0 | AQ22: =SUM(T22:AP22) -> 0
D23: Siccob do Vale | E23: 3059 | F23: ='Risco por Cooperativa'!H24 -> 1 | G23: =IFERROR((COUNTIF('A3059'!$AL:$AL,"Sim"))/F23,0) -> 1 | H23: =COUNTIF('A3059'!$AL:$AL,"Sim") -> 1 | I23: =COUNTIF('A3059'!AM:AM,"Verificar") -> 0 | N23: Trabalho Escravo | S23: =HLOOKUP($S$18,$T$18:$AQ$28,6,0) -> 0 | T23: =COUNTIFS('A3042'!$AK:$AK,'Cooperados Alto Risco'!N23) -> 0 | U23: =COUNTIFS('A3043'!$AK:$AK,'Cooperados Alto Risco'!N23) -> 0 | V23: =COUNTIFS('A3054'!$AK:$AK,'Cooperados Alto Risco'!N23) -> 0 | W23: =COUNTIFS('A3059'!$AK:$AK,'Cooperados Alto Risco'!N23) -> 0 | X23: =COUNTIFS('A3060'!$AK:$AK,'Cooperados Alto Risco'!N23) -> 0 | Y23: =COUNTIFS('A3233'!$AK:$AK,'Cooperados Alto Risco'!N23) -> 0 | Z23: =COUNTIFS('A3261'!$AK:$AK,'Cooperados Alto Risco'!N23) -> 0 | AA23: =COUNTIFS('A3263'!$AK:$AK,'Cooperados Alto Risco'!N23) -> 0 | AB23: =COUNTIFS('A3320'!$AK:$AK,'Cooperados Alto Risco'!N23) -> 0 | AC23: =COUNTIFS('A3332'!$AK:$AK,'Cooperados Alto Risco'!N23) -> 0 | AD23: =COUNTIFS('A3333'!$AK:$AK,'Cooperados Alto Risco'!N23) -> 0 | AE23: =COUNTIFS('A3348'!$AK:$AK,'Cooperados Alto Risco'!N23) -> 0 | AF23: =COUNTIFS('A3349'!$AK:$AK,'Cooperados Alto Risco'!N23) -> 0 | AG23: =COUNTIFS('A3351'!$AK:$AK,'Cooperados Alto Risco'!N23) -> 0 | AH23: =COUNTIFS('A4001'!$AK:$AK,'Cooperados Alto Risco'!N23) -> 0 | AI23: =COUNTIFS('A4002'!$AK:$AK,'Cooperados Alto Risco'!N23) -> 0 | AJ23: =COUNTIFS('A4041'!$AK:$AK,'Cooperados Alto Risco'!N23) -> 0 | AK23: =COUNTIFS('A4155'!$AK:$AK,'Cooperados Alto Risco'!N23) -> 0 | AL23: =COUNTIFS('A4198'!$AK:$AK,'Cooperados Alto Risco'!N23) -> 0 | AM23: =COUNTIFS('A4221'!$AK:$AK,'Cooperados Alto Risco'!N23) -> 0 | AN23: =COUNTIFS('A4278'!$AK:$AK,'Cooperados Alto Risco'!N23) -> 0 | AO23: =COUNTIFS('A4332'!$AK:$AK,'Cooperados Alto Risco'!N23) -> 0 | AP23: =COUNTIFS('A4364'!$AK:$AK,'Cooperados Alto Risco'!N23) -> 0 | AQ23: =SUM(T23:AP23) -> 0
D24: Sicoob Palmeiras | E24: 3060 | F24: ='Risco por Cooperativa'!H25 -> 1 | G24: =IFERROR((COUNTIF('A3060'!$AL:$AL,"Sim"))/F24,0) -> 1 | H24: =COUNTIF('A3060'!$AL:$AL,"Sim") -> 1 | I24: =COUNTIF('A3060'!AM:AM,"Verificar") -> 0 | S24: =HLOOKUP($S$18,$T$18:$AQ$28,7,0) -> 0 | T24: =COUNTIFS('A3042'!$AK:$AK,'Cooperados Alto Risco'!N24) -> 0 | U24: =COUNTIFS('A3043'!$AK:$AK,'Cooperados Alto Risco'!N24) -> 0 | V24: =COUNTIFS('A3054'!$AK:$AK,'Cooperados Alto Risco'!N24) -> 0 | W24: =COUNTIFS('A3059'!$AK:$AK,'Cooperados Alto Risco'!N24) -> 0 | X24: =COUNTIFS('A3060'!$AK:$AK,'Cooperados Alto Risco'!N24) -> 0 | Y24: =COUNTIFS('A3233'!$AK:$AK,'Cooperados Alto Risco'!N24) -> 0 | Z24: =COUNTIFS('A3261'!$AK:$AK,'Cooperados Alto Risco'!N24) -> 0 | AA24: =COUNTIFS('A3263'!$AK:$AK,'Cooperados Alto Risco'!N24) -> 0 | AB24: =COUNTIFS('A3320'!$AK:$AK,'Cooperados Alto Risco'!N24) -> 0 | AC24: =COUNTIFS('A3332'!$AK:$AK,'Cooperados Alto Risco'!N24) -> 0 | AD24: =COUNTIFS('A3333'!$AK:$AK,'Cooperados Alto Risco'!N24) -> 0 | AE24: =COUNTIFS('A3348'!$AK:$AK,'Cooperados Alto Risco'!N24) -> 0 | AF24: =COUNTIFS('A3349'!$AK:$AK,'Cooperados Alto Risco'!N24) -> 0 | AG24: =COUNTIFS('A3351'!$AK:$AK,'Cooperados Alto Risco'!N24) -> 0 | AH24: =COUNTIFS('A4001'!$AK:$AK,'Cooperados Alto Risco'!N24) -> 0 | AI24: =COUNTIFS('A4002'!$AK:$AK,'Cooperados Alto Risco'!N24) -> 0 | AJ24: =COUNTIFS('A4041'!$AK:$AK,'Cooperados Alto Risco'!N24) -> 0 | AK24: =COUNTIFS('A4155'!$AK:$AK,'Cooperados Alto Risco'!N24) -> 0 | AL24: =COUNTIFS('A4198'!$AK:$AK,'Cooperados Alto Risco'!N24) -> 0 | AM24: =COUNTIFS('A4221'!$AK:$AK,'Cooperados Alto Risco'!N24) -> 0 | AN24: =COUNTIFS('A4278'!$AK:$AK,'Cooperados Alto Risco'!N24) -> 0 | AO24: =COUNTIFS('A4332'!$AK:$AK,'Cooperados Alto Risco'!N24) -> 0 | AP24: =COUNTIFS('A4364'!$AK:$AK,'Cooperados Alto Risco'!N24) -> 0 | AQ24: =SUM(T24:AP24) -> 0
D25: Sicoob Credijur | E25: 3233 | F25: ='Risco por Cooperativa'!H26 -> 0 | G25: =IFERROR((COUNTIF('A3233'!$AL:$AL,"Sim"))/F25,0) -> 0 | H25: =COUNTIF('A3233'!$AL:$AL,"Sim") -> 0 | I25: =COUNTIF('A3233'!AM:AM,"Verificar") -> 0 | S25: =HLOOKUP($S$18,$T$18:$AQ$28,8,0) -> 0 | T25: =COUNTIFS('A3042'!$AK:$AK,'Cooperados Alto Risco'!N25) -> 0 | U25: =COUNTIFS('A3043'!$AK:$AK,'Cooperados Alto Risco'!N25) -> 0 | V25: =COUNTIFS('A3054'!$AK:$AK,'Cooperados Alto Risco'!N25) -> 0 | W25: =COUNTIFS('A3059'!$AK:$AK,'Cooperados Alto Risco'!N25) -> 0 | X25: =COUNTIFS('A3060'!$AK:$AK,'Cooperados Alto Risco'!N25) -> 0 | Y25: =COUNTIFS('A3233'!$AK:$AK,'Cooperados Alto Risco'!N25) -> 0 | Z25: =COUNTIFS('A3261'!$AK:$AK,'Cooperados Alto Risco'!N25) -> 0 | AA25: =COUNTIFS('A3263'!$AK:$AK,'Cooperados Alto Risco'!N25) -> 0 | AB25: =COUNTIFS('A3320'!$AK:$AK,'Cooperados Alto Risco'!N25) -> 0 | AC25: =COUNTIFS('A3332'!$AK:$AK,'Cooperados Alto Risco'!N25) -> 0 | AD25: =COUNTIFS('A3333'!$AK:$AK,'Cooperados Alto Risco'!N25) -> 0 | AE25: =COUNTIFS('A3348'!$AK:$AK,'Cooperados Alto Risco'!N25) -> 0 | AF25: =COUNTIFS('A3349'!$AK:$AK,'Cooperados Alto Risco'!N25) -> 0 | AG25: =COUNTIFS('A3351'!$AK:$AK,'Cooperados Alto Risco'!N25) -> 0 | AH25: =COUNTIFS('A4001'!$AK:$AK,'Cooperados Alto Risco'!N25) -> 0 | AI25: =COUNTIFS('A4002'!$AK:$AK,'Cooperados Alto Risco'!N25) -> 0 | AJ25: =COUNTIFS('A4041'!$AK:$AK,'Cooperados Alto Risco'!N25) -> 0 | AK25: =COUNTIFS('A4155'!$AK:$AK,'Cooperados Alto Risco'!N25) -> 0 | AL25: =COUNTIFS('A4198'!$AK:$AK,'Cooperados Alto Risco'!N25) -> 0 | AM25: =COUNTIFS('A4221'!$AK:$AK,'Cooperados Alto Risco'!N25) -> 0 | AN25: =COUNTIFS('A4278'!$AK:$AK,'Cooperados Alto Risco'!N25) -> 0 | AO25: =COUNTIFS('A4332'!$AK:$AK,'Cooperados Alto Risco'!N25) -> 0 | AP25: =COUNTIFS('A4364'!$AK:$AK,'Cooperados Alto Risco'!N25) -> 0 | AQ25: =SUM(T25:AP25) -> 0
D26: Sicoob Credicapa | E26: 3261 | F26: ='Risco por Cooperativa'!H27 -> 1 | G26: =IFERROR((COUNTIF('A3261'!$AL:$AL,"Sim"))/F26,0) -> 1 | H26: =COUNTIF('A3261'!$AL:$AL,"Sim") -> 1 | I26: =COUNTIF('A3261'!AM:AM,"Verificar") -> 0 | S26: =HLOOKUP($S$18,$T$18:$AQ$28,9,0) -> 0 | T26: =COUNTIFS('A3042'!$AK:$AK,'Cooperados Alto Risco'!N26) -> 0 | U26: =COUNTIFS('A3043'!$AK:$AK,'Cooperados Alto Risco'!N26) -> 0 | V26: =COUNTIFS('A3054'!$AK:$AK,'Cooperados Alto Risco'!N26) -> 0 | W26: =COUNTIFS('A3059'!$AK:$AK,'Cooperados Alto Risco'!N26) -> 0 | X26: =COUNTIFS('A3060'!$AK:$AK,'Cooperados Alto Risco'!N26) -> 0 | Y26: =COUNTIFS('A3233'!$AK:$AK,'Cooperados Alto Risco'!N26) -> 0 | Z26: =COUNTIFS('A3261'!$AK:$AK,'Cooperados Alto Risco'!N26) -> 0 | AA26: =COUNTIFS('A3263'!$AK:$AK,'Cooperados Alto Risco'!N26) -> 0 | AB26: =COUNTIFS('A3320'!$AK:$AK,'Cooperados Alto Risco'!N26) -> 0 | AC26: =COUNTIFS('A3332'!$AK:$AK,'Cooperados Alto Risco'!N26) -> 0 | AD26: =COUNTIFS('A3333'!$AK:$AK,'Cooperados Alto Risco'!N26) -> 0 | AE26: =COUNTIFS('A3348'!$AK:$AK,'Cooperados Alto Risco'!N26) -> 0 | AF26: =COUNTIFS('A3349'!$AK:$AK,'Cooperados Alto Risco'!N26) -> 0 | AG26: =COUNTIFS('A3351'!$AK:$AK,'Cooperados Alto Risco'!N26) -> 0 | AH26: =COUNTIFS('A4001'!$AK:$AK,'Cooperados Alto Risco'!N26) -> 0 | AI26: =COUNTIFS('A4002'!$AK:$AK,'Cooperados Alto Risco'!N26) -> 0 | AJ26: =COUNTIFS('A4041'!$AK:$AK,'Cooperados Alto Risco'!N26) -> 0 | AK26: =COUNTIFS('A4155'!$AK:$AK,'Cooperados Alto Risco'!N26) -> 0 | AL26: =COUNTIFS('A4198'!$AK:$AK,'Cooperados Alto Risco'!N26) -> 0 | AM26: =COUNTIFS('A4221'!$AK:$AK,'Cooperados Alto Risco'!N26) -> 0 | AN26: =COUNTIFS('A4278'!$AK:$AK,'Cooperados Alto Risco'!N26) -> 0 | AO26: =COUNTIFS('A4332'!$AK:$AK,'Cooperados Alto Risco'!N26) -> 0 | AP26: =COUNTIFS('A4364'!$AK:$AK,'Cooperados Alto Risco'!N26) -> 0 | AQ26: =SUM(T26:AP26) -> 0
D27: Sicoob Tocantins | E27: 3263 | F27: ='Risco por Cooperativa'!H28 -> 2 | G27: =IFERROR((COUNTIF('A3263'!$AL:$AL,"Sim"))/F27,0) -> 0.5 | H27: =COUNTIF('A3263'!$AL:$AL,"Sim") -> 1 | I27: =COUNTIF('A3263'!AM:AM,"Verificar") -> 1 | T27: =COUNTIFS('A3042'!$AK:$AK,'Cooperados Alto Risco'!N27) -> 0 | U27: =COUNTIFS('A3043'!$AK:$AK,'Cooperados Alto Risco'!N27) -> 0 | V27: =COUNTIFS('A3054'!$AK:$AK,'Cooperados Alto Risco'!N27) -> 0 | W27: =COUNTIFS('A3059'!$AK:$AK,'Cooperados Alto Risco'!N27) -> 0 | X27: =COUNTIFS('A3060'!$AK:$AK,'Cooperados Alto Risco'!N27) -> 0 | Y27: =COUNTIFS('A3233'!$AK:$AK,'Cooperados Alto Risco'!N27) -> 0 | Z27: =COUNTIFS('A3261'!$AK:$AK,'Cooperados Alto Risco'!N27) -> 0 | AA27: =COUNTIFS('A3263'!$AK:$AK,'Cooperados Alto Risco'!N27) -> 0 | AB27: =COUNTIFS('A3320'!$AK:$AK,'Cooperados Alto Risco'!N27) -> 0 | AC27: =COUNTIFS('A3332'!$AK:$AK,'Cooperados Alto Risco'!N27) -> 0 | AD27: =COUNTIFS('A3333'!$AK:$AK,'Cooperados Alto Risco'!N27) -> 0 | AE27: =COUNTIFS('A3348'!$AK:$AK,'Cooperados Alto Risco'!N27) -> 0 | AF27: =COUNTIFS('A3349'!$AK:$AK,'Cooperados Alto Risco'!N27) -> 0 | AG27: =COUNTIFS('A3351'!$AK:$AK,'Cooperados Alto Risco'!N27) -> 0 | AH27: =COUNTIFS('A4001'!$AK:$AK,'Cooperados Alto Risco'!N27) -> 0 | AI27: =COUNTIFS('A4002'!$AK:$AK,'Cooperados Alto Risco'!N27) -> 0 | AJ27: =COUNTIFS('A4041'!$AK:$AK,'Cooperados Alto Risco'!N27) -> 0 | AK27: =COUNTIFS('A4155'!$AK:$AK,'Cooperados Alto Risco'!N27) -> 0 | AL27: =COUNTIFS('A4198'!$AK:$AK,'Cooperados Alto Risco'!N27) -> 0 | AM27: =COUNTIFS('A4221'!$AK:$AK,'Cooperados Alto Risco'!N27) -> 0 | AN27: =COUNTIFS('A4278'!$AK:$AK,'Cooperados Alto Risco'!N27) -> 0 | AO27: =COUNTIFS('A4332'!$AK:$AK,'Cooperados Alto Risco'!N27) -> 0 | AP27: =COUNTIFS('A4364'!$AK:$AK,'Cooperados Alto Risco'!N27) -> 0 | AQ27: =SUM(T27:AP27) -> 0
D28: Sicoob Cerrado | E28: 3320 | F28: ='Risco por Cooperativa'!H29 -> 2 | G28: =IFERROR((COUNTIF('A3320'!$AL:$AL,"Sim"))/F28,0) -> 0.5 | H28: =COUNTIF('A3320'!$AL:$AL,"Sim") -> 1 | I28: =COUNTIF('A3320'!AM:AM,"Verificar") -> 1 | S28: =SUM(S20:S27) -> 0 | T28: =IFERROR(SUM(T20:T27),0) -> 0 | U28: =IFERROR(SUM(U20:U27),0) -> 0 | V28: =IFERROR(SUM(V20:V27),0) -> 0 | W28: =IFERROR(SUM(W20:W27),0) -> 0 | X28: =IFERROR(SUM(X20:X27),0) -> 0 | Y28: =IFERROR(SUM(Y20:Y27),0) -> 0 | Z28: =IFERROR(SUM(Z20:Z27),0) -> 0 | AA28: =IFERROR(SUM(AA20:AA27),0) -> 0 | ... AQ28: =IFERROR(SUM(AQ20:AQ27),0) -> 0
D29: Sicoob Emprecred | E29: 3332 | F29: ='Risco por Cooperativa'!H30 -> 4 | G29: =IFERROR((COUNTIF('A3332'!$AL:$AL,"Sim"))/F29,0) -> 1 | H29: =COUNTIF('A3332'!$AL:$AL,"Sim") -> 4 | I29: =COUNTIF('A3332'!AM:AM,"Verificar") -> 0
D30: Sicob Secovicred | E30: 3333 | F30: ='Risco por Cooperativa'!H31 -> 4 | G30: =IFERROR((COUNTIF('A3333'!$AL:$AL,"Sim"))/F30,0) -> 1 | H30: =COUNTIF('A3333'!$AL:$AL,"Sim") -> 4 | I30: =COUNTIF('A3333'!AM:AM,"Verificar") -> 0
D31: Sicoob Juriscredcelg | E31: 3348 | F31: ='Risco por Cooperativa'!H32 -> 0 | G31: =IFERROR((COUNTIF('A3348'!$AL:$AL,"Sim"))/F31,0) -> 0 | H31: =COUNTIF('A3348'!$AL:$AL,"Sim") -> 0 | I31: =COUNTIF('A3348'!AM:AM,"Verificar") -> 0
D32: Sicoob Credicer | E32: 3349 | F32: ='Risco por Cooperativa'!H33 -> 1 | G32: =IFERROR((COUNTIF('A3349'!$AL:$AL,"Sim"))/F32,0) -> 1 | H32: =COUNTIF('A3349'!$AL:$AL,"Sim") -> 1 | I32: =COUNTIF('A3349'!AM:AM,"Verificar") -> 0
D33: Sicoob Crediadag | E33: 3351 | F33: ='Risco por Cooperativa'!H34 -> 1 | G33: =IFERROR((COUNTIF('A3351'!$AL:$AL,"Sim"))/F33,0) -> 0 | H33: =COUNTIF('A3351'!$AL:$AL,"Sim") -> 0 | I33: =COUNTIF('A3351'!AM:AM,"Verificar") -> 1
D34: Sicoob Empresarial | E34: 3343 | F34: ='Risco por Cooperativa'!H35 -> 0 | G34: =IFERROR((COUNTIF('A3343'!$AL:$AL,"Sim"))/F34,0) -> 0 | H34: =COUNTIF('A3343'!$AL:$AL,"Sim") -> 0 | I34: =COUNTIF('A3343'!AM:AM,"Verificar") -> 0
D35: Sicoob Cooprem | E35: 3350 | F35: ='Risco por Cooperativa'!H36 -> 1 | G35: =IFERROR((COUNTIF('A3350'!$AL:$AL,"Sim"))/F35,0) -> 1 | H35: =COUNTIF('A3350'!$AL:$AL,"Sim") -> 1 | I35: =COUNTIF('A3350'!AM:AM,"Verificar") -> 0
D36: Sicoob Credi-Comigo | E36: 3336 | F36: ='Risco por Cooperativa'!H37 -> 0 | G36: =IFERROR((COUNTIF('A3336'!$AL:$AL,"Sim"))/F36,0) -> 0 | H36: =COUNTIF('A3336'!$AL:$AL,"Sim") -> 0 | I36: =COUNTIF('A3336'!AM:AM,"Verificar") -> 0
D37: Sicoob Credigóias | E37: 3058 | F37: ='Risco por Cooperativa'!H38 -> 1 | G37: =IFERROR((COUNTIF('A3058'!$AL:$AL,"Sim"))/F37,0) -> 0 | H37: =COUNTIF('A3058'!$AL:$AL,"Sim") -> 0 | I37: =COUNTIF('A3058'!AM:AM,"Verificar") -> 1
D38: Sicoob Coopercred | E38: 3055 | F38: ='Risco por Cooperativa'!H39 -> 0 | G38: =IFERROR((COUNTIF('A3055'!$AL:$AL,"Sim"))/F38,0) -> 0 | H38: =COUNTIF('A3055'!$AL:$AL,"Sim") -> 0 | I38: =COUNTIF('A3055'!AM:AM,"Verificar") -> 0
D39: Sicoob Unicidades | E39: 5014 | F39: ='Risco por Cooperativa'!H40 -> 1 | G39: =IFERROR((COUNTIF('A5014'!$AL:$AL,"Sim"))/F39,0) -> 1 | H39: =COUNTIF('A5014'!$AL:$AL,"Sim") -> 1 | I39: =COUNTIF('A5014'!AM:AM,"Verificar") -> 0
D40: Sicoob Mineiros | E40: 3056 | F40: ='Risco por Cooperativa'!H41 -> 2 | G40: =IFERROR((COUNTIF('A3056'!$AL:$AL,"Sim"))/F40,0) -> 1.5 | H40: =COUNTIF('A3056'!$AL:$AL,"Sim") -> 3 | I40: =COUNTIF('A3056'!AM:AM,"Verificar") -> 0
D41: Sicoob Centro Oeste BR | E41: 3300 | F41: ='Risco por Cooperativa'!H42 -> 2 | G41: =IFERROR((COUNTIF('A3300'!$AL:$AL,"Sim"))/F41,0) -> 1 | H41: =COUNTIF('A3300'!$AL:$AL,"Sim") -> 2 | I41: =COUNTIF('A3300'!AM:AM,"Verificar") -> 0
D42: Sicoob Executivo | E42: 4001 | F42: ='Risco por Cooperativa'!H43 -> 0 | G42: =IFERROR((COUNTIF('A4001'!$AL:$AL,"Sim"))/F42,0) -> 0 | H42: =COUNTIF('A4001'!$AL:$AL,"Sim") -> 0 | I42: =COUNTIF('A4001'!AM:AM,"Verificar") -> 0
D43: Sicoob Judiciário | E43: 4002 | F43: ='Risco por Cooperativa'!H44 -> 0 | G43: =IFERROR((COUNTIF('A4002'!$AL:$AL,"Sim"))/F43,0) -> 0 | H43: =COUNTIF('A4002'!$AL:$AL,"Sim") -> 0 | I43: =COUNTIF('A4002'!AM:AM,"Verificar") -> 0
D44: Sicoob Credijustra | E44: 4041 | F44: ='Risco por Cooperativa'!H45 -> 0 | G44: =IFERROR((COUNTIF('A4041'!$AL:$AL,"Sim"))/F44,0) -> 0 | H44: =COUNTIF('A4041'!$AL:$AL,"Sim") -> 0 | I44: =COUNTIF('A4041'!AM:AM,"Verificar") -> 0
D45: Sicoob Credibrasília | E45: 4155 | F45: ='Risco por Cooperativa'!H46 -> 0 | G45: =IFERROR((COUNTIF('A4155'!$AL:$AL,"Sim"))/F45,0) -> 0 | H45: =COUNTIF('A4155'!$AL:$AL,"Sim") -> 0 | I45: =COUNTIF('A4155'!AM:AM,"Verificar") -> 0
D46: Sicoob Crediembrapa | E46: 4198 | F46: ='Risco por Cooperativa'!H47 -> 0 | G46: =IFERROR((COUNTIF('A4198'!$AL:$AL,"Sim"))/F46,0) -> 0 | H46: =COUNTIF('A4198'!$AL:$AL,"Sim") -> 0 | I46: =COUNTIF('A4198'!AM:AM,"Verificar") -> 0
D47: Sicoob Credfaz | E47: 4221 | F47: ='Risco por Cooperativa'!H48 -> 0 | G47: =IFERROR((COUNTIF('A4221'!$AL:$AL,"Sim"))/F47,0) -> 0 | H47: =COUNTIF('A4221'!$AL:$AL,"Sim") -> 0 | I47: =COUNTIF('A4221'!AM:AM,"Verificar") -> 0
D48: Sicoob Cooperplan Credsef | E48: 4278 | F48: ='Risco por Cooperativa'!H49 -> 1 | G48: =IFERROR((COUNTIF('A4278'!$AL:$AL,"Sim"))/F48,0) -> 1 | H48: =COUNTIF('A4278'!$AL:$AL,"Sim") -> 1 | I48: =COUNTIF('A4278'!AM:AM,"Verificar") -> 0
D49: Sicoob Dfmil | E49: 4332 | F49: ='Risco por Cooperativa'!H50 -> 0 | G49: =IFERROR((COUNTIF('A4332'!$AL:$AL,"Sim"))/F49,0) -> 0 | H49: =COUNTIF('A4332'!$AL:$AL,"Sim") -> 0 | I49: =COUNTIF('A4332'!AM:AM,"Verificar") -> 0
D50: Sicoob Empresarial | E50: 4364 | F50: ='Risco por Cooperativa'!H51 -> 0 | G50: =IFERROR((COUNTIF('A4364'!$AL:$AL,"Sim"))/F50,0) -> 0 | H50: =COUNTIF('A4364'!$AL:$AL,"Sim") -> 0 | I50: =COUNTIF('A4364'!AM:AM,"Verificar") -> 0
D51: TODAS as singulares | E51: TOTAL | F51: =SUM(F20:F50) -> 37 | G51: =SUM(H20:H50)/SUM(F20:F50) -> 0.89189189 | H51: =SUM(H20:H50) -> 33 | I51: =SUM(I20:I50) -> 5
D52: Nota: Dados de acordo com a PGPC.

Sheet Análise Efetuada
F4: PAPEL DE TRABALHO RSAC (Risco Social Ambiental e Climático) | O4: Retorno
C9: Elaborado por: Gleibson Carreiro de Sousa | F9: Data Base: | G9: 46023 | H9: Periodicadade: Mensal
C10: Revisado por: | F10: Data da Revisão
C13: BASE NORMATIVA:
C15: Manual de Riscos Social, Ambiental e Climático | H15: Última atualização em 12/4/2024
D16: a) promover, em parceria com a área de gestão de pessoas da cooperativa central, a disseminação da cultura de gerenciamento dos riscos social, ambiental e climático aos empregados das cooperativas singulares filiadas; b) monitorar a carteira e as atividades de gerenciamento dos riscos social, ambiental e climático executadas pelas cooperativas singulares filiadas, observando a avaliação de alto risco social, ambiental e climático, o desenquadramento do limite de concentração da carteira de setores sensíveis e a inclusão do plano de ação na Plataforma de Gestão de Processos e Controles (PGPC); c) verificar os registros do processo de gerenciamento dos riscos social, ambiental e climático realizados pelas cooperativas singulares filiadas; d) comunicar, por meio da Diretoria Executiva da cooperativa central, às Diretorias Executivas das cooperativas singulares filiadas os casos em que os trabalhos executados estão inadequados e/ou que estão em desconformidade com a norma em vigor; e) apresentar aos Conselhos de Administração e Fiscal, e à Diretoria Executiva da cooperativa central, o resultado dos trabalhos dos riscos social, ambiental e climático nas operações de crédito, bem como planos de ação, quando houver; f) monitorar, por meio do módulo Risco Operacional, da Plataforma de Gestão de Processos e Controles (PGPC), se as perdas por danos sociais, ambientais e climáticos foram devidamente registradas pela cooperativa singular; g) monitorar a implementação da PRSAC nas cooperativas singulares filiadas; h) monitorar os fornecedores e prestadores de serviços terceirizados avaliados como alto risco social, ambiental e climático; i) consultar os fornecedores e prestadores de serviços terceirizados na Lista Suja do Ministério do Trabalho e Emprego (MTE); j) posicionar a área responsável pelas contratações na cooperativa central quando houver fornecedor ou prestador de serviço terceirizado incluído na Lista Suja do MTE.
C32: Item de Conhecimento 18300 - Monitoramento Automático de RSAC | H32: Atualizado em: 05/09/2023
D34: A partir do monitoramento automático, as cooperativas serão notificadas via e-mail, nas seguintes situações: Quando os cooperados forem avaliados como Alto Risco RSAC; Quando for constatada uma piora da nota de risco RSAC, pelo monitoramento , resultado em "Alto Risco" RSAC. No vencimento dos questionários. IMPORTANTE: Quando do vencimento das classificações de RSAC de alto, médio ou baixo risco, as consultas externas serão renovadas automaticamente pelo sistema, sendo facultativo à cooperativa o preenchimento do QRSAC Declaratório. Ressalta-se que na composição da nota será considerado o questionário declaratório vigente, se houver.
C42: CCI - 436/2024 - CCS | H42: Publicada em 2 de abril de 2024.
D44: A área responsável pelo gerenciamento de RSAC da entidade deverá: a) analisar os fornecedores classificados com alto RSAC e emitir parecer com recomendações, que poderão desconsiderar o fornecedor avaliado no processo de contratação ou construir um plano de ação de mitigação de riscos, que será acompanhado anualmente pela própria área de RSAC da entidade; b) monitorar os fornecedores avaliados com alto RSAC, após 1 (um) ano do firmamento do contrato, aplicando avaliação por meio da Agrotools Gestão e Monitoramento Geo-Espacial de Riscos S.A., especializada na disponibilização de dados socioambientais.
C51: ANÁLISES EFETUADAS
D53: ANÁLISE 01: Permite verificar quantos cooperados foram classificados em cada categoria de risco: Baixo, Médio e Alto quanto ao risco RSAC, por cooperativa, contribuindo para o fortalecimento e a sustentabilidade da filiada e também tomada de decisão.
D55: ANÁLISE 02: Analisamos a conformidade do preenchimento do questionário RSAC, uma vez, que de acordo com o Manual é obrigatória a solicitação de documentos que evidenciem as respostas fornecidas no preenchimento do questionário declaratório relacionadas a licenciamentos ambientais, compensação de reserva legal em outra propriedade, certidão negativa de débitos trabalhistas, e termo de ajustamento de conduta. Outras evidências deverão ser observadas mediante regras dos produtos de crédito.
D60: ANÁLISE 04 e 05: Monitoramos fornecedores e prestadores de serviços terceirizados de alto risco social, ambiental e climático das Filiadas e verificamos se estão na Lista Suja do Ministério do Trabalho e Emprego (MTE) e o enquadramento dos setores ensíveis.
D63: ANÁLISE 06: Monitoramos as avaliações classificadas como de Alto Risco para compreender os motivos dessa classificação e garantir que o plano de ação correspondente seja registrado na Plataforma de Gestão de Processos e Controles (PGPC) de acordo com a causa identificada.

Sheet Rel de fornecedores
B6: SISBR - RISCOS SOCIAL, AMBIENTAL E CLIMÁTICO
B7: RELATÓRIO DE FORNECEDORES E PRESTADORES DE SERVIÇOS TERCEIRIZADOS
B8: 1004 - SICOOB NOVA CENTRAL
B9: DATA DE EMISSÃO: | D9: 46073.63
B11: Central | E11: Cooperativa | F11: Área Solicitante | G11: CPF/CNPJ | H11: Nome/Razão Social | I11: Nível de risco | J11: Data/Hora | K11: Usuário
B12: 1004 - SICOOB NOVA CENTRAL | E12: 3343 - SICOOB EMPRESARIAL | F12: Unidade Administrativa/Suprimentos | G12: 02.033.677/0001-51 | H12: UNIODONTO SUDOESTE GOIANO COOPERATIVA DE TRABALHO | I12: Baixo | J12: 28/01/2026 08:51:33 | K12: --
B13: 1004 - SICOOB NOVA CENTRAL | E13: 3054 - SICOOB CREDI-RURAL | F13: Unidade Administrativa/Suprimentos | G13: 20.376.444/0001-33 | H13: ATHENAS TURISMO LTDA | I13: Baixo | J13: 16/01/2026 13:44:45 | K13: --
B14: 1004 - SICOOB NOVA CENTRAL | E14: 3054 - SICOOB CREDI-RURAL | F14: Unidade Administrativa/Suprimentos | G14: 26.160.445/0001-22 | H14: ELETRICOM TECNOLOGIA E CONSTRUCOES LTDA | I14: Baixo | J14: 13/01/2026 09:47:29 | K14: --
B15: 1004 - SICOOB NOVA CENTRAL | E15: 3054 - SICOOB CREDI-RURAL | F15: Unidade Administrativa/Suprimentos | G15: 07.858.131/0001-53 | H15: ESTEVES & PIRES LTDA | I15: Baixo | J15: 05/01/2026 15:31:30 | K15: --

Sheet CNAEs
A1: Código | B1: Classe da Classificação Nacional de Atividade Econômica (CNAE) | C1: Nível de | D1: Classificação de Risco | E1: Saldo devedor
A2: A011 | B2: Produção de lavouras temporárias | C2: 4 | D2: Alto | E2: ≥ R$ 800 mil | H2: Retorno
A3: B091 | B3: Atividades de apoio à extração de petróleo e gás natural | C3: 4 | D3: Alto | E3: ≥ R$ 800 mil
A4: B099 | B4: Atividades de apoio à extração de minerais, exceto petróleo e gás natural | C4: 4 | D4: Alto | E4: ≥ R$ 800 mil
A5: C101 | B5: Abate e fabricação de produtos de carne | C5: 5 | D5: Muito Alto | E5: ≥ R$ 700 mil
A6: C104 | B6: Fabricação de óleos e gorduras vegetais e animais | C6: 5 | D6: Muito Alto | E6: ≥ R$ 700 mil
A7: A013 | B7: Produção de lavouras permanentes | C7: 5 | D7: Muito Alto | E7: ≥ R$ 700 mil
A8: A014 | B8: Produção de sementes e mudas certificadas | C8: 5 | D8: Muito Alto | E8: ≥ R$ 700 mil
A9: A015 | B9: Pecuária | C9: 5 | D9: Muito Alto | E9: ≥ R$ 700 mil
A10: A016 | B10: Atividades de apoio à agricultura e à pecuária; atividades de pós colheita | C10: 2 | D10: Baixo | E10: ≥ R$ 1,5 milhão
A11: A017 | B11: Caça e serviços relacionados | C11: 3 | D11: Médio | E11: ≥ R$ 1 milhão
A12: A021 | B12: Produção florestal - florestas plantadas | C12: 5 | D12: Muito Alto | E12: ≥ R$ 700 mil
A13: A022 | B13: Produção florestal - florestas nativas | C13: 5 | D13: Muito Alto | E13: ≥ R$ 700 mil
A14: A023 | B14: Atividades de apoio à produção florestal | C14: 5 | D14: Muito Alto | E14: ≥ R$ 700 mil
... A275: U990 | B275: Organismos internacionais e outras instituições extraterritoriais | C275: 1 | D275: Muito Baixo | E275: -

Sheet A3300
B2: Risco Social Ambiental e Climático (3300) | F2: 3300 - SICOOB CENTRO OESTE BR | H2: Retorno
B3: =I8 -> 46023 | C3: BAIXO RISCO | D3: MÉDIO RISCO | E3: ALTO RISCO | O3: Pergunta 01: A atividade está sujeita ao licenciamento ambiental conforme Resolução CONAMA n° 237/1997 ou normativo estadual / Municipal, se houver? Se sim, declara possuir o licenciamento necessário vigente? A empresa trabalha com equipamentos e sistemas destinados ao armazenamento e a distribuição de combustíveis automotivos, assim como sua montagem e instalação? | R3: Pergunta 02: Declara que há a compensação da Reserva Legal em outra Propriedade? | V3: Pergunta 03: O uso da água na área de produção e/ou construção está em conformidade com as normas de utilização de recursos hídricos (Lei n° 9.433/1997?)? | Z3: Pergunta 04: Possui débitos trabalhistas inadimplidos perante a Justiça do Trabalho? A Certidão negativa de débitos trabalhistas está anexada na Plataforma de Atendimento? | AD3: Pergunta 05: Quanto há infrações ou embargos de ordem ambiental e/ou social, o infrator poderá firmar o TAC (Termo de Ajustamento de Conduta) para regularização. Nos últimos 5 anos, as atividades da empresa/produtor rural foram objeto de inquérito, multa, auto de infração ou TAC em decorrência de questões sociais ou ambientais? | AH3: Pergunta 06: O questionário está datado e assinado de forma adequada e anexado na plataforma de atendimento? | AJ3: Pergunta 07: Verificação dos planos de ações.
B4: =IF(SUM(C4:E4)=0,"Não apresentou cooperados avaliados ",IF(SUM(C4:E4)=1,"TOTAL: 01 Coperado elegível ao RSAC","TOTAL: "&SUM(C4:E4)&" Cooperados avaliados ao RSAC")) -> TOTAL: 5 Cooperados avaliados ao RSAC | C4: =SUM(L:L) -> 2 | D4: =SUM(M:M) -> 1 | E4: =SUM(N:N) -> 2
B5: Setor Sensível
B6: Resultado | C6: Limite | D6: Situação
B7: =SUM('Setor_S 3300'!L:L) -> 0.0014007534 | C7: 0.15 | D7: =IF(B7<C7,"ENQUADRADO","DESENQUADRADO") -> ENQUADRADO | H7: Singular 3300 - Detalhamento do Mês | L7: Baixo | M7: Médio | N7: Alto
B8: Quantidade de fornecedores cadastrados no Sistema | H8: Data Base | I8: ='Análise Efetuada'!G9 -> 46023 | J8: {=_xlfn.XLOOKUP(_xlfn.UNIQUE('3300'!$C:$C),'3300'!C:C,'3300'!D:D,"")} -> 0
B9: TOTAL DE FORNECEDORES | C9: BAIXO RISCO | D9: MÉDIO RISCO | E9: ALTO RISCO | H9: CNAE | I9: CNPJ | J9: Nome/Razão Social | K9: Data da avaliação | O9: O CNAE está sujeito? | P9: Colocou a evidencia? | Q9: Resultado Pergunta 01 | R9: Qual foi a resposta do quest.? | S9: Precisa de evidencia? | T9: Colocou a evidencia? | U9: Resultado Pergunta 02 | V9: Qual foi a resposta do quest.? | W9: Precisa de outorga? | X9: Colocou a evidencia? | Y9: Resultado Pergunta 03 | Z9: Qual foi a resposta do quest.? | AA9: Precisa da certidão? | AB9: Colocou a evidencia? | AC9: Resultado Pergunta 04 | AD9: Qual foi a resposta do quest.? | AE9: Precisa da comprovação? | AF9: Colocou a evidencia? | AG9: Resultado Pergunta 05 | AH9: O questionário está datadado e assinado e anexado? | AI9: Resultado Pergunta 06 | AJ9: A avaliação é de Alto Risco? | AK9: Qual o motivo da avaliação de Alto Risco? | AL9: Foi feito o cadastro do Plano de ação na PGPC? | AM9: Resultado Pergunta 07 | AO9: Arrastar a fórmula, conforme necessário
B10: =SUM(C10:E10) -> 0 | C10: ='Análise Fornecedores'!G21 -> 0 | D10: ='Análise Fornecedores'!H21 -> 0 | E10: ='Análise Fornecedores'!I21 -> 0 | H10: F4120400 - Construção de edifícios | I10: =_xlfn.XLOOKUP(J10,'3300'!$D:$D,'3300'!$C:$C,0,0) -> 14.229.475/0001-69 | J10: SUMMUS ENGENHARIA LTDA | K10: {=MAX(IF(J10='3300'!$D:$D,'3300'!$I:$I))} -> 46038 | L10: =IF(COUNTIFS('3300'!$D:$D,'A3300'!J10,'3300'!$I:$I,'A3300'!K10,'3300'!$F:$F,'A3300'!$L$7)>=1,1,0) -> 1 | M10: =IF(COUNTIFS('3300'!$D:$D,'A3300'!J10,'3300'!$I:$I,'A3300'!K10,'3300'!$F:$F,'A3300'!$M$7)>=1,1,0) -> 0 | N10: =IF(COUNTIFS('3300'!$D:$D,'A3300'!J10,'3300'!$I:$I,'A3300'!K10,'3300'!$F:$F,'A3300'!$N$7)>=1,1,0) -> 0 | Q10: =IF(AND(O10="Sim")*OR(P10="Não",P10="Não se aplica",P10=""),"Verificar","Ok") -> Ok | U10: =IF(AND(R10="Sim",T10="Siim"),"Ok",IF(AND(S10="Sim")*OR(T10="Não",T10="Não se aplica",T10=""),"Verificar","Ok")) -> Ok | Y10: =IF(AND(V10="Sim",X10="Siim"),"Ok",IF(AND(W10="Sim")*OR(X10="Não",X10="Não se aplica",X10=""),"Verificar","Ok")) -> Ok | AC10: =IF(AND(Z10="Sim",AB10="Siim"),"Ok",IF(AND(AA10="Sim")*OR(AB10="Não",AB10="Não se aplica",AB10=""),"Verificar","Ok")) -> Ok | AG10: =IF(AND(AE10="sim",AF10="Não"),"Verificar","Ok") -> Ok | AI10: =IF(AH10="Não","Verificar","Ok") -> Ok | AJ10: =IF(N10=1,"Sim, precisa de plano cadastrado na PGPC", "Não") -> Não | AM10: =IF(OR(AL10=" ",AL10="Sim"),"Ok",IF(AJ10="Não","Ok","Verificar")) -> Ok | AO10: =IF(AND(Q10="Ok",U10="Ok",Y10="Ok",AC10="Ok",AG10="Ok",AI10="Ok",AM10="Ok"),"Cooperado SEM perguntas a serem evidenciadas","Cooperado COM perguntas a serem evidenciadas") -> Cooperado SEM perguntas a serem evidenciadas
B11: Perguntas que precisam ser evidenciadas do questionário dos fornecedores: | H11: F4110700 - Incorporação de empreendimentos imobiliários | I11: =_xlfn.XLOOKUP(J11,'3300'!$D:$D,'3300'!$C:$C,0,0) -> 22.896.197/0001-21 | J11: CORUMBA EMPREENDIMENTOS E PARTICIPACOES LTDA | K11: {=MAX(IF(J11='3300'!$D:$D,'3300'!$I:$I))} -> 46050 | L11: =IF(COUNTIFS('3300'!$D:$D,'A3300'!J11,'3300'!$I:$I,'A3300'!K11,'3300'!$F:$F,'A3300'!$L$7)>=1,1,0) -> 0 | M11: =IF(COUNTIFS('3300'!$D:$D,'A3300'!J11,'3300'!$I:$I,'A3300'!K11,'3300'!$F:$F,'A3300'!$M$7)>=1,1,0) -> 0 | N11: =IF(COUNTIFS('3300'!$D:$D,'A3300'!J11,'3300'!$I:$I,'A3300'!K11,'3300'!$F:$F,'A3300'!$N$7)>=1,1,0) -> 1 | Q11: =IF(AND(O11="Sim")*OR(P11="Não",P11="Não se aplica",P11=""),"Verificar","Ok") -> Ok | U11: =IF(AND(R11="Sim",T11="Siim"),"Ok",IF(AND(S11="Sim")*OR(T11="Não",T11="Não se aplica",T11=""),"Verificar","Ok")) -> Ok | Y11: =IF(AND(V11="Sim",X11="Siim"),"Ok",IF(AND(W11="Sim")*OR(X11="Não",X11="Não se aplica",X11=""),"Verificar","Ok")) -> Ok | AC11: =IF(AND(Z11="Sim",AB11="Siim"),"Ok",IF(AND(AA11="Sim")*OR(AB11="Não",AB11="Não se aplica",AB11=""),"Verificar","Ok")) -> Ok | AG11: =IF(AND(AE11="sim",AF11="Não"),"Verificar","Ok") -> Ok | AI11: =IF(AH11="Não","Verificar","Ok") -> Ok | AJ11: =IF(N11=1,"Sim, precisa de plano cadastrado na PGPC", "Não") -> Sim, precisa de plano cadastrado na PGPC | AL11: Sim | AM11: =IF(OR(AL11=" ",AL11="Sim"),"Ok",IF(AJ11="Não","Ok","Verificar")) -> Ok | AO11: =IF(AND(Q11="Ok",U11="Ok",Y11="Ok",AC11="Ok",AG11="Ok",AI11="Ok",AM11="Ok"),"Cooperado SEM perguntas a serem evidenciadas","Cooperado COM perguntas a serem evidenciadas") -> Cooperado SEM perguntas a serem evidenciadas
B12: Fornecedor | C12: Pergunta | H12: G4731800 - Comércio varejista de combustíveis para veículos automotores | I12: =_xlfn.XLOOKUP(J12,'3300'!$D:$D,'3300'!$C:$C,0,0) -> 34.906.478/0001-05 | J12: AGPETRO COMERCIO DE PETROLEO LTDA | K12: {=MAX(IF(J12='3300'!$D:$D,'3300'!$I:$I))} -> 46039 | L12: =IF(COUNTIFS('3300'!$D:$D,'A3300'!J12,'3300'!$I:$I,'A3300'!K12,'3300'!$F:$F,'A3300'!$L$7)>=1,1,0) -> 1 | M12: =IF(COUNTIFS('3300'!$D:$D,'A3300'!J12,'3300'!$I:$I,'A3300'!K12,'3300'!$F:$F,'A3300'!$M$7)>=1,1,0) -> 0 | N12: =IF(COUNTIFS('3300'!$D:$D,'A3300'!J12,'3300'!$I:$I,'A3300'!K12,'3300'!$F:$F,'A3300'!$N$7)>=1,1,0) -> 0 | Q12: =IF(AND(O12="Sim")*OR(P12="Não",P12="Não se aplica",P12=""),"Verificar","Ok") -> Ok | U12: =IF(AND(R12="Sim",T12="Siim"),"Ok",IF(AND(S12="Sim")*OR(T12="Não",T12="Não se aplica",T12=""),"Verificar","Ok")) -> Ok | Y12: =IF(AND(V12="Sim",X12="Siim"),"Ok",IF(AND(W12="Sim")*OR(X12="Não",X12="Não se aplica",X12=""),"Verificar","Ok")) -> Ok | AC12: =IF(AND(Z12="Sim",AB12="Siim"),"Ok",IF(AND(AA12="Sim")*OR(AB12="Não",AB12="Não se aplica",AB12=""),"Verificar","Ok")) -> Ok | AG12: =IF(AND(AE12="sim",AF12="Não"),"Verificar","Ok") -> Ok | AI12: =IF(AH12="Não","Verificar","Ok") -> Ok | AJ12: =IF(N12=1,"Sim, precisa de plano cadastrado na PGPC", "Não") -> Não | AM12: =IF(OR(AL12=" ",AL12="Sim"),"Ok",IF(AJ12="Não","Ok","Verificar")) -> Ok | AO12: =IF(AND(Q12="Ok",U12="Ok",Y12="Ok",AC12="Ok",AG12="Ok",AI12="Ok",AM12="Ok"),"Cooperado SEM perguntas a serem evidenciadas","Cooperado COM perguntas a serem evidenciadas") -> Cooperado SEM perguntas a serem evidenciadas
A13: =IFERROR(IF(ROW(_xlfn.XLOOKUP(B13,For_3300!D:D,For_3300!D:D))=1,"",ROW(_xlfn.XLOOKUP(B13,For_3300!D:D,For_3300!D:D))),"") | B13: {=_xlfn.UNIQUE(IF(_xlfn._xlws.FILTER(For_3300!D:D,For_3300!Z:Z="Fornecedor COM perguntas a serem evidenciadas","")="","",_xlfn._xlws.FILTER(For_3300!D:D,For_3300!Z:Z:'For_3300'!Z:Z="Fornecedor COM perguntas a serem evidenciadas","")))} | C13: {=IFERROR(LEFT( IF(INDIRECT("For_3300!N"&A13)="verificar","6, ","")& IF(INDIRECT("For_3300!q"&A13)="verificar","7, ","")& IF(INDIRECT("For_3300!t"&A13)="verificar","8, ","")& IF(INDIRECT("For_3300!w"&A13)="verificar","16, ","")& IF(INDIRECT("For_3300!x"&A13)="não","QUESTIONÁRIO, ",""), LEN( IF(INDIRECT("For_3300!N"&A13)="verificar","6, ","")& IF(INDIRECT("For_3300!q"&A13)="verificar","7, ","")& IF(INDIRECT("For_3300!t"&A13)="verificar","8, ","")& IF(INDIRECT("For_3300!w"&A13)="verificar","16, ","")& IF(INDIRECT("For_3300!x"&A13)="não","QUESTIONÁRIO, ",""))-2)&".","")} | H13: Sem CNAE | I13: =_xlfn.XLOOKUP(J13,'3300'!$D:$D,'3300'!$C:$C,0,0) -> 735.051.961-34 | J13: JOSE FELIPE FERREIRA LINS | K13: {=MAX(IF(J13='3300'!$D:$D,'3300'!$I:$I))} -> 46026 | L13: =IF(COUNTIFS('3300'!$D:$D,'A3300'!J13,'3300'!$I:$I,'A3300'!K13,'3300'!$F:$F,'A3300'!$L$7)>=1,1,0) -> 0 | M13: =IF(COUNTIFS('3300'!$D:$D,'A3300'!J13,'3300'!$I:$I,'A3300'!K13,'3300'!$F:$F,'A3300'!$M$7)>=1,1,0) -> 0 | N13: =IF(COUNTIFS('3300'!$D:$D,'A3300'!J13,'3300'!$I:$I,'A3300'!K13,'3300'!$F:$F,'A3300'!$N$7)>=1,1,0) -> 1 | Q13: =IF(AND(O13="Sim")*OR(P13="Não",P13="Não se aplica",P13=""),"Verificar","Ok") -> Ok | U13: =IF(AND(R13="Sim",T13="Siim"),"Ok",IF(AND(S13="Sim")*OR(T13="Não",T13="Não se aplica",T13=""),"Verificar","Ok")) -> Ok | Y13: =IF(AND(V13="Sim",X13="Siim"),"Ok",IF(AND(W13="Sim")*OR(X13="Não",X13="Não se aplica",X13=""),"Verificar","Ok")) -> Ok | AC13: =IF(AND(Z13="Sim",AB13="Siim"),"Ok",IF(AND(AA13="Sim")*OR(AB13="Não",AB13="Não se aplica",AB13=""),"Verificar","Ok")) -> Ok | AG13: =IF(AND(AE13="sim",AF13="Não"),"Verificar","Ok") -> Ok | AI13: =IF(AH13="Não","Verificar","Ok") -> Ok | AJ13: =IF(N13=1,"Sim, precisa de plano cadastrado na PGPC", "Não") -> Sim, precisa de plano cadastrado na PGPC | AL13: Sim | AM13: =IF(OR(AL13=" ",AL13="Sim"),"Ok",IF(AJ13="Não","Ok","Verificar")) -> Ok | AO13: =IF(AND(Q13="Ok",U13="Ok",Y13="Ok",AC13="Ok",AG13="Ok",AI13="Ok",AM13="Ok"),"Cooperado SEM perguntas a serem evidenciadas","Cooperado COM perguntas a serem evidenciadas") -> Cooperado SEM perguntas a serem evidenciadas
A14: =IFERROR(IF(ROW(_xlfn.XLOOKUP(B14,For_3300!D:D,For_3300!D:D))=1,"",ROW(_xlfn.XLOOKUP(B14,For_3300!D:D,For_3300!D:D))),"") | B14: {=_xlfn.UNIQUE(IF(_xlfn._xlws.FILTER(For_3300!D:D,For_3300!Z:Z="Fornecedor COM perguntas a serem evidenciadas","")="","",_xlfn._xlws.FILTER(For_3300!D:D,For_3300!Z:Z:'For_3300'!Z:Z="Fornecedor COM perguntas a serem evidenciadas","")))} | C14: {=IFERROR(LEFT( IF(INDIRECT("For_3300!N"&A14)="verificar","6, ","")& IF(INDIRECT("For_3300!q"&A14)="verificar","7, ","")& IF(INDIRECT("For_3300!t"&A14)="verificar","8, ","")& IF(INDIRECT("For_3300!w"&A14)="verificar","16, ","")& IF(INDIRECT("For_3300!x"&A14)="não","QUESTIONÁRIO, ",""), LEN( IF(INDIRECT("For_3300!N"&A14)="verificar","6, ","")& IF(INDIRECT("For_3300!q"&A14)="verificar","7, ","")& IF(INDIRECT("For_3300!t"&A14)="verificar","8, ","")& IF(INDIRECT("For_3300!w"&A14)="verificar","16, ","")& IF(INDIRECT("For_3300!x"&A14)="não","QUESTIONÁRIO, ",""))-2)&".","")} | H14: A0115600 - Cultivo de soja | I14: =_xlfn.XLOOKUP(J14,'3300'!$D:$D,'3300'!$C:$C,0,0) -> 899.421.751-72 | J14: DERMEVAL LUIS ALVES FERRO | K14: {=MAX(IF(J14='3300'!$D:$D,'3300'!$I:$I))} -> 46026 | L14: =IF(COUNTIFS('3300'!$D:$D,'A3300'!J14,'3300'!$I:$I,'A3300'!K14,'3300'!$F:$F,'A3300'!$L$7)>=1,1,0) -> 0 | M14: =IF(COUNTIFS('3300'!$D:$D,'A3300'!J14,'3300'!$I:$I,'A3300'!K14,'3300'!$F:$F,'A3300'!$M$7)>=1,1,0) -> 1 | N14: =IF(COUNTIFS('3300'!$D:$D,'A3300'!J14,'3300'!$I:$I,'A3300'!K14,'3300'!$F:$F,'A3300'!$N$7)>=1,1,0) -> 0 | Q14: =IF(AND(O14="Sim")*OR(P14="Não",P14="Não se aplica",P14=""),"Verificar","Ok") -> Ok | U14: =IF(AND(R14="Sim",T14="Siim"),"Ok",IF(AND(S14="Sim")*OR(T14="Não",T14="Não se aplica",T14=""),"Verificar","Ok")) -> Ok | Y14: =IF(AND(V14="Sim",X14="Siim"),"Ok",IF(AND(W14="Sim")*OR(X14="Não",X14="Não se aplica",X14=""),"Verificar","Ok")) -> Ok | AC14: =IF(AND(Z14="Sim",AB14="Siim"),"Ok",IF(AND(AA14="Sim")*OR(AB14="Não",AB14="Não se aplica",AB14=""),"Verificar","Ok")) -> Ok | AG14: =IF(AND(AE14="sim",AF14="Não"),"Verificar","Ok") -> Ok | AI14: =IF(AH14="Não","Verificar","Ok") -> Ok | AJ14: =IF(N14=1,"Sim, precisa de plano cadastrado na PGPC", "Não") -> Não | AM14: =IF(OR(AL14=" ",AL14="Sim"),"Ok",IF(AJ14="Não","Ok","Verificar")) -> Ok | AO14: =IF(AND(Q14="Ok",U14="Ok",Y14="Ok",AC14="Ok",AG14="Ok",AI14="Ok",AM14="Ok"),"Cooperado SEM perguntas a serem evidenciadas","Cooperado COM perguntas a serem evidenciadas") -> Cooperado SEM perguntas a serem evidenciadas
A15: =IFERROR(IF(ROW(_xlfn.XLOOKUP(B15,For_3300!D:D,For_3300!D:D))=1,"",ROW(_xlfn.XLOOKUP(B15,For_3300!D:D,For_3300!D:D))),"") | B15: {=_xlfn.UNIQUE(IF(_xlfn._xlws.FILTER(For_3300!D:D,For_3300!Z:Z="Fornecedor COM perguntas a serem evidenciadas","")="","",_xlfn._xlws.FILTER(For_3300!D:D,For_3300!Z:Z:'For_3300'!Z:Z="Fornecedor COM perguntas a serem evidenciadas","")))} | C15: {=IFERROR(LEFT( IF(INDIRECT("For_3300!N"&A15)="verificar","6, ","")& IF(INDIRECT("For_3300!q"&A15)="verificar","7, ","")& IF(INDIRECT("For_3300!t"&A15)="verificar","8, ","")& IF(INDIRECT("For_3300!w"&A15)="verificar","16, ","")& IF(INDIRECT("For_3300!x"&A15)="não","QUESTIONÁRIO, ",""), LEN( IF(INDIRECT("For_3300!N"&A15)="verificar","6, ","")& IF(INDIRECT("For_3300!q"&A15)="verificar","7, ","")& IF(INDIRECT("For_3300!t"&A15)="verificar","8, ","")& IF(INDIRECT("For_3300!w"&A15)="verificar","16, ","")& IF(INDIRECT("For_3300!x"&A15)="não","QUESTIONÁRIO, ",""))-2)&".","")} | I15: =_xlfn.XLOOKUP(J15,'3300'!$D:$D,'3300'!$C:$C,0,0) -> 0 | K15: {=MAX(IF(J15='3300'!$D:$D,'3300'!$I:$I))} -> 0 | L15: =IF(COUNTIFS('3300'!$D:$D,'A3300'!J15,'3300'!$I:$I,'A3300'!K15,'3300'!$F:$F,'A3300'!$L$7)>=1,1,0) -> 0 | M15: =IF(COUNTIFS('3300'!$D:$D,'A3300'!J15,'3300'!$I:$I,'A3300'!K15,'3300'!$F:$F,'A3300'!$M$7)>=1,1,0) -> 0 | N15: =IF(COUNTIFS('3300'!$D:$D,'A3300'!J15,'3300'!$I:$I,'A3300'!K15,'3300'!$F:$F,'A3300'!$N$7)>=1,1,0) -> 0 | Q15: =IF(AND(O15="Sim")*OR(P15="Não",P15="Não se aplica",P15=""),"Verificar","Ok") -> Ok | U15: =IF(AND(R15="Sim",T15="Siim"),"Ok",IF(AND(S15="Sim")*OR(T15="Não",T15="Não se aplica",T15=""),"Verificar","Ok")) -> Ok | Y15: =IF(AND(V15="Sim",X15="Siim"),"Ok",IF(AND(W15="Sim")*OR(X15="Não",X15="Não se aplica",X15=""),"Verificar","Ok")) -> Ok | AC15: =IF(AND(Z15="Sim",AB15="Siim"),"Ok",IF(AND(AA15="Sim")*OR(AB15="Não",AB15="Não se aplica",AB15=""),"Verificar","Ok")) -> Ok | AG15: =IF(AND(AE15="sim",AF15="Não"),"Verificar","Ok") -> Ok | AI15: =IF(AH15="Não","Verificar","Ok") -> Ok | AJ15: =IF(N15=1,"Sim, precisa de plano cadastrado na PGPC", "Não") -> Não | AM15: =IF(OR(AL15=" ",AL15="Sim"),"Ok",IF(AJ15="Não","Ok","Verificar")) -> Ok | AO15: =IF(AND(Q15="Ok",U15="Ok",Y15="Ok",AC15="Ok",AG15="Ok",AI15="Ok",AM15="Ok"),"Cooperado SEM perguntas a serem evidenciadas","Cooperado COM perguntas a serem evidenciadas") -> Cooperado SEM perguntas a serem evidenciadas
A16: =IFERROR(IF(ROW(_xlfn.XLOOKUP(B16,For_3300!D:D,For_3300!D:D))=1,"",ROW(_xlfn.XLOOKUP(B16,For_3300!D:D,For_3300!D:D))),"") | B16: {=_xlfn.UNIQUE(IF(_xlfn._xlws.FILTER(For_3300!D:D,For_3300!Z:Z="Fornecedor COM perguntas a serem evidenciadas","")="","",_xlfn._xlws.FILTER(For_3300!D:D,For_3300!Z:Z:'For_3300'!Z:Z="Fornecedor COM perguntas a serem evidenciadas","")))} | C16: {=IFERROR(LEFT( IF(INDIRECT("For_3300!N"&A16)="verificar","6, ","")& IF(INDIRECT("For_3300!q"&A16)="verificar","7, ","")& IF(INDIRECT("For_3300!t"&A16)="verificar","8, ","")& IF(INDIRECT("For_3300!w"&A16)="verificar","16, ","")& IF(INDIRECT("For_3300!x"&A16)="não","QUESTIONÁRIO, ",""), LEN( IF(INDIRECT("For_3300!N"&A16)="verificar","6, ","")& IF(INDIRECT("For_3300!q"&A16)="verificar","7, ","")& IF(INDIRECT("For_3300!t"&A16)="verificar","8, ","")& IF(INDIRECT("For_3300!w"&A16)="verificar","16, ","")& IF(INDIRECT("For_3300!x"&A16)="não","QUESTIONÁRIO, ",""))-2)&".","")} | I16: =_xlfn.XLOOKUP(J16,'3300'!$D:$D,'3300'!$C:$C,0,0) -> 0 | K16: {=MAX(IF(J16='3300'!$D:$D,'3300'!$I:$I))} -> 0 | L16: =IF(COUNTIFS('3300'!$D:$D,'A3300'!J16,'3300'!$I:$I,'A3300'!K16,'3300'!$F:$F,'A3300'!$L$7)>=1,1,0) -> 0 | M16: =IF(COUNTIFS('3300'!$D:$D,'A3300'!J16,'3300'!$I:$I,'A3300'!K16,'3300'!$F:$F,'A3300'!$M$7)>=1,1,0) -> 0 | N16: =IF(COUNTIFS('3300'!$D:$D,'A3300'!J16,'3300'!$I:$I,'A3300'!K16,'3300'!$F:$F,'A3300'!$N$7)>=1,1,0) -> 0 | Q16: =IF(AND(O16="Sim")*OR(P16="Não",P16="Não se aplica",P16=""),"Verificar","Ok") -> Ok | U16: =IF(AND(R16="Sim",T16="Siim"),"Ok",IF(AND(S16="Sim")*OR(T16="Não",T16="Não se aplica",T16=""),"Verificar","Ok")) -> Ok | Y16: =IF(AND(V16="Sim",X16="Siim"),"Ok",IF(AND(W16="Sim")*OR(X16="Não",X16="Não se aplica",X16=""),"Verificar","Ok")) -> Ok | AC16: =IF(AND(Z16="Sim",AB16="Siim"),"Ok",IF(AND(AA16="Sim")*OR(AB16="Não",AB16="Não se aplica",AB16=""),"Verificar","Ok")) -> Ok | AG16: =IF(AND(AE16="sim",AF16="Não"),"Verificar","Ok") -> Ok | AI16: =IF(AH16="Não","Verificar","Ok") -> Ok | AJ16: =IF(N16=1,"Sim, precisa de plano cadastrado na PGPC", "Não") -> Não | AM16: =IF(OR(AL16=" ",AL16="Sim"),"Ok",IF(AJ16="Não","Ok","Verificar")) -> Ok | AO16: =IF(AND(Q16="Ok",U16="Ok",Y16="Ok",AC16="Ok",AG16="Ok",AI16="Ok",AM16="Ok"),"Cooperado SEM perguntas a serem evidenciadas","Cooperado COM perguntas a serem evidenciadas") -> Cooperado SEM perguntas a serem evidenciadas
A17: =IFERROR(IF(ROW(_xlfn.XLOOKUP(B17,For_3300!D:D,For_3300!D:D))=1,"",ROW(_xlfn.XLOOKUP(B17,For_3300!D:D,For_3300!D:D))),"") | B17: {=_xlfn.UNIQUE(IF(_xlfn._xlws.FILTER(For_3300!D:D,For_3300!Z:Z="Fornecedor COM perguntas a serem evidenciadas","")="","",_xlfn._xlws.FILTER(For_3300!D:D,For_3300!Z:Z:'For_3300'!Z:Z="Fornecedor COM perguntas a serem evidenciadas","")))} | C17: {=IFERROR(LEFT( IF(INDIRECT("For_3300!N"&A17)="verificar","6, ","")& IF(INDIRECT("For_3300!q"&A17)="verificar","7, ","")& IF(INDIRECT("For_3300!t"&A17)="verificar","8, ","")& IF(INDIRECT("For_3300!w"&A17)="verificar","16, ","")& IF(INDIRECT("For_3300!x"&A17)="não","QUESTIONÁRIO, ",""), LEN( IF(INDIRECT("For_3300!N"&A17)="verificar","6, ","")& IF(INDIRECT("For_3300!q"&A17)="verificar","7, ","")& IF(INDIRECT("For_3300!t"&A17)="verificar","8, ","")& IF(INDIRECT("For_3300!w"&A17)="verificar","16, ","")& IF(INDIRECT("For_3300!x"&A17)="não","QUESTIONÁRIO, ",""))-2)&".","")} | I17: =_xlfn.XLOOKUP(J17,'3300'!$D:$D,'3300'!$C:$C,0,0) -> 0 | K17: {=MAX(IF(J17='3300'!$D:$D,'3300'!$I:$I))} -> 0 | L17: =IF(COUNTIFS('3300'!$D:$D,'A3300'!J17,'3300'!$I:$I,'A3300'!K17,'3300'!$F:$F,'A3300'!$L$7)>=1,1,0) -> 0 | M17: =IF(COUNTIFS('3300'!$D:$D,'A3300'!J17,'3300'!$I:$I,'A3300'!K17,'3300'!$F:$F,'A3300'!$M$7)>=1,1,0) -> 0 | N17: =IF(COUNTIFS('3300'!$D:$D,'A3300'!J17,'3300'!$I:$I,'A3300'!K17,'3300'!$F:$F,'A3300'!$N$7)>=1,1,0) -> 0 | Q17: =IF(AND(O17="Sim")*OR(P17="Não",P17="Não se aplica",P17=""),"Verificar","Ok") -> Ok | U17: =IF(AND(R17="Sim",T17="Siim"),"Ok",IF(AND(S17="Sim")*OR(T17="Não",T17="Não se aplica",T17=""),"Verificar","Ok")) -> Ok | Y17: =IF(AND(V17="Sim",X17="Siim"),"Ok",IF(AND(W17="Sim")*OR(X17="Não",X17="Não se aplica",X17=""),"Verificar","Ok")) -> Ok | AC17: =IF(AND(Z17="Sim",AB17="Siim"),"Ok",IF(AND(AA17="Sim")*OR(AB17="Não",AB17="Não se aplica",AB17=""),"Verificar","Ok")) -> Ok | AG17: =IF(AND(AE17="sim",AF17="Não"),"Verificar","Ok") -> Ok | AI17: =IF(AH17="Não","Verificar","Ok") -> Ok | AJ17: =IF(N17=1,"Sim, precisa de plano cadastrado na PGPC", "Não") -> Não | AM17: =IF(OR(AL17=" ",AL17="Sim"),"Ok",IF(AJ17="Não","Ok","Verificar")) -> Ok | AO17: =IF(AND(Q17="Ok",U17="Ok",Y17="Ok",AC17="Ok",AG17="Ok",AI17="Ok",AM17="Ok"),"Cooperado SEM perguntas a serem evidenciadas","Cooperado COM perguntas a serem evidenciadas") -> Cooperado SEM perguntas a serem evidenciadas
A18: =IFERROR(IF(ROW(_xlfn.XLOOKUP(B18,For_3300!D:D,For_3300!D:D))=1,"",ROW(_xlfn.XLOOKUP(B18,For_3300!D:D,For_3300!D:D))),"") | B18: {=_xlfn.UNIQUE(IF(_xlfn._xlws.FILTER(For_3300!D:D,For_3300!Z:Z="Fornecedor COM perguntas a serem evidenciadas","")="","",_xlfn._xlws.FILTER(For_3300!D:D,For_3300!Z:Z:'For_3300'!Z:Z="Fornecedor COM perguntas a serem evidenciadas","")))} | C18: {=IFERROR(LEFT( IF(INDIRECT("For_3300!N"&A18)="verificar","6, ","")& IF(INDIRECT("For_3300!q"&A18)="verificar","7, ","")& IF(INDIRECT("For_3300!t"&A18)="verificar","8, ","")& IF(INDIRECT("For_3300!w"&A18)="verificar","16, ","")& IF(INDIRECT("For_3300!x"&A18)="não","QUESTIONÁRIO, ",""), LEN( IF(INDIRECT("For_3300!N"&A18)="verificar","6, ","")& IF(INDIRECT("For_3300!q"&A18)="verificar","7, ","")& IF(INDIRECT("For_3300!t"&A18)="verificar","8, ","")& IF(INDIRECT("For_3300!w"&A18)="verificar","16, ","")& IF(INDIRECT("For_3300!x"&A18)="não","QUESTIONÁRIO, ",""))-2)&".","")} | I18: =_xlfn.XLOOKUP(J18,'3300'!$D:$D,'3300'!$C:$C,0,0) -> 0 | K18: {=MAX(IF(J18='3300'!$D:$D,'3300'!$I:$I))} -> 0 | L18: =IF(COUNTIFS('3300'!$D:$D,'A3300'!J18,'3300'!$I:$I,'A3300'!K18,'3300'!$F:$F,'A3300'!$L$7)>=1,1,0) -> 0 | M18: =IF(COUNTIFS('3300'!$D:$D,'A3300'!J18,'3300'!$I:$I,'A3300'!K18,'3300'!$F:$F,'A3300'!$M$7)>=1,1,0) -> 0 | N18: =IF(COUNTIFS('3300'!$D:$D,'A3300'!J18,'3300'!$I:$I,'A3300'!K18,'3300'!$F:$F,'A3300'!$N$7)>=1,1,0) -> 0 | Q18: =IF(AND(O18="Sim")*OR(P18="Não",P18="Não se aplica",P18=""),"Verificar","Ok") -> Ok | U18: =IF(AND(R18="Sim",T18="Siim"),"Ok",IF(AND(S18="Sim")*OR(T18="Não",T18="Não se aplica",T18=""),"Verificar","Ok")) -> Ok | Y18: =IF(AND(V18="Sim",X18="Siim"),"Ok",IF(AND(W18="Sim")*OR(X18="Não",X18="Não se aplica",X18=""),"Verificar","Ok")) -> Ok | AC18: =IF(AND(Z18="Sim",AB18="Siim"),"Ok",IF(AND(AA18="Sim")*OR(AB18="Não",AB18="Não se aplica",AB18=""),"Verificar","Ok")) -> Ok | AG18: =IF(AND(AE18="sim",AF18="Não"),"Verificar","Ok") -> Ok | AI18: =IF(AH18="Não","Verificar","Ok") -> Ok | AJ18: =IF(N18=1,"Sim, precisa de plano cadastrado na PGPC", "Não") -> Não | AM18: =IF(OR(AL18=" ",AL18="Sim"),"Ok",IF(AJ18="Não","Ok","Verificar")) -> Ok | AO18: =IF(AND(Q18="Ok",U18="Ok",Y18="Ok",AC18="Ok",AG18="Ok",AI18="Ok",AM18="Ok"),"Cooperado SEM perguntas a serem evidenciadas","Cooperado COM perguntas a serem evidenciadas") -> Cooperado SEM perguntas a serem evidenciadas
A19: =IFERROR(IF(ROW(_xlfn.XLOOKUP(B19,For_3300!D:D,For_3300!D:D))=1,"",ROW(_xlfn.XLOOKUP(B19,For_3300!D:D,For_3300!D:D))),"") | B19: {=_xlfn.UNIQUE(IF(_xlfn._xlws.FILTER(For_3300!D:D,For_3300!Z:Z="Fornecedor COM perguntas a serem evidenciadas","")="","",_xlfn._xlws.FILTER(For_3300!D:D,For_3300!Z:Z:'For_3300'!Z:Z="Fornecedor COM perguntas a serem evidenciadas","")))} | C19: {=IFERROR(LEFT( IF(INDIRECT("For_3300!N"&A19)="verificar","6, ","")& IF(INDIRECT("For_3300!q"&A19)="verificar","7, ","")& IF(INDIRECT("For_3300!t"&A19)="verificar","8, ","")& IF(INDIRECT("For_3300!w"&A19)="verificar","16, ","")& IF(INDIRECT("For_3300!x"&A19)="não","QUESTIONÁRIO, ",""), LEN( IF(INDIRECT("For_3300!N"&A19)="verificar","6, ","")& IF(INDIRECT("For_3300!q"&A19)="verificar","7, ","")& IF(INDIRECT("For_3300!t"&A19)="verificar","8, ","")& IF(INDIRECT("For_3300!w"&A19)="verificar","16, ","")& IF(INDIRECT("For_3300!x"&A19)="não","QUESTIONÁRIO, ",""))-2)&".","")} | I19: =_xlfn.XLOOKUP(J19,'3300'!$D:$D,'3300'!$C:$C,0,0) -> 0 | K19: {=MAX(IF(J19='3300'!$D:$D,'3300'!$I:$I))} -> 0 | L19: =IF(COUNTIFS('3300'!$D:$D,'A3300'!J19,'3300'!$I:$I,'A3300'!K19,'3300'!$F:$F,'A3300'!$L$7)>=1,1,0) -> 0 | M19: =IF(COUNTIFS('3300'!$D:$D,'A3300'!J19,'3300'!$I:$I,'A3300'!K19,'3300'!$F:$F,'A3300'!$M$7)>=1,1,0) -> 0 | N19: =IF(COUNTIFS('3300'!$D:$D,'A3300'!J19,'3300'!$I:$I,'A3300'!K19,'3300'!$F:$F,'A3300'!$N$7)>=1,1,0) -> 0 | Q19: =IF(AND(O19="Sim")*OR(P19="Não",P19="Não se aplica",P19=""),"Verificar","Ok") -> Ok | U19: =IF(AND(R19="Sim",T19="Siim"),"Ok",IF(AND(S19="Sim")*OR(T19="Não",T19="Não se aplica",T19=""),"Verificar","Ok")) -> Ok | Y19: =IF(AND(V19="Sim",X19="Siim"),"Ok",IF(AND(W19="Sim")*OR(X19="Não",X19="Não se aplica",X19=""),"Verificar","Ok")) -> Ok | AC19: =IF(AND(Z19="Sim",AB19="Siim"),"Ok",IF(AND(AA19="Sim")*OR(AB19="Não",AB19="Não se aplica",AB19=""),"Verificar","Ok")) -> Ok | AG19: =IF(AND(AE19="sim",AF19="Não"),"Verificar","Ok") -> Ok | AI19: =IF(AH19="Não","Verificar","Ok") -> Ok | AJ19: =IF(N19=1,"Sim, precisa de plano cadastrado na PGPC", "Não") -> Não | AM19: =IF(OR(AL19=" ",AL19="Sim"),"Ok",IF(AJ19="Não","Ok","Verificar")) -> Ok | AO19: =IF(AND(Q19="Ok",U19="Ok",Y19="Ok",AC19="Ok",AG19="Ok",AI19="Ok",AM19="Ok"),"Cooperado SEM perguntas a serem evidenciadas","Cooperado COM perguntas a serem evidenciadas") -> Cooperado SEM perguntas a serem evidenciadas
A20: =IFERROR(IF(ROW(_xlfn.XLOOKUP(B20,For_3300!D:D,For_3300!D:D))=1,"",ROW(_xlfn.XLOOKUP(B20,For_3300!D:D,For_3300!D:D))),"") | B20: {=_xlfn.UNIQUE(IF(_xlfn._xlws.FILTER(For_3300!D:D,For_3300!Z:Z="Fornecedor COM perguntas a serem evidenciadas","")="","",_xlfn._xlws.FILTER(For_3300!D:D,For_3300!Z:Z:'For_3300'!Z:Z="Fornecedor COM perguntas a serem evidenciadas","")))} | C20: {=IFERROR(LEFT( IF(INDIRECT("For_3300!N"&A20)="verificar","6, ","")& IF(INDIRECT("For_3300!q"&A20)="verificar","7, ","")& IF(INDIRECT("For_3300!t"&A20)="verificar","8, ","")& IF(INDIRECT("For_3300!w"&A20)="verificar","16, ","")& IF(INDIRECT("For_3300!x"&A20)="não","QUESTIONÁRIO, ",""), LEN( IF(INDIRECT("For_3300!N"&A20)="verificar","6, ","")& IF(INDIRECT("For_3300!q"&A20)="verificar","7, ","")& IF(INDIRECT("For_3300!t"&A20)="verificar","8, ","")& IF(INDIRECT("For_3300!w"&A20)="verificar","16, ","")& IF(INDIRECT("For_3300!x"&A20)="não","QUESTIONÁRIO, ",""))-2)&".","")} | I20: =_xlfn.XLOOKUP(J20,'3300'!$D:$D,'3300'!$C:$C,0,0) -> 0 | K20: {=MAX(IF(J20='3300'!$D:$D,'3300'!$I:$I))} -> 0 | L20: =IF(COUNTIFS('3300'!$D:$D,'A3300'!J20,'3300'!$I:$I,'A3300'!K20,'3300'!$F:$F,'A3300'!$L$7)>=1,1,0) -> 0 | M20: =IF(COUNTIFS('3300'!$D:$D,'A3300'!J20,'3300'!$I:$I,'A3300'!K20,'3300'!$F:$F,'A3300'!$M$7)>=1,1,0) -> 0 | N20: =IF(COUNTIFS('3300'!$D:$D,'A3300'!J20,'3300'!$I:$I,'A3300'!K20,'3300'!$F:$F,'A3300'!$N$7)>=1,1,0) -> 0 | Q20: =IF(AND(O20="Sim")*OR(P20="Não",P20="Não se aplica",P20=""),"Verificar","Ok") -> Ok | U20: =IF(AND(R20="Sim",T20="Siim"),"Ok",IF(AND(S20="Sim")*OR(T20="Não",T20="Não se aplica",T20=""),"Verificar","Ok")) -> Ok | Y20: =IF(AND(V20="Sim",X20="Siim"),"Ok",IF(AND(W20="Sim")*OR(X20="Não",X20="Não se aplica",X20=""),"Verificar","Ok")) -> Ok | AC20: =IF(AND(Z20="Sim",AB20="Siim"),"Ok",IF(AND(AA20="Sim")*OR(AB20="Não",AB20="Não se aplica",AB20=""),"Verificar","Ok")) -> Ok | AG20: =IF(AND(AE20="sim",AF20="Não"),"Verificar","Ok") -> Ok | AI20: =IF(AH20="Não","Verificar","Ok") -> Ok | AJ20: =IF(N20=1,"Sim, precisa de plano cadastrado na PGPC", "Não") -> Não | AM20: =IF(OR(AL20=" ",AL20="Sim"),"Ok",IF(AJ20="Não","Ok","Verificar")) -> Ok | AO20: =IF(AND(Q20="Ok",U20="Ok",Y20="Ok",AC20="Ok",AG20="Ok",AI20="Ok",AM20="Ok"),"Cooperado SEM perguntas a serem evidenciadas","Cooperado COM perguntas a serem evidenciadas") -> Cooperado SEM perguntas a serem evidenciadas
A21: =IFERROR(IF(ROW(_xlfn.XLOOKUP(B21,For_3300!D:D,For_3300!D:D))=1,"",ROW(_xlfn.XLOOKUP(B21,For_3300!D:D,For_3300!D:D))),"") | B21: {=_xlfn.UNIQUE(IF(_xlfn._xlws.FILTER(For_3300!D:D,For_3300!Z:Z="Fornecedor COM perguntas a serem evidenciadas","")="","",_xlfn._xlws.FILTER(For_3300!D:D,For_3300!Z:Z:'For_3300'!Z:Z="Fornecedor COM perguntas a serem evidenciadas","")))} | C21: {=IFERROR(LEFT( IF(INDIRECT("For_3300!N"&A21)="verificar","6, ","")& IF(INDIRECT("For_3300!q"&A21)="verificar","7, ","")& IF(INDIRECT("For_3300!t"&A21)="verificar","8, ","")& IF(INDIRECT("For_3300!w"&A21)="verificar","16, ","")& IF(INDIRECT("For_3300!x"&A21)="não","QUESTIONÁRIO, ",""), LEN( IF(INDIRECT("For_3300!N"&A21)="verificar","6, ","")& IF(INDIRECT("For_3300!q"&A21)="verificar","7, ","")& IF(INDIRECT("For_3300!t"&A21)="verificar","8, ","")& IF(INDIRECT("For_3300!w"&A21)="verificar","16, ","")& IF(INDIRECT("For_3300!x"&A21)="não","QUESTIONÁRIO, ",""))-2)&".","")} | I21: =_xlfn.XLOOKUP(J21,'3300'!$D:$D,'3300'!$C:$C,0,0) -> 0 | K21: {=MAX(IF(J21='3300'!$D:$D,'3300'!$I:$I))} -> 0 | L21: =IF(COUNTIFS('3300'!$D:$D,'A3300'!J21,'3300'!$I:$I,'A3300'!K21,'3300'!$F:$F,'A3300'!$L$7)>=1,1,0) -> 0 | M21: =IF(COUNTIFS('3300'!$D:$D,'A3300'!J21,'3300'!$I:$I,'A3300'!K21,'3300'!$F:$F,'A3300'!$M$7)>=1,1,0) -> 0 | N21: =IF(COUNTIFS('3300'!$D:$D,'A3300'!J21,'3300'!$I:$I,'A3300'!K21,'3300'!$F:$F,'A3300'!$N$7)>=1,1,0) -> 0
A22: =IFERROR(IF(ROW(_xlfn.XLOOKUP(B22,For_3300!D:D,For_3300!D:D))=1,"",ROW(_xlfn.XLOOKUP(B22,For_3300!D:D,For_3300!D:D))),"") | B22: {=_xlfn.UNIQUE(IF(_xlfn._xlws.FILTER(For_3300!D:D,For_3300!Z:Z="Fornecedor COM perguntas a serem evidenciadas","")="","",_xlfn._xlws.FILTER(For_3300!D:D,For_3300!Z:Z:'For_3300'!Z:Z="Fornecedor COM perguntas a serem evidenciadas","")))} | C22: {=IFERROR(LEFT( IF(INDIRECT("For_3300!N"&A22)="verificar","6, ","")& IF(INDIRECT("For_3300!q"&A22)="verificar","7, ","")& IF(INDIRECT("For_3300!t"&A22)="verificar","8, ","")& IF(INDIRECT("For_3300!w"&A22)="verificar","16, ","")& IF(INDIRECT("For_3300!x"&A22)="não","QUESTIONÁRIO, ",""), LEN( IF(INDIRECT("For_3300!N"&A22)="verificar","6, ","")& IF(INDIRECT("For_3300!q"&A22)="verificar","7, ","")& IF(INDIRECT("For_3300!t"&A22)="verificar","8, ","")& IF(INDIRECT("For_3300!w"&A22)="verificar","16, ","")& IF(INDIRECT("For_3300!x"&A22)="não","QUESTIONÁRIO, ",""))-2)&".","")} | L22: =IF(COUNTIFS('3300'!$D:$D,'A3300'!J22,'3300'!$I:$I,'A3300'!K22,'3300'!$F:$F,'A3300'!$L$7)>=1,1,0) -> 0
A23: =IFERROR(IF(ROW(_xlfn.XLOOKUP(B23,For_3300!D:D,For_3300!D:D))=1,"",ROW(_xlfn.XLOOKUP(B23,For_3300!D:D,For_3300!D:D))),"") | B23: {=_xlfn.UNIQUE(IF(_xlfn._xlws.FILTER(For_3300!D:D,For_3300!Z:Z="Fornecedor COM perguntas a serem evidenciadas","")="","",_xlfn._xlws.FILTER(For_3300!D:D,For_3300!Z:Z:'For_3300'!Z:Z="Fornecedor COM perguntas a serem evidenciadas","")))} | C23: {=IFERROR(LEFT( IF(INDIRECT("For_3300!N"&A23)="verificar","6, ","")& IF(INDIRECT("For_3300!q"&A23)="verificar","7, ","")& IF(INDIRECT("For_3300!t"&A23)="verificar","8, ","")& IF(INDIRECT("For_3300!w"&A23)="verificar","16, ","")& IF(INDIRECT("For_3300!x"&A23)="não","QUESTIONÁRIO, ",""), LEN( IF(INDIRECT("For_3300!N"&A23)="verificar","6, ","")& IF(INDIRECT("For_3300!q"&A23)="verificar","7, ","")& IF(INDIRECT("For_3300!t"&A23)="verificar","8, ","")& IF(INDIRECT("For_3300!w"&A23)="verificar","16, ","")& IF(INDIRECT("For_3300!x"&A23)="não","QUESTIONÁRIO, ",""))-2)&".","")}
A24: =IFERROR(IF(ROW(_xlfn.XLOOKUP(B24,For_3300!D:D,For_3300!D:D))=1,"",ROW(_xlfn.XLOOKUP(B24,For_3300!D:D,For_3300!D:D))),"") | B24: {=_xlfn.UNIQUE(IF(_xlfn._xlws.FILTER(For_3300!D:D,For_3300!Z:Z="Fornecedor COM perguntas a serem evidenciadas","")="","",_xlfn._xlws.FILTER(For_3300!D:D,For_3300!Z:Z:'For_3300'!Z:Z="Fornecedor COM perguntas a serem evidenciadas","")))} | C24: {=IFERROR(LEFT( IF(INDIRECT("For_3300!N"&A24)="verificar","6, ","")& IF(INDIRECT("For_3300!q"&A24)="verificar","7, ","")& IF(INDIRECT("For_3300!t"&A24)="verificar","8, ","")& IF(INDIRECT("For_3300!w"&A24)="verificar","16, ","")& IF(INDIRECT("For_3300!x"&A24)="não","QUESTIONÁRIO, ",""), LEN( IF(INDIRECT("For_3300!N"&A24)="verificar","6, ","")& IF(INDIRECT("For_3300!q"&A24)="verificar","7, ","")& IF(INDIRECT("For_3300!t"&A24)="verificar","8, ","")& IF(INDIRECT("For_3300!w"&A24)="verificar","16, ","")& IF(INDIRECT("For_3300!x"&A24)="não","QUESTIONÁRIO, ",""))-2)&".","")}
B26: Fornecedores que se encontram na Lista Suja do MTE
B27: CNPJ | C27: RAZÃO SOCIAL
A28: 1 | B28: {=_xlfn._xlws.FILTER(For_3300!D:E,For_3300!J:J="SIM","")}
A29: 2 | B29: A Central não apresenta fornecedores cadastrados na Lista Suja do MTE
A30: 3
A31: 4
A32: 5
A33: 6
A34: 7
A35: 8
A36: 9
A37: 10
A38: 11
A39: 12
A40: 13
A41: 14
... A46: 19
B48: Cooperados com respostas a serem evidenciadas.
A49: N° LIN | B49: Cooperado | C49: Pergunta
A50: =IFERROR(IF(ROW(_xlfn.XLOOKUP(B50,I:I,I:I))=1,"",ROW(_xlfn.XLOOKUP(B50,I:I,I:I))),"") | B50: {=IF(_xlfn._xlws.FILTER(I:I,AO:AO="Cooperado COM perguntas a serem evidenciadas","")="","",_xlfn._xlws.FILTER(I:I,AO:AO="Cooperado COM perguntas a serem evidenciadas",""))} | C50: {=IFERROR(LEFT( IF(INDIRECT("Q"&A50)="verificar","1, ", "")& IF(INDIRECT("U"&A50)="verificar","2, ", "")& IF(INDIRECT("Y"&A50)="verificar","3, ", "")& IF(INDIRECT("AC"&A50)="verificar","4, ", "")& IF(INDIRECT("AG"&A50)="verificar","5, ", "")& IF(INDIRECT("AI"&A50)="verificar","6, ", "")& IF(INDIRECT("AM"&A50)="verificar","7, ", ""), LEN( IF(INDIRECT("Q"&A50)="verificar","1, ", "")& IF(INDIRECT("U"&A50)="verificar","2, ", "")& IF(INDIRECT("Y"&A50)="verificar","3, ", "")& IF(INDIRECT("AC"&A50)="verificar","4, ", "")& IF(INDIRECT("AG"&A50)="verificar","5, ", "")& IF(INDIRECT("AI"&A50)="verificar","6, ", "")& IF(INDIRECT("AM"&A50)="verificar","7, ", ""))-2)&".","")}
A51: =IFERROR(IF(ROW(_xlfn.XLOOKUP(B51,I:I,I:I))=1,"",ROW(_xlfn.XLOOKUP(B51,I:I,I:I))),"") | C51: {=IFERROR(LEFT( IF(INDIRECT("Q"&A51)="verificar","1, ", "")& IF(INDIRECT("U"&A51)="verificar","2, ", "")& IF(INDIRECT("Y"&A51)="verificar","3, ", "")& IF(INDIRECT("AC"&A51)="verificar","4, ", "")& IF(INDIRECT("AG"&A51)="verificar","5, ", "")& IF(INDIRECT("AI"&A51)="verificar","6, ", "")& IF(INDIRECT("AM"&A51)="verificar","7, ", ""), LEN( IF(INDIRECT("Q"&A51)="verificar","1, ", "")& IF(INDIRECT("U"&A51)="verificar","2, ", "")& IF(INDIRECT("Y"&A51)="verificar","3, ", "")& IF(INDIRECT("AC"&A51)="verificar","4, ", "")& IF(INDIRECT("AG"&A51)="verificar","5, ", "")& IF(INDIRECT("AI"&A51)="verificar","6, ", "")& IF(INDIRECT("AM"&A51)="verificar","7, ", ""))-2)&".","")}
A52: =IFERROR(IF(ROW(_xlfn.XLOOKUP(B52,I:I,I:I))=1,"",ROW(_xlfn.XLOOKUP(B52,I:I,I:I))),"") | C52: {=IFERROR(LEFT( IF(INDIRECT("Q"&A52)="verificar","1, ", "")& IF(INDIRECT("U"&A52)="verificar","2, ", "")& IF(INDIRECT("Y"&A52)="verificar","3, ", "")& IF(INDIRECT("AC"&A52)="verificar","4, ", "")& IF(INDIRECT("AG"&A52)="verificar","5, ", "")& IF(INDIRECT("AI"&A52)="verificar","6, ", "")& IF(INDIRECT("AM"&A52)="verificar","7, ", ""), LEN( IF(INDIRECT("Q"&A52)="verificar","1, ", "")& IF(INDIRECT("U"&A52)="verificar","2, ", "")& IF(INDIRECT("Y"&A52)="verificar","3, ", "")& IF(INDIRECT("AC"&A52)="verificar","4, ", "")& IF(INDIRECT("AG"&A52)="verificar","5, ", "")& IF(INDIRECT("AI"&A52)="verificar","6, ", "")& IF(INDIRECT("AM"&A52)="verificar","7, ", ""))-2)&".","")}
A53: =IFERROR(IF(ROW(_xlfn.XLOOKUP(B53,I:I,I:I))=1,"",ROW(_xlfn.XLOOKUP(B53,I:I,I:I))),"") | C53: {=IFERROR(LEFT( IF(INDIRECT("Q"&A53)="verificar","1, ", "")& IF(INDIRECT("U"&A53)="verificar","2, ", "")& IF(INDIRECT("Y"&A53)="verificar","3, ", "")& IF(INDIRECT("AC"&A53)="verificar","4, ", "")& IF(INDIRECT("AG"&A53)="verificar","5, ", "")& IF(INDIRECT("AI"&A53)="verificar","6, ", "")& IF(INDIRECT("AM"&A53)="verificar","7, ", ""), LEN( IF(INDIRECT("Q"&A53)="verificar","1, ", "")& IF(INDIRECT("U"&A53)="verificar","2, ", "")& IF(INDIRECT("Y"&A53)="verificar","3, ", "")& IF(INDIRECT("AC"&A53)="verificar","4, ", "")& IF(INDIRECT("AG"&A53)="verificar","5, ", "")& IF(INDIRECT("AI"&A53)="verificar","6, ", "")& IF(INDIRECT("AM"&A53)="verificar","7, ", ""))-2)&".","")}
A54: =IFERROR(IF(ROW(_xlfn.XLOOKUP(B54,I:I,I:I))=1,"",ROW(_xlfn.XLOOKUP(B54,I:I,I:I))),"") | C54: {=IFERROR(LEFT( IF(INDIRECT("Q"&A54)="verificar","1, ", "")& IF(INDIRECT("U"&A54)="verificar","2, ", "")& IF(INDIRECT("Y"&A54)="verificar","3, ", "")& IF(INDIRECT("AC"&A54)="verificar","4, ", "")& IF(INDIRECT("AG"&A54)="verificar","5, ", "")& IF(INDIRECT("AI"&A54)="verificar","6, ", "")& IF(INDIRECT("AM"&A54)="verificar","7, ", ""), LEN( IF(INDIRECT("Q"&A54)="verificar","1, ", "")& IF(INDIRECT("U"&A54)="verificar","2, ", "")& IF(INDIRECT("Y"&A54)="verificar","3, ", "")& IF(INDIRECT("AC"&A54)="verificar","4, ", "")& IF(INDIRECT("AG"&A54)="verificar","5, ", "")& IF(INDIRECT("AI"&A54)="verificar","6, ", "")& IF(INDIRECT("AM"&A54)="verificar","7, ", ""))-2)&".","")}
A55: =IFERROR(IF(ROW(_xlfn.XLOOKUP(B55,I:I,I:I))=1,"",ROW(_xlfn.XLOOKUP(B55,I:I,I:I))),"") | C55: {=IFERROR(LEFT( IF(INDIRECT("Q"&A55)="verificar","1, ", "")& IF(INDIRECT("U"&A55)="verificar","2, ", "")& IF(INDIRECT("Y"&A55)="verificar","3, ", "")& IF(INDIRECT("AC"&A55)="verificar","4, ", "")& IF(INDIRECT("AG"&A55)="verificar","5, ", "")& IF(INDIRECT("AI"&A55)="verificar","6, ", "")& IF(INDIRECT("AM"&A55)="verificar","7, ", ""), LEN( IF(INDIRECT("Q"&A55)="verificar","1, ", "")& IF(INDIRECT("U"&A55)="verificar","2, ", "")& IF(INDIRECT("Y"&A55)="verificar","3, ", "")& IF(INDIRECT("AC"&A55)="verificar","4, ", "")& IF(INDIRECT("AG"&A55)="verificar","5, ", "")& IF(INDIRECT("AI"&A55)="verificar","6, ", "")& IF(INDIRECT("AM"&A55)="verificar","7, ", ""))-2)&".","")}
A56: =IFERROR(IF(ROW(_xlfn.XLOOKUP(B56,I:I,I:I))=1,"",ROW(_xlfn.XLOOKUP(B56,I:I,I:I))),"") | C56: {=IFERROR(LEFT( IF(INDIRECT("Q"&A56)="verificar","1, ", "")& IF(INDIRECT("U"&A56)="verificar","2, ", "")& IF(INDIRECT("Y"&A56)="verificar","3, ", "")& IF(INDIRECT("AC"&A56)="verificar","4, ", "")& IF(INDIRECT("AG"&A56)="verificar","5, ", "")& IF(INDIRECT("AI"&A56)="verificar","6, ", "")& IF(INDIRECT("AM"&A56)="verificar","7, ", ""), LEN( IF(INDIRECT("Q"&A56)="verificar","1, ", "")& IF(INDIRECT("U"&A56)="verificar","2, ", "")& IF(INDIRECT("Y"&A56)="verificar","3, ", "")& IF(INDIRECT("AC"&A56)="verificar","4, ", "")& IF(INDIRECT("AG"&A56)="verificar","5, ", "")& IF(INDIRECT("AI"&A56)="verificar","6, ", "")& IF(INDIRECT("AM"&A56)="verificar","7, ", ""))-2)&".","")}
A57: =IFERROR(IF(ROW(_xlfn.XLOOKUP(B57,I:I,I:I))=1,"",ROW(_xlfn.XLOOKUP(B57,I:I,I:I))),"") | C57: {=IFERROR(LEFT( IF(INDIRECT("Q"&A57)="verificar","1, ", "")& IF(INDIRECT("U"&A57)="verificar","2, ", "")& IF(INDIRECT("Y"&A57)="verificar","3, ", "")& IF(INDIRECT("AC"&A57)="verificar","4, ", "")& IF(INDIRECT("AG"&A57)="verificar","5, ", "")& IF(INDIRECT("AI"&A57)="verificar","6, ", "")& IF(INDIRECT("AM"&A57)="verificar","7, ", ""), LEN( IF(INDIRECT("Q"&A57)="verificar","1, ", "")& IF(INDIRECT("U"&A57)="verificar","2, ", "")& IF(INDIRECT("Y"&A57)="verificar","3, ", "")& IF(INDIRECT("AC"&A57)="verificar","4, ", "")& IF(INDIRECT("AG"&A57)="verificar","5, ", "")& IF(INDIRECT("AI"&A57)="verificar","6, ", "")& IF(INDIRECT("AM"&A57)="verificar","7, ", ""))-2)&".","")}
A58: =IFERROR(IF(ROW(_xlfn.XLOOKUP(B58,I:I,I:I))=1,"",ROW(_xlfn.XLOOKUP(B58,I:I,I:I))),"") | C58: {=IFERROR(LEFT( IF(INDIRECT("Q"&A58)="verificar","1, ", "")& IF(INDIRECT("U"&A58)="verificar","2, ", "")& IF(INDIRECT("Y"&A58)="verificar","3, ", "")& IF(INDIRECT("AC"&A58)="verificar","4, ", "")& IF(INDIRECT("AG"&A58)="verificar","5, ", "")& IF(INDIRECT("AI"&A58)="verificar","6, ", "")& IF(INDIRECT("AM"&A58)="verificar","7, ", ""), LEN( IF(INDIRECT("Q"&A58)="verificar","1, ", "")& IF(INDIRECT("U"&A58)="verificar","2, ", "")& IF(INDIRECT("Y"&A58)="verificar","3, ", "")& IF(INDIRECT("AC"&A58)="verificar","4, ", "")& IF(INDIRECT("AG"&A58)="verificar","5, ", "")& IF(INDIRECT("AI"&A58)="verificar","6, ", "")& IF(INDIRECT("AM"&A58)="verificar","7, ", ""))-2)&".","")}
A59: =IFERROR(IF(ROW(_xlfn.XLOOKUP(B59,I:I,I:I))=1,"",ROW(_xlfn.XLOOKUP(B59,I:I,I:I))),"") | C59: {=IFERROR(LEFT( IF(INDIRECT("Q"&A59)="verificar","1, ", "")& IF(INDIRECT("U"&A59)="verificar","2, ", "")& IF(INDIRECT("Y"&A59)="verificar","3, ", "")& IF(INDIRECT("AC"&A59)="verificar","4, ", "")& IF(INDIRECT("AG"&A59)="verificar","5, ", "")& IF(INDIRECT("AI"&A59)="verificar","6, ", "")& IF(INDIRECT("AM"&A59)="verificar","7, ", ""), LEN( IF(INDIRECT("Q"&A59)="verificar","1, ", "")& IF(INDIRECT("U"&A59)="verificar","2, ", "")& IF(INDIRECT("Y"&A59)="verificar","3, ", "")& IF(INDIRECT("AC"&A59)="verificar","4, ", "")& IF(INDIRECT("AG"&A59)="verificar","5, ", "")& IF(INDIRECT("AI"&A59)="verificar","6, ", "")& IF(INDIRECT("AM"&A59)="verificar","7, ", ""))-2)&".","")}
A60: =IFERROR(IF(ROW(_xlfn.XLOOKUP(B60,I:I,I:I))=1,"",ROW(_xlfn.XLOOKUP(B60,I:I,I:I))),"") | C60: {=IFERROR(LEFT( IF(INDIRECT("Q"&A60)="verificar","1, ", "")& IF(INDIRECT("U"&A60)="verificar","2, ", "")& IF(INDIRECT("Y"&A60)="verificar","3, ", "")& IF(INDIRECT("AC"&A60)="verificar","4, ", "")& IF(INDIRECT("AG"&A60)="verificar","5, ", "")& IF(INDIRECT("AI"&A60)="verificar","6, ", "")& IF(INDIRECT("AM"&A60)="verificar","7, ", ""), LEN( IF(INDIRECT("Q"&A60)="verificar","1, ", "")& IF(INDIRECT("U"&A60)="verificar","2, ", "")& IF(INDIRECT("Y"&A60)="verificar","3, ", "")& IF(INDIRECT("AC"&A60)="verificar","4, ", "")& IF(INDIRECT("AG"&A60)="verificar","5, ", "")& IF(INDIRECT("AI"&A60)="verificar","6, ", "")& IF(INDIRECT("AM"&A60)="verificar","7, ", ""))-2)&".","")}
A61: =IFERROR(IF(ROW(_xlfn.XLOOKUP(B61,I:I,I:I))=1,"",ROW(_xlfn.XLOOKUP(B61,I:I,I:I))),"") | C61: {=IFERROR(LEFT( IF(INDIRECT("Q"&A61)="verificar","1, ", "")& IF(INDIRECT("U"&A61)="verificar","2, ", "")& IF(INDIRECT("Y"&A61)="verificar","3, ", "")& IF(INDIRECT("AC"&A61)="verificar","4, ", "")& IF(INDIRECT("AG"&A61)="verificar","5, ", "")& IF(INDIRECT("AI"&A61)="verificar","6, ", "")& IF(INDIRECT("AM"&A61)="verificar","7, ", ""), LEN( IF(INDIRECT("Q"&A61)="verificar","1, ", "")& IF(INDIRECT("U"&A61)="verificar","2, ", "")& IF(INDIRECT("Y"&A61)="verificar","3, ", "")& IF(INDIRECT("AC"&A61)="verificar","4, ", "")& IF(INDIRECT("AG"&A61)="verificar","5, ", "")& IF(INDIRECT("AI"&A61)="verificar","6, ", "")& IF(INDIRECT("AM"&A61)="verificar","7, ", ""))-2)&".","")}
A62: =IFERROR(IF(ROW(_xlfn.XLOOKUP(B62,I:I,I:I))=1,"",ROW(_xlfn.XLOOKUP(B62,I:I,I:I))),"") | C62: {=IFERROR(LEFT( IF(INDIRECT("Q"&A62)="verificar","1, ", "")& IF(INDIRECT("U"&A62)="verificar","2, ", "")& IF(INDIRECT("Y"&A62)="verificar","3, ", "")& IF(INDIRECT("AC"&A62)="verificar","4, ", "")& IF(INDIRECT("AG"&A62)="verificar","5, ", "")& IF(INDIRECT("AI"&A62)="verificar","6, ", "")& IF(INDIRECT("AM"&A62)="verificar","7, ", ""), LEN( IF(INDIRECT("Q"&A62)="verificar","1, ", "")& IF(INDIRECT("U"&A62)="verificar","2, ", "")& IF(INDIRECT("Y"&A62)="verificar","3, ", "")& IF(INDIRECT("AC"&A62)="verificar","4, ", "")& IF(INDIRECT("AG"&A62)="verificar","5, ", "")& IF(INDIRECT("AI"&A62)="verificar","6, ", "")& IF(INDIRECT("AM"&A62)="verificar","7, ", ""))-2)&".","")}
... A82: =IFERROR(IF(ROW(_xlfn.XLOOKUP(B82,I:I,I:I))=1,"",ROW(_xlfn.XLOOKUP(B82,I:I,I:I))),"") | C82: {=IFERROR(LEFT( IF(INDIRECT("Q"&A82)="verificar","1, ", "")& IF(INDIRECT("U"&A82)="verificar","2, ", "")& IF(INDIRECT("Y"&A82)="verificar","3, ", "")& IF(INDIRECT("AC"&A82)="verificar","4, ", "")& IF(INDIRECT("AG"&A82)="verificar","5, ", "")& IF(INDIRECT("AI"&A82)="verificar","6, ", "")& IF(INDIRECT("AM"&A82)="verificar","7, ", ""), LEN( IF(INDIRECT("Q"&A82)="verificar","1, ", "")& IF(INDIRECT("U"&A82)="verificar","2, ", "")& IF(INDIRECT("Y"&A82)="verificar","3, ", "")& IF(INDIRECT("AC"&A82)="verificar","4, ", "")& IF(INDIRECT("AG"&A82)="verificar","5, ", "")& IF(INDIRECT("AI"&A82)="verificar","6, ", "")& IF(INDIRECT("AM"&A82)="verificar","7, ", ""))-2)&".","")}

Sheet 3300
A1: SISBR - RISCOS SOCIAL, AMBIENTAL E CLIMÁTICO
A2: RELATÓRIO DE RISCO POR COOPERATIVA
A3: 1004 - SICOOB NOVA CENTRAL
A4: DATA DE EMISSÃO | B4: 04/02/2026 10:21
A5: CRITÉRIOS | B5: DATABASE: 012026, CENTRAL: 1004, SINGULAR: 3300
A6: Central | B6: Singular | C6: CPF/CNPJ | D6: Nome/Razão Social | E6: Data-base | F6: Classificação de RSAC vigente | G6: Classificação por avaliação | H6: Tipo da avaliação | I6: Data da avaliação | J6: QRSAC Mobile | K6: Usuário
A7: 1004 - SICOOB NOVA CENTRAL | B7: 3300 - SICOOB CENTRO-OESTE BR | C7: 14.229.475/0001-69 | D7: SUMMUS ENGENHARIA LTDA | E7: 01/2026 | F7: Baixo | G7: BAIXO | H7: Manual (QRSAC declaratório) | I7: 46038 | J7: NÃO | K7: ANDREL3300_14
A8: 1004 - SICOOB NOVA CENTRAL | B8: 3300 - SICOOB CENTRO-OESTE BR | C8: 22.896.197/0001-21 | D8: CORUMBA EMPREENDIMENTOS E PARTICIPACOES LTDA | E8: 01/2026 | F8: Alto | G8: ALTO | H8: Automática (Consulta externa) | I8: 46050 | J8: NÃO | K8: SISBR
A9: 1004 - SICOOB NOVA CENTRAL | B9: 3300 - SICOOB CENTRO-OESTE BR | C9: 34.906.478/0001-05 | D9: AGPETRO COMERCIO DE PETROLEO LTDA | E9: 01/2026 | F9: Baixo | G9: BAIXO | H9: Automática (Consulta externa) | I9: 46039 | J9: NÃO | K9: SISBR
A10: 1004 - SICOOB NOVA CENTRAL | B10: 3300 - SICOOB CENTRO-OESTE BR | C10: 735.051.961-34 | D10: JOSE FELIPE FERREIRA LINS | E10: 01/2026 | F10: Alto | G10: ALTO | H10: Automática (Consulta externa) | I10: 46026 | J10: NÃO | K10: SISBR
A11: 1004 - SICOOB NOVA CENTRAL | B11: 3300 - SICOOB CENTRO-OESTE BR | C11: 899.421.751-72 | D11: DERMEVAL LUIS ALVES FERRO | E11: 01/2026 | F11: Médio | G11: BAIXO | H11: Automática (Consulta externa) | I11: 46026 | J11: NÃO | K11: SISBR

Sheet Setor_S 3300
A1: Ano-Mês Movimento | B1: Central | C1: Cooperativa | D1: PA | E1: Descrição Setor Sensível | F1: CPF/CNPJ | G1: Modalidade Bacen | H1: Submodalidade Bacen | I1: Contrato Crédito | J1: Saldo Setor Sensível | K1: Saldo Cooperativa | L1: Repres. Saldo (%) | M1: Valor Saldo Devedor INAD 90 | N1: INAD 90 Cooperativa | O1: Repres. INAD90 (%)
A2: 2026-01 | B2: 1004 - SICOOB NOVA CENTRAL | C2: 3300 - SICOOB CENTRO-OESTE BR | D2: 97 - PA-ATENDIMENTO DIGITAL | E2: S9491000 - Atividades de organizações religiosas | F2: 27348232000191 | G2: COOBRIGAÇÕES | H2: 1513 BENEFICIARIOS DE OUTRAS COOBRIGACOES | I2: 75633000418930300 | J2: 2978.56 | K2: 2.3099212e+08 | L2: 1.2894639e-05 | M2: 0 | N2: 23719314 | O2: 0
A3: 2026-01 | B3: 1004 - SICOOB NOVA CENTRAL | C3: 3300 - SICOOB CENTRO-OESTE BR | D3: 97 - PA-ATENDIMENTO DIGITAL | E3: S9491000 - Atividades de organizações religiosas | F3: 01496660002979 | G3: COOBRIGAÇÕES | H3: 1513 BENEFICIARIOS DE OUTRAS COOBRIGACOES | I3: 75633000376560300 | J3: 3621.84 | K3: 2.3099212e+08 | L3: 1.5679496e-05 | M3: 0 | N3: 23719314 | O3: 0
A4: 2026-01 | B4: 1004 - SICOOB NOVA CENTRAL | C4: 3300 - SICOOB CENTRO-OESTE BR | D4: 1 - SICOOB - PA CAMPINAS | E4: R9312300 - Clubes sociais, esportivos e similares | F4: 22850333115 | G4: EMPRESTIMOS | H4: CHEQUE ESPECIAL | I4: LM-4812 | J4: 466.06 | K4: 2.3099212e+08 | L4: 2.0176446e-06 | M4: 0 | N4: 23719314 | O4: 0
A5: 2026-01 | B5: 1004 - SICOOB NOVA CENTRAL | C5: 3300 - SICOOB CENTRO-OESTE BR | D5: 97 - PA-ATENDIMENTO DIGITAL | E5: S9491000 - Atividades de organizações religiosas | F5: 27348232000191 | G5: COOBRIGAÇÕES | H5: 1513 BENEFICIARIOS DE OUTRAS COOBRIGACOES | I5: 75633000407090300 | J5: 4118.52 | K5: 2.3099212e+08 | L5: 1.7829699e-05 | M5: 0 | N5: 23719314 | O5: 0
A6: 2026-01 | B6: 1004 - SICOOB NOVA CENTRAL | C6: 3300 - SICOOB CENTRO-OESTE BR | D6: 8 - SICOOB - PA GOIÁS | E6: S9491000 - Atividades de organizações religiosas | F6: 26872838000169 | G6: EMPRESTIMOS | H6: CAPITAL DE GIRO COM PRAZO VENCIMENTO SUPERIOR 365 DIAS | I6: 320839 | J6: 173158.49 | K6: 2.3099212e+08 | L6: 0.00074962944 | M6: 0 | N6: 23719314 | O6: 0
A7: 2026-01 | B7: 1004 - SICOOB NOVA CENTRAL | C7: 3300 - SICOOB CENTRO-OESTE BR | D7: 4 - SICOOB - PA TRINDADE | E7: R9312300 - Clubes sociais, esportivos e similares | F7: 01841923000139 | G7: COOBRIGAÇÕES | H7: 1513 BENEFICIARIOS DE OUTRAS COOBRIGACOES | I7: 75633000342020300 | J7: 2028.6 | K7: 2.3099212e+08 | L7: 8.7821179e-06 | M7: 0 | N7: 23719314 | O7: 0
A8: 2026-01 | B8: 1004 - SICOOB NOVA CENTRAL | C8: 3300 - SICOOB CENTRO-OESTE BR | D8: 1 - SICOOB - PA CAMPINAS | E8: R9312300 - Clubes sociais, esportivos e similares | F8: 40664627153 | G8: COOBRIGAÇÕES | H8: 1513 BENEFICIARIOS DE OUTRAS COOBRIGACOES | I8: 75633000256730300 | J8: 49160.24 | K8: 2.3099212e+08 | L8: 0.00021282215 | M8: 0 | N8: 23719314 | O8: 0
A9: 2026-01 | B9: 1004 - SICOOB NOVA CENTRAL | C9: 3300 - SICOOB CENTRO-OESTE BR | D9: 1 - SICOOB - PA CAMPINAS | E9: R9312300 - Clubes sociais, esportivos e similares | F9: 22850333115 | G9: COOBRIGAÇÕES | H9: 1513 BENEFICIARIOS DE OUTRAS COOBRIGACOES | I9: 75633000071620300 | J9: 42267.67 | K9: 2.3099212e+08 | L9: 0.00018298317 | M9: 0 | N9: 23719314 | O9: 0
A10: 2026-01 | B10: 1004 - SICOOB NOVA CENTRAL | C10: 3300 - SICOOB CENTRO-OESTE BR | D10: 97 - PA-ATENDIMENTO DIGITAL | E10: S9491000 - Atividades de organizações religiosas | F10: 14396132000199 | G10: COOBRIGAÇÕES | H10: 1513 BENEFICIARIOS DE OUTRAS COOBRIGACOES | I10: 75633000394460300 | J10: 3546.1 | K10: 2.3099212e+08 | L10: 1.5351606e-05 | M10: 0 | N10: 23719314 | O10: 0
A11: 2026-01 | B11: 1004 - SICOOB NOVA CENTRAL | C11: 3300 - SICOOB CENTRO-OESTE BR | D11: 7 - SICOOB PA - GALLO 44 | E11: S9491000 - Atividades de organizações religiosas | F11: 49933875000135 | G11: COOBRIGAÇÕES | H11: 1513 BENEFICIARIOS DE OUTRAS COOBRIGACOES | I11: 75633000372350300 | J11: 10308.68 | K11: 2.3099212e+08 | L11: 4.4627843e-05 | M11: 0 | N11: 23719314 | O11: 0
A12: 2026-01 | B12: 1004 - SICOOB NOVA CENTRAL | C12: 3300 - SICOOB CENTRO-OESTE BR | D12: 97 - PA-ATENDIMENTO DIGITAL | E12: S9491000 - Atividades de organizações religiosas | F12: 10954384000135 | G12: COOBRIGAÇÕES | H12: 1513 BENEFICIARIOS DE OUTRAS COOBRIGACOES | I12: 75633000411710100 | J12: 0.97 | K12: 2.3099212e+08 | L12: 4.1992775e-09 | M12: 0 | N12: 23719314 | O12: 0
A13: 2026-01 | B13: 1004 - SICOOB NOVA CENTRAL | C13: 3300 - SICOOB CENTRO-OESTE BR | D13: 97 - PA-ATENDIMENTO DIGITAL | E13: S9491000 - Atividades de organizações religiosas | F13: 18670207000139 | G13: COOBRIGAÇÕES | H13: 1513 BENEFICIARIOS DE OUTRAS COOBRIGACOES | I13: 75633000414160400 | J13: 6969.99 | K13: 2.3099212e+08 | L13: 3.0174147e-05 | M13: 0 | N13: 23719314 | O13: 0
... A19: 2026-01 | B19: 1004 - SICOOB NOVA CENTRAL | C19: 3300 - SICOOB CENTRO-OESTE BR | D19: 97 - PA-ATENDIMENTO DIGITAL | E19: S9491000 - Atividades de organizações religiosas | F19: 01496660004599 | G19: COOBRIGAÇÕES | H19: 1513 BENEFICIARIOS DE OUTRAS COOBRIGACOES | I19: 75633000378310300 | J19: 6986.84 | K19: 2.3099212e+08 | L19: 3.0247093e-05 | M19: 0 | N19: 23719314 | O19: 0

Sheet For_3300
J1: =_xlfn.XLOOKUP(IF(COUNTIF(D:D,D5)>1,MAX(H:H),H5),H:H,F:F,0,0) -> 0
C2: Listagem de fornecedores | F2: 3300 - SICOOB CENTRO OESTE BR | J2: ATENÇÃO: OS QUE ESTÃO MARCADOS EM VERMELHO NA COLUNA C, APLICARAM QUESTIONÁRIOS MAIS DE UMA VEZ. VERIFICAR A DATA DE APLICAÇÃO, E CONSIDERAR O ÚLTIMO. | L2: 6) A empresa dispõe de todas as autorizações para funcionar (ex.: Bombeiros, Junta Comercial, Vigilância Sanitária, dentre outras) junto aos órgãos competentes? | O2: 7) A empresa declara possuir a licença ambiental exigida para as atividades realizadas? | R2: 8) A empresa possui embargos junto ao órgão ambiental competente? | U2: 16) Quando há infrações ou embargos de ordem ambiental e/ou social, o infrator poderá firmar um TAC - Termo de Ajustamento de Conduta para regularização. Nos últimos 5 anos, as atividades da empresa foram objeto de inquérito, multa ou auto de infração em decorrência de questões sociais ou ambientais? Houve algum firmamento de TAC em decorrência de questões sociais ou ambientais? | X2: ANÁLISE DO QUESTIONÁRIO
A3: CNPJs dos Fornecedores | B3: Risco do questionário | C3: Quantidade | D3: CNPJ | E3: Razão Social | F3: Nível de Risco | G3: Data de aplicação do QUESTIONÁRIO | H3: Data | I3: Risco vigente | J3: Está na lista suja do (MTE)? | K3: Se Alto Risco, foi emitido parecer ou plano de ação pela Unidade de Riscos da Singular? | L3: Precisa de evidencia? | M3: Colocou a evidência? | N3: Resultado Pergunta 06 | O3: Precisa de evidencia? | P3: Colocou a evidência? | Q3: Resultado Pergunta 07 | R3: Precisa de evidencia? | S3: Colocou a evidência? | T3: Resultado Pergunta 08 | U3: Precisa de evidencia? | V3: Colocou a evidência? | W3: Resultado Pergunta 16 | X3: Está anexado, datado e assinado? | Z3: Arrastar a fórmula, conforme necessário
A4: {=_xlfn.UNIQUE(D4:D33)} -> #VALUE! | B4: =_xlfn.XLOOKUP(A4,$D$4:$D$33,$I$4:$I$33,"",0) -> #VALUE! | C4: 1 | D4: {=_xlfn._xlws.FILTER('Rel de fornecedores'!G:J,'Rel de fornecedores'!E:E=For_3300!F2)} -> #VALUE! | H4: =IFERROR(VALUE(LEFT(G4,10)),0) -> 0 | I4: =IF(F4="","",IF(COUNTIF($D$4:$D$33,D4)=1,F4,_xlfn.XLOOKUP(MAX($H$4:$H$33),$H$4:$H$33,$F$4:$F$33,0))) | N4: =IF(L4="","Ok",IF(L4="Não","Ok",IF(AND(L4="Sim",M4="Sim"),"Ok","Verificar"))) -> Ok | Q4: =IF(O4="","Ok",IF(O4="Não","Ok",IF(AND(O4="Sim",P4="Sim"),"Ok","Verificar"))) -> Ok | T4: =IF(R4="","Ok",IF(R4="Não","Ok",IF(AND(R4="Sim",S4="Sim"),"Ok","Verificar"))) -> Ok | W4: =IF(U4="","Ok",IF(U4="Não","Ok",IF(AND(U4="Sim",V4="Sim"),"Ok","Verificar"))) -> Ok | Z4: =IF(AND(OR(N4="Ok",N4=""),OR(Q4="Ok",Q4=""),OR(T4="Ok",T4=""),OR(W4="Ok",W4=""),OR(X4="Sim",X4="")),"", "Fornecedor COM perguntas a serem evidenciadas")
A5: 0 | B5: =_xlfn.XLOOKUP(A5,$D$4:$D$33,$I$4:$I$33,"",0) | C5: 2 | I5: =IF(F5="","",IF(COUNTIF($D$4:$D$33,D5)=1,F5,_xlfn.XLOOKUP(MAX($H$4:$H$33),$H$4:$H$33,$F$4:$F$33,0))) | N5: =IF(L5="","Ok",IF(L5="Não","Ok",IF(AND(L5="Sim",M5="Sim"),"Ok","Verificar"))) -> Ok | Q5: =IF(O5="","Ok",IF(O5="Não","Ok",IF(AND(O5="Sim",P5="Sim"),"Ok","Verificar"))) -> Ok | T5: =IF(R5="","Ok",IF(R5="Não","Ok",IF(AND(R5="Sim",S5="Sim"),"Ok","Verificar"))) -> Ok | W5: =IF(U5="","Ok",IF(U5="Não","Ok",IF(AND(U5="Sim",V5="Sim"),"Ok","Verificar"))) -> Ok | Z5: =IF(AND(OR(N5="Ok",N5=""),OR(Q5="Ok",Q5=""),OR(T5="Ok",T5=""),OR(W5="Ok",W5=""),OR(X5="Sim",X5="")),"", "Fornecedor COM perguntas a serem evidenciadas")
B6: =_xlfn.XLOOKUP(A6,$D$4:$D$33,$I$4:$I$33,"",0) | C6: 3 | I6: =IF(F6="","",IF(COUNTIF($D$4:$D$33,D6)=1,F6,_xlfn.XLOOKUP(MAX($H$4:$H$33),$H$4:$H$33,$F$4:$F$33,0))) | N6: =IF(L6="","Ok",IF(L6="Não","Ok",IF(AND(L6="Sim",M6="Sim"),"Ok","Verificar"))) -> Ok | Q6: =IF(O6="","Ok",IF(O6="Não","Ok",IF(AND(O6="Sim",P6="Sim"),"Ok","Verificar"))) -> Ok | T6: =IF(R6="","Ok",IF(R6="Não","Ok",IF(AND(R6="Sim",S6="Sim"),"Ok","Verificar"))) -> Ok | W6: =IF(U6="","Ok",IF(U6="Não","Ok",IF(AND(U6="Sim",V6="Sim"),"Ok","Verificar"))) -> Ok | Z6: =IF(AND(OR(N6="Ok",N6=""),OR(Q6="Ok",Q6=""),OR(T6="Ok",T6=""),OR(W6="Ok",W6=""),OR(X6="Sim",X6="")),"", "Fornecedor COM perguntas a serem evidenciadas")
B7: =_xlfn.XLOOKUP(A7,$D$4:$D$33,$I$4:$I$33,"",0) | C7: 4 | I7: =IF(F7="","",IF(COUNTIF($D$4:$D$33,D7)=1,F7,_xlfn.XLOOKUP(MAX($H$4:$H$33),$H$4:$H$33,$F$4:$F$33,0))) | N7: =IF(L7="","Ok",IF(L7="Não","Ok",IF(AND(L7="Sim",M7="Sim"),"Ok","Verificar"))) -> Ok | Q7: =IF(O7="","Ok",IF(O7="Não","Ok",IF(AND(O7="Sim",P7="Sim"),"Ok","Verificar"))) -> Ok | T7: =IF(R7="","Ok",IF(R7="Não","Ok",IF(AND(R7="Sim",S7="Sim"),"Ok","Verificar"))) -> Ok | W7: =IF(U7="","Ok",IF(U7="Não","Ok",IF(AND(U7="Sim",V7="Sim"),"Ok","Verificar"))) -> Ok | Z7: =IF(AND(OR(N7="Ok",N7=""),OR(Q7="Ok",Q7=""),OR(T7="Ok",T7=""),OR(W7="Ok",W7=""),OR(X7="Sim",X7="")),"", "Fornecedor COM perguntas a serem evidenciadas")
B8: =_xlfn.XLOOKUP(A8,$D$4:$D$33,$I$4:$I$33,"",0) | C8: 5 | I8: =IF(F8="","",IF(COUNTIF($D$4:$D$33,D8)=1,F8,_xlfn.XLOOKUP(MAX($H$4:$H$33),$H$4:$H$33,$F$4:$F$33,0))) | N8: =IF(L8="","Ok",IF(L8="Não","Ok",IF(AND(L8="Sim",M8="Sim"),"Ok","Verificar"))) -> Ok | Q8: =IF(O8="","Ok",IF(O8="Não","Ok",IF(AND(O8="Sim",P8="Sim"),"Ok","Verificar"))) -> Ok | T8: =IF(R8="","Ok",IF(R8="Não","Ok",IF(AND(R8="Sim",S8="Sim"),"Ok","Verificar"))) -> Ok | W8: =IF(U8="","Ok",IF(U8="Não","Ok",IF(AND(U8="Sim",V8="Sim"),"Ok","Verificar"))) -> Ok | Z8: =IF(AND(OR(N8="Ok",N8=""),OR(Q8="Ok",Q8=""),OR(T8="Ok",T8=""),OR(W8="Ok",W8=""),OR(X8="Sim",X8="")),"", "Fornecedor COM perguntas a serem evidenciadas")
B9: =_xlfn.XLOOKUP(A9,$D$4:$D$33,$I$4:$I$33,"",0) | C9: 6 | I9: =IF(F9="","",IF(COUNTIF($D$4:$D$33,D9)=1,F9,_xlfn.XLOOKUP(MAX($H$4:$H$33),$H$4:$H$33,$F$4:$F$33,0))) | N9: =IF(L9="","Ok",IF(L9="Não","Ok",IF(AND(L9="Sim",M9="Sim"),"Ok","Verificar"))) -> Ok | Q9: =IF(O9="","Ok",IF(O9="Não","Ok",IF(AND(O9="Sim",P9="Sim"),"Ok","Verificar"))) -> Ok | T9: =IF(R9="","Ok",IF(R9="Não","Ok",IF(AND(R9="Sim",S9="Sim"),"Ok","Verificar"))) -> Ok | W9: =IF(U9="","Ok",IF(U9="Não","Ok",IF(AND(U9="Sim",V9="Sim"),"Ok","Verificar"))) -> Ok | Z9: =IF(AND(OR(N9="Ok",N9=""),OR(Q9="Ok",Q9=""),OR(T9="Ok",T9=""),OR(W9="Ok",W9=""),OR(X9="Sim",X9="")),"", "Fornecedor COM perguntas a serem evidenciadas")
B10: =_xlfn.XLOOKUP(A10,$D$4:$D$33,$I$4:$I$33,"",0) | C10: 7 | I10: =IF(F10="","",IF(COUNTIF($D$4:$D$33,D10)=1,F10,_xlfn.XLOOKUP(MAX($H$4:$H$33),$H$4:$H$33,$F$4:$F$33,0))) | N10: =IF(L10="","Ok",IF(L10="Não","Ok",IF(AND(L10="Sim",M10="Sim"),"Ok","Verificar"))) -> Ok | Q10: =IF(O10="","Ok",IF(O10="Não","Ok",IF(AND(O10="Sim",P10="Sim"),"Ok","Verificar"))) -> Ok | T10: =IF(R10="","Ok",IF(R10="Não","Ok",IF(AND(R10="Sim",S10="Sim"),"Ok","Verificar"))) -> Ok | W10: =IF(U10="","Ok",IF(U10="Não","Ok",IF(AND(U10="Sim",V10="Sim"),"Ok","Verificar"))) -> Ok | Z10: =IF(AND(OR(N10="Ok",N10=""),OR(Q10="Ok",Q10=""),OR(T10="Ok",T10=""),OR(W10="Ok",W10=""),OR(X10="Sim",X10="")),"", "Fornecedor COM perguntas a serem evidenciadas")
B11: =_xlfn.XLOOKUP(A11,$D$4:$D$33,$I$4:$I$33,"",0) | C11: 8 | I11: =IF(F11="","",IF(COUNTIF($D$4:$D$33,D11)=1,F11,_xlfn.XLOOKUP(MAX($H$4:$H$33),$H$4:$H$33,$F$4:$F$33,0))) | N11: =IF(L11="","Ok",IF(L11="Não","Ok",IF(AND(L11="Sim",M11="Sim"),"Ok","Verificar"))) -> Ok | Q11: =IF(O11="","Ok",IF(O11="Não","Ok",IF(AND(O11="Sim",P11="Sim"),"Ok","Verificar"))) -> Ok | T11: =IF(R11="","Ok",IF(R11="Não","Ok",IF(AND(R11="Sim",S11="Sim"),"Ok","Verificar"))) -> Ok | W11: =IF(U11="","Ok",IF(U11="Não","Ok",IF(AND(U11="Sim",V11="Sim"),"Ok","Verificar"))) -> Ok | Z11: =IF(AND(OR(N11="Ok",N11=""),OR(Q11="Ok",Q11=""),OR(T11="Ok",T11=""),OR(W11="Ok",W11=""),OR(X11="Sim",X11="")),"", "Fornecedor COM perguntas a serem evidenciadas")
B12: =_xlfn.XLOOKUP(A12,$D$4:$D$33,$I$4:$I$33,"",0) | C12: 9 | I12: =IF(F12="","",IF(COUNTIF($D$4:$D$33,D12)=1,F12,_xlfn.XLOOKUP(MAX($H$4:$H$33),$H$4:$H$33,$F$4:$F$33,0))) | N12: =IF(L12="","Ok",IF(L12="Não","Ok",IF(AND(L12="Sim",M12="Sim"),"Ok","Verificar"))) -> Ok | Q12: =IF(O12="","Ok",IF(O12="Não","Ok",IF(AND(O12="Sim",P12="Sim"),"Ok","Verificar"))) -> Ok | T12: =IF(R12="","Ok",IF(R12="Não","Ok",IF(AND(R12="Sim",S12="Sim"),"Ok","Verificar"))) -> Ok | W12: =IF(U12="","Ok",IF(U12="Não","Ok",IF(AND(U12="Sim",V12="Sim"),"Ok","Verificar"))) -> Ok | Z12: =IF(AND(OR(N12="Ok",N12=""),OR(Q12="Ok",Q12=""),OR(T12="Ok",T12=""),OR(W12="Ok",W12=""),OR(X12="Sim",X12="")),"", "Fornecedor COM perguntas a serem evidenciadas")
B13: =_xlfn.XLOOKUP(A13,$D$4:$D$33,$I$4:$I$33,"",0) | C13: 10 | I13: =IF(F13="","",IF(COUNTIF($D$4:$D$33,D13)=1,F13,_xlfn.XLOOKUP(MAX($H$4:$H$33),$H$4:$H$33,$F$4:$F$33,0))) | N13: =IF(L13="","Ok",IF(L13="Não","Ok",IF(AND(L13="Sim",M13="Sim"),"Ok","Verificar"))) -> Ok | Q13: =IF(O13="","Ok",IF(O13="Não","Ok",IF(AND(O13="Sim",P13="Sim"),"Ok","Verificar"))) -> Ok | T13: =IF(R13="","Ok",IF(R13="Não","Ok",IF(AND(R13="Sim",S13="Sim"),"Ok","Verificar"))) -> Ok | W13: =IF(U13="","Ok",IF(U13="Não","Ok",IF(AND(U13="Sim",V13="Sim"),"Ok","Verificar"))) -> Ok | Z13: =IF(AND(OR(N13="Ok",N13=""),OR(Q13="Ok",Q13=""),OR(T13="Ok",T13=""),OR(W13="Ok",W13=""),OR(X13="Sim",X13="")),"", "Fornecedor COM perguntas a serem evidenciadas")
B14: =_xlfn.XLOOKUP(A14,$D$4:$D$33,$I$4:$I$33,"",0) | C14: 11 | I14: =IF(F14="","",IF(COUNTIF($D$4:$D$33,D14)=1,F14,_xlfn.XLOOKUP(MAX($H$4:$H$33),$H$4:$H$33,$F$4:$F$33,0))) | N14: =IF(L14="","Ok",IF(L14="Não","Ok",IF(AND(L14="Sim",M14="Sim"),"Ok","Verificar"))) -> Ok | Q14: =IF(O14="","Ok",IF(O14="Não","Ok",IF(AND(O14="Sim",P14="Sim"),"Ok","Verificar"))) -> Ok | T14: =IF(R14="","Ok",IF(R14="Não","Ok",IF(AND(R14="Sim",S14="Sim"),"Ok","Verificar"))) -> Ok | W14: =IF(U14="","Ok",IF(U14="Não","Ok",IF(AND(U14="Sim",V14="Sim"),"Ok","Verificar"))) -> Ok | Z14: =IF(AND(OR(N14="Ok",N14=""),OR(Q14="Ok",Q14=""),OR(T14="Ok",T14=""),OR(W14="Ok",W14=""),OR(X14="Sim",X14="")),"", "Fornecedor COM perguntas a serem evidenciadas")
B15: =_xlfn.XLOOKUP(A15,$D$4:$D$33,$I$4:$I$33,"",0) | C15: 12 | I15: =IF(F15="","",IF(COUNTIF($D$4:$D$33,D15)=1,F15,_xlfn.XLOOKUP(MAX($H$4:$H$33),$H$4:$H$33,$F$4:$F$33,0))) | N15: =IF(L15="","Ok",IF(L15="Não","Ok",IF(AND(L15="Sim",M15="Sim"),"Ok","Verificar"))) -> Ok | Q15: =IF(O15="","Ok",IF(O15="Não","Ok",IF(AND(O15="Sim",P15="Sim"),"Ok","Verificar"))) -> Ok | T15: =IF(R15="","Ok",IF(R15="Não","Ok",IF(AND(R15="Sim",S15="Sim"),"Ok","Verificar"))) -> Ok | W15: =IF(U15="","Ok",IF(U15="Não","Ok",IF(AND(U15="Sim",V15="Sim"),"Ok","Verificar"))) -> Ok | Z15: =IF(AND(OR(N15="Ok",N15=""),OR(Q15="Ok",Q15=""),OR(T15="Ok",T15=""),OR(W15="Ok",W15=""),OR(X15="Sim",X15="")),"", "Fornecedor COM perguntas a serem evidenciadas")
B16: =_xlfn.XLOOKUP(A16,$D$4:$D$33,$I$4:$I$33,"",0) | C16: 13 | I16: =IF(F16="","",IF(COUNTIF($D$4:$D$33,D16)=1,F16,_xlfn.XLOOKUP(MAX($H$4:$H$33),$H$4:$H$33,$F$4:$F$33,0))) | N16: =IF(L16="","Ok",IF(L16="Não","Ok",IF(AND(L16="Sim",M16="Sim"),"Ok","Verificar"))) -> Ok | Q16: =IF(O16="","Ok",IF(O16="Não","Ok",IF(AND(O16="Sim",P16="Sim"),"Ok","Verificar"))) -> Ok | T16: =IF(R16="","Ok",IF(R16="Não","Ok",IF(AND(R16="Sim",S16="Sim"),"Ok","Verificar"))) -> Ok | W16: =IF(U16="","Ok",IF(U16="Não","Ok",IF(AND(U16="Sim",V16="Sim"),"Ok","Verificar"))) -> Ok | Z16: =IF(AND(OR(N16="Ok",N16=""),OR(Q16="Ok",Q16=""),OR(T16="Ok",T16=""),OR(W16="Ok",W16=""),OR(X16="Sim",X16="")),"", "Fornecedor COM perguntas a serem evidenciadas")
B17: =_xlfn.XLOOKUP(A17,$D$4:$D$33,$I$4:$I$33,"",0) | C17: 14 | I17: =IF(F17="","",IF(COUNTIF($D$4:$D$33,D17)=1,F17,_xlfn.XLOOKUP(MAX($H$4:$H$33),$H$4:$H$33,$F$4:$F$33,0))) | N17: =IF(L17="","Ok",IF(L17="Não","Ok",IF(AND(L17="Sim",M17="Sim"),"Ok","Verificar"))) -> Ok | Q17: =IF(O17="","Ok",IF(O17="Não","Ok",IF(AND(O17="Sim",P17="Sim"),"Ok","Verificar"))) -> Ok | T17: =IF(R17="","Ok",IF(R17="Não","Ok",IF(AND(R17="Sim",S17="Sim"),"Ok","Verificar"))) -> Ok | W17: =IF(U17="","Ok",IF(U17="Não","Ok",IF(AND(U17="Sim",V17="Sim"),"Ok","Verificar"))) -> Ok | Z17: =IF(AND(OR(N17="Ok",N17=""),OR(Q17="Ok",Q17=""),OR(T17="Ok",T17=""),OR(W17="Ok",W17=""),OR(X17="Sim",X17="")),"", "Fornecedor COM perguntas a serem evidenciadas")
B18: =_xlfn.XLOOKUP(A18,$D$4:$D$33,$I$4:$I$33,"",0) | C18: 15 | I18: =IF(F18="","",IF(COUNTIF($D$4:$D$33,D18)=1,F18,_xlfn.XLOOKUP(MAX($H$4:$H$33),$H$4:$H$33,$F$4:$F$33,0))) | N18: =IF(L18="","Ok",IF(L18="Não","Ok",IF(AND(L18="Sim",M18="Sim"),"Ok","Verificar"))) -> Ok | Q18: =IF(O18="","Ok",IF(O18="Não","Ok",IF(AND(O18="Sim",P18="Sim"),"Ok","Verificar"))) -> Ok | T18: =IF(R18="","Ok",IF(R18="Não","Ok",IF(AND(R18="Sim",S18="Sim"),"Ok","Verificar"))) -> Ok | W18: =IF(U18="","Ok",IF(U18="Não","Ok",IF(AND(U18="Sim",V18="Sim"),"Ok","Verificar"))) -> Ok | Z18: =IF(AND(OR(N18="Ok",N18=""),OR(Q18="Ok",Q18=""),OR(T18="Ok",T18=""),OR(W18="Ok",W18=""),OR(X18="Sim",X18="")),"", "Fornecedor COM perguntas a serem evidenciadas")
B19: =_xlfn.XLOOKUP(A19,$D$4:$D$33,$I$4:$I$33,"",0) | C19: 16 | N19: =IF(L19="","Ok",IF(L19="Não","Ok",IF(AND(L19="Sim",M19="Sim"),"Ok","Verificar"))) -> Ok | Q19: =IF(O19="","Ok",IF(O19="Não","Ok",IF(AND(O19="Sim",P19="Sim"),"Ok","Verificar"))) -> Ok | T19: =IF(R19="","Ok",IF(R19="Não","Ok",IF(AND(R19="Sim",S19="Sim"),"Ok","Verificar"))) -> Ok | W19: =IF(U19="","Ok",IF(U19="Não","Ok",IF(AND(U19="Sim",V19="Sim"),"Ok","Verificar"))) -> Ok | Z19: =IF(AND(OR(N19="Ok",N19=""),OR(Q19="Ok",Q19=""),OR(T19="Ok",T19=""),OR(W19="Ok",W19=""),OR(X19="Sim",X19="")),"", "Fornecedor COM perguntas a serem evidenciadas")
B20: =_xlfn.XLOOKUP(A20,$D$4:$D$33,$I$4:$I$33,"",0) | C20: 17 | N20: =IF(L20="","Ok",IF(L20="Não","Ok",IF(AND(L20="Sim",M20="Sim"),"Ok","Verificar"))) -> Ok | Q20: =IF(O20="","Ok",IF(O20="Não","Ok",IF(AND(O20="Sim",P20="Sim"),"Ok","Verificar"))) -> Ok | T20: =IF(R20="","Ok",IF(R20="Não","Ok",IF(AND(R20="Sim",S20="Sim"),"Ok","Verificar"))) -> Ok | W20: =IF(U20="","Ok",IF(U20="Não","Ok",IF(AND(U20="Sim",V20="Sim"),"Ok","Verificar"))) -> Ok | Z20: =IF(AND(OR(N20="Ok",N20=""),OR(Q20="Ok",Q20=""),OR(T20="Ok",T20=""),OR(W20="Ok",W20=""),OR(X20="Sim",X20="")),"", "Fornecedor COM perguntas a serem evidenciadas")
B21: =_xlfn.XLOOKUP(A21,$D$4:$D$33,$I$4:$I$33,"",0) | C21: 18 | I21: =IF(F21="","",IF(COUNTIF($D$4:$D$33,D21)=1,F21,_xlfn.XLOOKUP(MAX($H$4:$H$33),$H$4:$H$33,$F$4:$F$33,0))) | N21: =IF(L21="","Ok",IF(L21="Não","Ok",IF(AND(L21="Sim",M21="Sim"),"Ok","Verificar"))) -> Ok | Q21: =IF(O21="","Ok",IF(O21="Não","Ok",IF(AND(O21="Sim",P21="Sim"),"Ok","Verificar"))) -> Ok | T21: =IF(R21="","Ok",IF(R21="Não","Ok",IF(AND(R21="Sim",S21="Sim"),"Ok","Verificar"))) -> Ok | W21: =IF(U21="","Ok",IF(U21="Não","Ok",IF(AND(U21="Sim",V21="Sim"),"Ok","Verificar"))) -> Ok | Z21: =IF(AND(OR(N21="Ok",N21=""),OR(Q21="Ok",Q21=""),OR(T21="Ok",T21=""),OR(W21="Ok",W21=""),OR(X21="Sim",X21="")),"", "Fornecedor COM perguntas a serem evidenciadas")
B22: =_xlfn.XLOOKUP(A22,$D$4:$D$33,$I$4:$I$33,"",0) | C22: 19 | I22: =IF(F22="","",IF(COUNTIF($D$4:$D$33,D22)=1,F22,_xlfn.XLOOKUP(MAX($H$4:$H$33),$H$4:$H$33,$F$4:$F$33,0))) | N22: =IF(L22="","Ok",IF(L22="Não","Ok",IF(AND(L22="Sim",M22="Sim"),"Ok","Verificar"))) -> Ok | Q22: =IF(O22="","Ok",IF(O22="Não","Ok",IF(AND(O22="Sim",P22="Sim"),"Ok","Verificar"))) -> Ok | T22: =IF(R22="","Ok",IF(R22="Não","Ok",IF(AND(R22="Sim",S22="Sim"),"Ok","Verificar"))) -> Ok | W22: =IF(U22="","Ok",IF(U22="Não","Ok",IF(AND(U22="Sim",V22="Sim"),"Ok","Verificar"))) -> Ok | Z22: =IF(AND(OR(N22="Ok",N22=""),OR(Q22="Ok",Q22=""),OR(T22="Ok",T22=""),OR(W22="Ok",W22=""),OR(X22="Sim",X22="")),"", "Fornecedor COM perguntas a serem evidenciadas")
B23: =_xlfn.XLOOKUP(A23,$D$4:$D$33,$I$4:$I$33,"",0) | C23: 20 | I23: =IF(F23="","",IF(COUNTIF($D$4:$D$33,D23)=1,F23,_xlfn.XLOOKUP(MAX($H$4:$H$33),$H$4:$H$33,$F$4:$F$33,0))) | N23: =IF(L23="","Ok",IF(L23="Não","Ok",IF(AND(L23="Sim",M23="Sim"),"Ok","Verificar"))) -> Ok | Q23: =IF(O23="","Ok",IF(O23="Não","Ok",IF(AND(O23="Sim",P23="Sim"),"Ok","Verificar"))) -> Ok | T23: =IF(R23="","Ok",IF(R23="Não","Ok",IF(AND(R23="Sim",S23="Sim"),"Ok","Verificar"))) -> Ok | W23: =IF(U23="","Ok",IF(U23="Não","Ok",IF(AND(U23="Sim",V23="Sim"),"Ok","Verificar"))) -> Ok | Z23: =IF(AND(OR(N23="Ok",N23=""),OR(Q23="Ok",Q23=""),OR(T23="Ok",T23=""),OR(W23="Ok",W23=""),OR(X23="Sim",X23="")),"", "Fornecedor COM perguntas a serem evidenciadas")
B24: =_xlfn.XLOOKUP(A24,$D$4:$D$33,$I$4:$I$33,"",0) | C24: 21 | I24: =IF(F24="","",IF(COUNTIF($D$4:$D$33,D24)=1,F24,_xlfn.XLOOKUP(MAX($H$4:$H$33),$H$4:$H$33,$F$4:$F$33,0))) | N24: =IF(L24="","Ok",IF(L24="Não","Ok",IF(AND(L24="Sim",M24="Sim"),"Ok","Verificar"))) -> Ok | Q24: =IF(O24="","Ok",IF(O24="Não","Ok",IF(AND(O24="Sim",P24="Sim"),"Ok","Verificar"))) -> Ok | T24: =IF(R24="","Ok",IF(R24="Não","Ok",IF(AND(R24="Sim",S24="Sim"),"Ok","Verificar"))) -> Ok | W24: =IF(U24="","Ok",IF(U24="Não","Ok",IF(AND(U24="Sim",V24="Sim"),"Ok","Verificar"))) -> Ok | Z24: =IF(AND(OR(N24="Ok",N24=""),OR(Q24="Ok",Q24=""),OR(T24="Ok",T24=""),OR(W24="Ok",W24=""),OR(X24="Sim",X24="")),"", "Fornecedor COM perguntas a serem evidenciadas")
B25: =_xlfn.XLOOKUP(A25,$D$4:$D$33,$I$4:$I$33,"",0) | C25: 22 | I25: =IF(F25="","",IF(COUNTIF($D$4:$D$33,D25)=1,F25,_xlfn.XLOOKUP(MAX($H$4:$H$33),$H$4:$H$33,$F$4:$F$33,0))) | N25: =IF(L25="","Ok",IF(L25="Não","Ok",IF(AND(L25="Sim",M25="Sim"),"Ok","Verificar"))) -> Ok | Q25: =IF(O25="","Ok",IF(O25="Não","Ok",IF(AND(O25="Sim",P25="Sim"),"Ok","Verificar"))) -> Ok | T25: =IF(R25="","Ok",IF(R25="Não","Ok",IF(AND(R25="Sim",S25="Sim"),"Ok","Verificar"))) -> Ok | W25: =IF(U25="","Ok",IF(U25="Não","Ok",IF(AND(U25="Sim",V25="Sim"),"Ok","Verificar"))) -> Ok | Z25: =IF(AND(OR(N25="Ok",N25=""),OR(Q25="Ok",Q25=""),OR(T25="Ok",T25=""),OR(W25="Ok",W25=""),OR(X25="Sim",X25="")),"", "Fornecedor COM perguntas a serem evidenciadas")
B26: =_xlfn.XLOOKUP(A26,$D$4:$D$33,$I$4:$I$33,"",0) | C26: 23 | I26: =IF(F26="","",IF(COUNTIF($D$4:$D$33,D26)=1,F26,_xlfn.XLOOKUP(MAX($H$4:$H$33),$H$4:$H$33,$F$4:$F$33,0))) | N26: =IF(L26="","Ok",IF(L26="Não","Ok",IF(AND(L26="Sim",M26="Sim"),"Ok","Verificar"))) -> Ok | Q26: =IF(O26="","Ok",IF(O26="Não","Ok",IF(AND(O26="Sim",P26="Sim"),"Ok","Verificar"))) -> Ok | T26: =IF(R26="","Ok",IF(R26="Não","Ok",IF(AND(R26="Sim",S26="Sim"),"Ok","Verificar"))) -> Ok | W26: =IF(U26="","Ok",IF(U26="Não","Ok",IF(AND(U26="Sim",V26="Sim"),"Ok","Verificar"))) -> Ok | Z26: =IF(AND(OR(N26="Ok",N26=""),OR(Q26="Ok",Q26=""),OR(T26="Ok",T26=""),OR(W26="Ok",W26=""),OR(X26="Sim",X26="")),"", "Fornecedor COM perguntas a serem evidenciadas")
B27: =_xlfn.XLOOKUP(A27,$D$4:$D$33,$I$4:$I$33,"",0) | C27: 24 | I27: =IF(F27="","",IF(COUNTIF($D$4:$D$33,D27)=1,F27,_xlfn.XLOOKUP(MAX($H$4:$H$33),$H$4:$H$33,$F$4:$F$33,0))) | N27: =IF(L27="","Ok",IF(L27="Não","Ok",IF(AND(L27="Sim",M27="Sim"),"Ok","Verificar"))) -> Ok | Q27: =IF(O27="","Ok",IF(O27="Não","Ok",IF(AND(O27="Sim",P27="Sim"),"Ok","Verificar"))) -> Ok | T27: =IF(R27="","Ok",IF(R27="Não","Ok",IF(AND(R27="Sim",S27="Sim"),"Ok","Verificar"))) -> Ok | W27: =IF(U27="","Ok",IF(U27="Não","Ok",IF(AND(U27="Sim",V27="Sim"),"Ok","Verificar"))) -> Ok | Z27: =IF(AND(OR(N27="Ok",N27=""),OR(Q27="Ok",Q27=""),OR(T27="Ok",T27=""),OR(W27="Ok",W27=""),OR(X27="Sim",X27="")),"", "Fornecedor COM perguntas a serem evidenciadas")
B28: =_xlfn.XLOOKUP(A28,$D$4:$D$33,$I$4:$I$33,"",0) | C28: 25 | I28: =IF(F28="","",IF(COUNTIF($D$4:$D$33,D28)=1,F28,_xlfn.XLOOKUP(MAX($H$4:$H$33),$H$4:$H$33,$F$4:$F$33,0))) | N28: =IF(L28="","Ok",IF(L28="Não","Ok",IF(AND(L28="Sim",M28="Sim"),"Ok","Verificar"))) -> Ok | Q28: =IF(O28="","Ok",IF(O28="Não","Ok",IF(AND(O28="Sim",P28="Sim"),"Ok","Verificar"))) -> Ok | T28: =IF(R28="","Ok",IF(R28="Não","Ok",IF(AND(R28="Sim",S28="Sim"),"Ok","Verificar"))) -> Ok | W28: =IF(U28="","Ok",IF(U28="Não","Ok",IF(AND(U28="Sim",V28="Sim"),"Ok","Verificar"))) -> Ok | Z28: =IF(AND(OR(N28="Ok",N28=""),OR(Q28="Ok",Q28=""),OR(T28="Ok",T28=""),OR(W28="Ok",W28=""),OR(X28="Sim",X28="")),"", "Fornecedor COM perguntas a serem evidenciadas")
B29: =_xlfn.XLOOKUP(A29,$D$4:$D$33,$I$4:$I$33,"",0) | C29: 26 | I29: =IF(F29="","",IF(COUNTIF($D$4:$D$33,D29)=1,F29,_xlfn.XLOOKUP(MAX($H$4:$H$33),$H$4:$H$33,$F$4:$F$33,0))) | N29: =IF(L29="","Ok",IF(L29="Não","Ok",IF(AND(L29="Sim",M29="Sim"),"Ok","Verificar"))) -> Ok | Q29: =IF(O29="","Ok",IF(O29="Não","Ok",IF(AND(O29="Sim",P29="Sim"),"Ok","Verificar"))) -> Ok | T29: =IF(R29="","Ok",IF(R29="Não","Ok",IF(AND(R29="Sim",S29="Sim"),"Ok","Verificar"))) -> Ok | W29: =IF(U29="","Ok",IF(U29="Não","Ok",IF(AND(U29="Sim",V29="Sim"),"Ok","Verificar"))) -> Ok | Z29: =IF(AND(OR(N29="Ok",N29=""),OR(Q29="Ok",Q29=""),OR(T29="Ok",T29=""),OR(W29="Ok",W29=""),OR(X29="Sim",X29="")),"", "Fornecedor COM perguntas a serem evidenciadas")
B30: =_xlfn.XLOOKUP(A30,$D$4:$D$33,$I$4:$I$33,"",0) | C30: 27 | I30: =IF(F30="","",IF(COUNTIF($D$4:$D$33,D30)=1,F30,_xlfn.XLOOKUP(MAX($H$4:$H$33),$H$4:$H$33,$F$4:$F$33,0))) | N30: =IF(L30="","Ok",IF(L30="Não","Ok",IF(AND(L30="Sim",M30="Sim"),"Ok","Verificar"))) -> Ok | Q30: =IF(O30="","Ok",IF(O30="Não","Ok",IF(AND(O30="Sim",P30="Sim"),"Ok","Verificar"))) -> Ok | T30: =IF(R30="","Ok",IF(R30="Não","Ok",IF(AND(R30="Sim",S30="Sim"),"Ok","Verificar"))) -> Ok | W30: =IF(U30="","Ok",IF(U30="Não","Ok",IF(AND(U30="Sim",V30="Sim"),"Ok","Verificar"))) -> Ok | Z30: =IF(AND(OR(N30="Ok",N30=""),OR(Q30="Ok",Q30=""),OR(T30="Ok",T30=""),OR(W30="Ok",W30=""),OR(X30="Sim",X30="")),"", "Fornecedor COM perguntas a serem evidenciadas")
B31: =_xlfn.XLOOKUP(A31,$D$4:$D$33,$I$4:$I$33,"",0) | C31: 28 | I31: =IF(F31="","",IF(COUNTIF($D$4:$D$33,D31)=1,F31,_xlfn.XLOOKUP(MAX($H$4:$H$33),$H$4:$H$33,$F$4:$F$33,0))) | N31: =IF(L31="","Ok",IF(L31="Não","Ok",IF(AND(L31="Sim",M31="Sim"),"Ok","Verificar"))) -> Ok | Q31: =IF(O31="","Ok",IF(O31="Não","Ok",IF(AND(O31="Sim",P31="Sim"),"Ok","Verificar"))) -> Ok | T31: =IF(R31="","Ok",IF(R31="Não","Ok",IF(AND(R31="Sim",S31="Sim"),"Ok","Verificar"))) -> Ok | W31: =IF(U31="","Ok",IF(U31="Não","Ok",IF(AND(U31="Sim",V31="Sim"),"Ok","Verificar"))) -> Ok | Z31: =IF(AND(OR(N31="Ok",N31=""),OR(Q31="Ok",Q31=""),OR(T31="Ok",T31=""),OR(W31="Ok",W31=""),OR(X31="Sim",X31="")),"", "Fornecedor COM perguntas a serem evidenciadas")
B32: =_xlfn.XLOOKUP(A32,$D$4:$D$33,$I$4:$I$33,"",0) | C32: 29 | I32: =IF(F32="","",IF(COUNTIF($D$4:$D$33,D32)=1,F32,_xlfn.XLOOKUP(MAX($H$4:$H$33),$H$4:$H$33,$F$4:$F$33,0))) | N32: =IF(L32="","Ok",IF(L32="Não","Ok",IF(AND(L32="Sim",M32="Sim"),"Ok","Verificar"))) -> Ok | Q32: =IF(O32="","Ok",IF(O32="Não","Ok",IF(AND(O32="Sim",P32="Sim"),"Ok","Verificar"))) -> Ok | T32: =IF(R32="","Ok",IF(R32="Não","Ok",IF(AND(R32="Sim",S32="Sim"),"Ok","Verificar"))) -> Ok | W32: =IF(U32="","Ok",IF(U32="Não","Ok",IF(AND(U32="Sim",V32="Sim"),"Ok","Verificar"))) -> Ok | Z32: =IF(AND(OR(N32="Ok",N32=""),OR(Q32="Ok",Q32=""),OR(T32="Ok",T32=""),OR(W32="Ok",W32=""),OR(X32="Sim",X32="")),"", "Fornecedor COM perguntas a serem evidenciadas")
B33: =_xlfn.XLOOKUP(A33,$D$4:$D$33,$I$4:$I$33,"",0) | C33: 30 | I33: =IF(F33="","",IF(COUNTIF($D$4:$D$33,D33)=1,F33,_xlfn.XLOOKUP(MAX($H$4:$H$33),$H$4:$H$33,$F$4:$F$33,0))) | N33: =IF(L33="","Ok",IF(L33="Não","Ok",IF(AND(L33="Sim",M33="Sim"),"Ok","Verificar"))) -> Ok | Q33: =IF(O33="","Ok",IF(O33="Não","Ok",IF(AND(O33="Sim",P33="Sim"),"Ok","Verificar"))) -> Ok | T33: =IF(R33="","Ok",IF(R33="Não","Ok",IF(AND(R33="Sim",S33="Sim"),"Ok","Verificar"))) -> Ok | W33: =IF(U33="","Ok",IF(U33="Não","Ok",IF(AND(U33="Sim",V33="Sim"),"Ok","Verificar"))) -> Ok | Z33: =IF(AND(OR(N33="Ok",N33=""),OR(Q33="Ok",Q33=""),OR(T33="Ok",T33=""),OR(W33="Ok",W33=""),OR(X33="Sim",X33="")),"", "Fornecedor COM perguntas a serem evidenciadas")

Sheet A3056
B2: Risco Social Ambiental e Climático (3056) | H2: Retorno
B3: =I8 -> 46023 | C3: BAIXO RISCO | D3: MÉDIO RISCO | E3: ALTO RISCO | O3: Pergunta 01: A atividade está sujeita ao licenciamento ambiental conforme Resolução CONAMA n° 237/1997 ou normativo estadual / Municipal, se houver? Se sim, declara possuir o licenciamento necessário vigente? A empresa trabalha com equipamentos e sistemas destinados ao armazenamento e a distribuição de combustíveis automotivos, assim como sua montagem e instalação? | R3: Pergunta 02: Declara que há a compensação da Reserva Legal em outra Propriedade? | V3: Pergunta 03: O uso da água na área de produção e/ou construção está em conformidade com as normas de utilização de recursos hídricos (Lei n° 9.433/1997?)? | Z3: Pergunta 04: Possui débitos trabalhistas inadimplidos perante a Justiça do Trabalho? A Certidão negativa de débitos trabalhistas está anexada na Plataforma de Atendimento? | AD3: Pergunta 05: Quanto há infrações ou embargos de ordem ambiental e/ou social, o infrator poderá firmar o TAC (Termo de Ajustamento de Conduta) para regularização. Nos últimos 5 anos, as atividades da empresa/produtor rural foram objeto de inquérito, multa, auto de infração ou TAC em decorrência de questões sociais ou ambientais? | AH3: Pergunta 06: O questionário está datado e assinado de forma adequada e anexado na plataforma de atendimento? | AJ3: Pergunta 07: Verificação dos planos de ações.
B4: =IF(SUM(C4:E4)=0,"Não apresentou cooperados avaliados ",IF(SUM(C4:E4)=1,"TOTAL: 01 Coperado elegível ao RSAC","TOTAL: "&SUM(C4:E4)&" Cooperados avaliados ao RSAC")) -> TOTAL: 15 Cooperados avaliados ao RSAC | C4: 13 | D4: =SUM(M:M) -> 0 | E4: =SUM(N:N) -> 2
B5: Setor Sensível
B6: Resultado | C6: Limite | D6: Situação
B7: =SUM('Setor_S 3056'!L:L) -> 0.00019725333 | C7: 0.15 | D7: =IF(B7<C7,"ENQUADRADO","DESENQUADRADO") -> ENQUADRADO | H7: Singular 3056 - Detalhamento do Mês | L7: Baixo | M7: Médio | N7: Alto
B8: Quantidade de fornecedores cadastrados no Sistema | H8: Data Base | I8: ='Análise Efetuada'!G9 -> 46023 | J8: {=_xlfn.XLOOKUP(_xlfn.UNIQUE('3056'!$C:$C),'3056'!C:C,'3056'!D:D,"")} -> 0
B9: TOTAL DE FORNECEDORES | C9: BAIXO RISCO | D9: MÉDIO RISCO | E9: ALTO RISCO | H9: CNAE | I9: CNPJ | J9: Nome/Razão Social | K9: Data da avaliação | O9: O CNAE está sujeito? | P9: Colocou a evidencia? | Q9: Resultado Pergunta 01 | R9: Qual foi a resposta do quest.? | S9: Precisa de evidencia? | T9: Colocou a evidencia? | U9: Resultado Pergunta 02 | V9: Qual foi a resposta do quest.? | W9: Precisa de outorga? | X9: Colocou a evidencia? | Y9: Resultado Pergunta 03 | Z9: Qual foi a resposta do quest.? | AA9: Precisa da certidão? | AB9: Colocou a evidencia? | AC9: Resultado Pergunta 04 | AD9: Qual foi a resposta do quest.? | AE9: Precisa da comprovação? | AF9: Colocou a evidencia? | AG9: Resultado Pergunta 05 | AH9: O questionário está datadado e assinado e anexado? | AI9: Resultado Pergunta 06 | AJ9: A avaliação é de Alto Risco? | AK9: Qual o motivo da avaliação de Alto Risco? | AL9: Foi feito o cadastro do Plano de ação na PGPC? | AM9: Resultado Pergunta 07 | AO9: Arrastar a fórmula, conforme necessário
B10: =SUM(C10:E10) -> 0 | C10: ='Análise Fornecedores'!G21 -> 0 | D10: ='Análise Fornecedores'!H21 -> 0 | E10: ='Análise Fornecedores'!I21 -> 0 | H10: A0115600 - Cultivo de soja | I10: =_xlfn.XLOOKUP(J10,'3056'!$D:$D,'3056'!$C:$C,0,0) -> 009.817.641-26 | J10: BRUNA OTILIA GUARESCHI BARION | K10: {=MAX(IF(J10='3056'!$D:$D,'3056'!$I:$I))} -> 46051 | M10: =IF(COUNTIFS('3056'!$D:$D,'A3056'!J10,'3056'!$I:$I,'A3056'!K10,'3056'!$F:$F,'A3056'!$M$7)>=1,1,0) -> 0 | Q10: =IF(AND(O10="Sim")*OR(P10="Não",P10="Não se aplica",P10=""),"Verificar","Ok") -> Ok | U10: =IF(AND(R10="Sim",T10="Siim"),"Ok",IF(AND(S10="Sim")*OR(T10="Não",T10="Não se aplica",T10=""),"Verificar","Ok")) -> Ok | Y10: =IF(AND(V10="Sim",X10="Siim"),"Ok",IF(AND(W10="Sim")*OR(X10="Não",X10="Não se aplica",X10=""),"Verificar","Ok")) -> Ok | Z10: Não | AA10: Sim | AB10: Não | AC10: =IF(AND(Z10="Sim",AB10="Siim"),"Ok",IF(AND(AA10="Sim")*OR(AB10="Não",AB10="Não se aplica",AB10=""),"Verificar","Ok")) -> Verificar | AG10: =IF(AND(AE10="sim",AF10="Não"),"Verificar","Ok") -> Ok | AH10: Não | AI10: =IF(AH10="Não","Verificar","Ok") -> Verificar | AJ10: =IF(N10=1,"Sim, precisa de plano cadastrado na PGPC", "Não") -> Não | AL10: Sim | AM10: =IF(OR(AL10=" ",AL10="Sim"),"Ok",IF(AJ10="Não","Ok","Verificar")) -> Ok | AO10: =IF(AND(Q10="Ok",U10="Ok",Y10="Ok",AC10="Ok",AG10="Ok",AI10="Ok",AM10="Ok"),"Cooperado SEM perguntas a serem evidenciadas","Cooperado COM perguntas a serem evidenciadas") -> Cooperado COM perguntas a serem evidenciadas
B11: Perguntas que precisam ser evidenciadas do questionário dos fornecedores: | H11: A0151201 - Criação de bovinos para corte | I11: =_xlfn.XLOOKUP(J11,'3056'!$D:$D,'3056'!$C:$C,0,0) -> 015.678.951-58 | J11: THIAGO VINICIUS DE BRITO MIRANDA | K11: {=MAX(IF(J11='3056'!$D:$D,'3056'!$I:$I))} -> 46028 | L11: =IF(COUNTIFS('3056'!$D:$D,'A3056'!J11,'3056'!$I:$I,'A3056'!K11,'3056'!$F:$F,'A3056'!$L$7)>=1,1,0) -> 1 | M11: =IF(COUNTIFS('3056'!$D:$D,'A3056'!J11,'3056'!$I:$I,'A3056'!K11,'3056'!$F:$F,'A3056'!$M$7)>=1,1,0) -> 0 | N11: =IF(COUNTIFS('3056'!$D:$D,'A3056'!J11,'3056'!$I:$I,'A3056'!K11,'3056'!$F:$F,'A3056'!$N$7)>=1,1,0) -> 0 | Q11: =IF(AND(O11="Sim")*OR(P11="Não",P11="Não se aplica",P11=""),"Verificar","Ok") -> Ok | U11: =IF(AND(R11="Sim",T11="Siim"),"Ok",IF(AND(S11="Sim")*OR(T11="Não",T11="Não se aplica",T11=""),"Verificar","Ok")) -> Ok | Y11: =IF(AND(V11="Sim",X11="Siim"),"Ok",IF(AND(W11="Sim")*OR(X11="Não",X11="Não se aplica",X11=""),"Verificar","Ok")) -> Ok | AC11: =IF(AND(Z11="Sim",AB11="Siim"),"Ok",IF(AND(AA11="Sim")*OR(AB11="Não",AB11="Não se aplica",AB11=""),"Verificar","Ok")) -> Ok | AG11: =IF(AND(AE11="sim",AF11="Não"),"Verificar","Ok") -> Ok | AI11: =IF(AH11="Não","Verificar","Ok") -> Ok | AJ11: =IF(N11=1,"Sim, precisa de plano cadastrado na PGPC", "Não") -> Não | AM11: =IF(OR(AL11=" ",AL11="Sim"),"Ok",IF(AJ11="Não","Ok","Verificar")) -> Ok | AO11: =IF(AND(Q11="Ok",U11="Ok",Y11="Ok",AC11="Ok",AG11="Ok",AI11="Ok",AM11="Ok"),"Cooperado SEM perguntas a serem evidenciadas","Cooperado COM perguntas a serem evidenciadas") -> Cooperado SEM perguntas a serem evidenciadas
B12: Fornecedor | C12: Pergunta | H12: G4683400 - Comércio atacadista de defensivos agrícolas, adubos, fertilizantes e corretivo | I12: =_xlfn.XLOOKUP(J12,'3056'!$D:$D,'3056'!$C:$C,0,0) -> 05.597.933/0001-21 | J12: PONTO FORTE COMERCIO E REPRESENTACAO DE INSUMOS AGROPECUARIOS LTDA | K12: {=MAX(IF(J12='3056'!$D:$D,'3056'!$I:$I))} -> 46036 | L12: =IF(COUNTIFS('3056'!$D:$D,'A3056'!J12,'3056'!$I:$I,'A3056'!K12,'3056'!$F:$F,'A3056'!$L$7)>=1,1,0) -> 1 | M12: =IF(COUNTIFS('3056'!$D:$D,'A3056'!J12,'3056'!$I:$I,'A3056'!K12,'3056'!$F:$F,'A3056'!$M$7)>=1,1,0) -> 0 | N12: =IF(COUNTIFS('3056'!$D:$D,'A3056'!J12,'3056'!$I:$I,'A3056'!K12,'3056'!$F:$F,'A3056'!$N$7)>=1,1,0) -> 0 | Q12: =IF(AND(O12="Sim")*OR(P12="Não",P12="Não se aplica",P12=""),"Verificar","Ok") -> Ok | U12: =IF(AND(R12="Sim",T12="Siim"),"Ok",IF(AND(S12="Sim")*OR(T12="Não",T12="Não se aplica",T12=""),"Verificar","Ok")) -> Ok | Y12: =IF(AND(V12="Sim",X12="Siim"),"Ok",IF(AND(W12="Sim")*OR(X12="Não",X12="Não se aplica",X12=""),"Verificar","Ok")) -> Ok | AC12: =IF(AND(Z12="Sim",AB12="Siim"),"Ok",IF(AND(AA12="Sim")*OR(AB12="Não",AB12="Não se aplica",AB12=""),"Verificar","Ok")) -> Ok | AG12: =IF(AND(AE12="sim",AF12="Não"),"Verificar","Ok") -> Ok | AI12: =IF(AH12="Não","Verificar","Ok") -> Ok | AJ12: =IF(N12=1,"Sim, precisa de plano cadastrado na PGPC", "Não") -> Não | AM12: =IF(OR(AL12=" ",AL12="Sim"),"Ok",IF(AJ12="Não","Ok","Verificar")) -> Ok | AO12: =IF(AND(Q12="Ok",U12="Ok",Y12="Ok",AC12="Ok",AG12="Ok",AI12="Ok",AM12="Ok"),"Cooperado SEM perguntas a serem evidenciadas","Cooperado COM perguntas a serem evidenciadas") -> Cooperado SEM perguntas a serem evidenciadas
A13: =IFERROR(IF(ROW(_xlfn.XLOOKUP(B13,For_3056!D:D,For_3056!D:D))=1,"",ROW(_xlfn.XLOOKUP(B13,For_3056!D:D,For_3056!D:D))),"") | B13: {=_xlfn.UNIQUE(IF(_xlfn._xlws.FILTER(For_3056!D:D,For_3056!Z:Z="Fornecedor COM perguntas a serem evidenciadas","")="","",_xlfn._xlws.FILTER(For_3056!D:D,For_3056!Z:Z:'For_3056'!Z:Z="Fornecedor COM perguntas a serem evidenciadas","")))} | C13: {=IFERROR(LEFT( IF(INDIRECT("For_3056!N"&A13)="verificar","6, ","")& IF(INDIRECT("For_3056!q"&A13)="verificar","7, ","")& IF(INDIRECT("For_3056!t"&A13)="verificar","8, ","")& IF(INDIRECT("For_3056!w"&A13)="verificar","16, ","")& IF(INDIRECT("For_3056!x"&A13)="não","QUESTIONÁRIO, ",""), LEN( IF(INDIRECT("For_3056!N"&A13)="verificar","6, ","")& IF(INDIRECT("For_3056!q"&A13)="verificar","7, ","")& IF(INDIRECT("For_3056!t"&A13)="verificar","8, ","")& IF(INDIRECT("For_3056!w"&A13)="verificar","16, ","")& IF(INDIRECT("For_3056!x"&A13)="não","QUESTIONÁRIO, ",""))-2)&".","")} | H13: A0151201 - Criação de bovinos para corte | I13: =_xlfn.XLOOKUP(J13,'3056'!$D:$D,'3056'!$C:$C,0,0) -> 134.426.781-53 | J13: ODEIR GUINUAR DE CARVALHO | K13: {=MAX(IF(J13='3056'!$D:$D,'3056'!$I:$I))} -> 46026 | L13: =IF(COUNTIFS('3056'!$D:$D,'A3056'!J13,'3056'!$I:$I,'A3056'!K13,'3056'!$F:$F,'A3056'!$L$7)>=1,1,0) -> 1 | M13: =IF(COUNTIFS('3056'!$D:$D,'A3056'!J13,'3056'!$I:$I,'A3056'!K13,'3056'!$F:$F,'A3056'!$M$7)>=1,1,0) -> 0 | N13: =IF(COUNTIFS('3056'!$D:$D,'A3056'!J13,'3056'!$I:$I,'A3056'!K13,'3056'!$F:$F,'A3056'!$N$7)>=1,1,0) -> 0 | Q13: =IF(AND(O13="Sim")*OR(P13="Não",P13="Não se aplica",P13=""),"Verificar","Ok") -> Ok | U13: =IF(AND(R13="Sim",T13="Siim"),"Ok",IF(AND(S13="Sim")*OR(T13="Não",T13="Não se aplica",T13=""),"Verificar","Ok")) -> Ok | Y13: =IF(AND(V13="Sim",X13="Siim"),"Ok",IF(AND(W13="Sim")*OR(X13="Não",X13="Não se aplica",X13=""),"Verificar","Ok")) -> Ok | AC13: =IF(AND(Z13="Sim",AB13="Siim"),"Ok",IF(AND(AA13="Sim")*OR(AB13="Não",AB13="Não se aplica",AB13=""),"Verificar","Ok")) -> Ok | AG13: =IF(AND(AE13="sim",AF13="Não"),"Verificar","Ok") -> Ok | AI13: =IF(AH13="Não","Verificar","Ok") -> Ok | AJ13: =IF(N13=1,"Sim, precisa de plano cadastrado na PGPC", "Não") -> Não | AM13: =IF(OR(AL13=" ",AL13="Sim"),"Ok",IF(AJ13="Não","Ok","Verificar")) -> Ok | AO13: =IF(AND(Q13="Ok",U13="Ok",Y13="Ok",AC13="Ok",AG13="Ok",AI13="Ok",AM13="Ok"),"Cooperado SEM perguntas a serem evidenciadas","Cooperado COM perguntas a serem evidenciadas") -> Cooperado SEM perguntas a serem evidenciadas
A14: =IFERROR(IF(ROW(_xlfn.XLOOKUP(B14,For_3056!D:D,For_3056!D:D))=1,"",ROW(_xlfn.XLOOKUP(B14,For_3056!D:D,For_3056!D:D))),"") | B14: {=_xlfn.UNIQUE(IF(_xlfn._xlws.FILTER(For_3056!D:D,For_3056!Z:Z="Fornecedor COM perguntas a serem evidenciadas","")="","",_xlfn._xlws.FILTER(For_3056!D:D,For_3056!Z:Z:'For_3056'!Z:Z="Fornecedor COM perguntas a serem evidenciadas","")))} | C14: {=IFERROR(LEFT( IF(INDIRECT("For_3056!N"&A14)="verificar","6, ","")& IF(INDIRECT("For_3056!q"&A14)="verificar","7, ","")& IF(INDIRECT("For_3056!t"&A14)="verificar","8, ","")& IF(INDIRECT("For_3056!w"&A14)="verificar","16, ","")& IF(INDIRECT("For_3056!x"&A14)="não","QUESTIONÁRIO, ",""), LEN( IF(INDIRECT("For_3056!N"&A14)="verificar","6, ","")& IF(INDIRECT("For_3056!q"&A14)="verificar","7, ","")& IF(INDIRECT("For_3056!t"&A14)="verificar","8, ","")& IF(INDIRECT("For_3056!w"&A14)="verificar","16, ","")& IF(INDIRECT("For_3056!x"&A14)="não","QUESTIONÁRIO, ",""))-2)&".","")} | H14: A0133404 - Cultivo de cítricos, exceto laranja | I14: =_xlfn.XLOOKUP(J14,'3056'!$D:$D,'3056'!$C:$C,0,0) -> 234.262.501-44 | J14: MARCOS REZENDE SOUZA | K14: {=MAX(IF(J14='3056'!$D:$D,'3056'!$I:$I))} -> 46049 | L14: =IF(COUNTIFS('3056'!$D:$D,'A3056'!J14,'3056'!$I:$I,'A3056'!K14,'3056'!$F:$F,'A3056'!$L$7)>=1,1,0) -> 1 | M14: =IF(COUNTIFS('3056'!$D:$D,'A3056'!J14,'3056'!$I:$I,'A3056'!K14,'3056'!$F:$F,'A3056'!$M$7)>=1,1,0) -> 0 | N14: =IF(COUNTIFS('3056'!$D:$D,'A3056'!J14,'3056'!$I:$I,'A3056'!K14,'3056'!$F:$F,'A3056'!$N$7)>=1,1,0) -> 0 | Q14: =IF(AND(O14="Sim")*OR(P14="Não",P14="Não se aplica",P14=""),"Verificar","Ok") -> Ok | U14: =IF(AND(R14="Sim",T14="Siim"),"Ok",IF(AND(S14="Sim")*OR(T14="Não",T14="Não se aplica",T14=""),"Verificar","Ok")) -> Ok | Y14: =IF(AND(V14="Sim",X14="Siim"),"Ok",IF(AND(W14="Sim")*OR(X14="Não",X14="Não se aplica",X14=""),"Verificar","Ok")) -> Ok | AC14: =IF(AND(Z14="Sim",AB14="Siim"),"Ok",IF(AND(AA14="Sim")*OR(AB14="Não",AB14="Não se aplica",AB14=""),"Verificar","Ok")) -> Ok | AG14: =IF(AND(AE14="sim",AF14="Não"),"Verificar","Ok") -> Ok | AI14: =IF(AH14="Não","Verificar","Ok") -> Ok | AJ14: =IF(N14=1,"Sim, precisa de plano cadastrado na PGPC", "Não") -> Não | AM14: =IF(OR(AL14=" ",AL14="Sim"),"Ok",IF(AJ14="Não","Ok","Verificar")) -> Ok | AO14: =IF(AND(Q14="Ok",U14="Ok",Y14="Ok",AC14="Ok",AG14="Ok",AI14="Ok",AM14="Ok"),"Cooperado SEM perguntas a serem evidenciadas","Cooperado COM perguntas a serem evidenciadas") -> Cooperado SEM perguntas a serem evidenciadas
A15: =IFERROR(IF(ROW(_xlfn.XLOOKUP(B15,For_3056!D:D,For_3056!D:D))=1,"",ROW(_xlfn.XLOOKUP(B15,For_3056!D:D,For_3056!D:D))),"") | B15: {=_xlfn.UNIQUE(IF(_xlfn._xlws.FILTER(For_3056!D:D,For_3056!Z:Z="Fornecedor COM perguntas a serem evidenciadas","")="","",_xlfn._xlws.FILTER(For_3056!D:D,For_3056!Z:Z:'For_3056'!Z:Z="Fornecedor COM perguntas a serem evidenciadas","")))} | C15: {=IFERROR(LEFT( IF(INDIRECT("For_3056!N"&A15)="verificar","6, ","")& IF(INDIRECT("For_3056!q"&A15)="verificar","7, ","")& IF(INDIRECT("For_3056!t"&A15)="verificar","8, ","")& IF(INDIRECT("For_3056!w"&A15)="verificar","16, ","")& IF(INDIRECT("For_3056!x"&A15)="não","QUESTIONÁRIO, ",""), LEN( IF(INDIRECT("For_3056!N"&A15)="verificar","6, ","")& IF(INDIRECT("For_3056!q"&A15)="verificar","7, ","")& IF(INDIRECT("For_3056!t"&A15)="verificar","8, ","")& IF(INDIRECT("For_3056!w"&A15)="verificar","16, ","")& IF(INDIRECT("For_3056!x"&A15)="não","QUESTIONÁRIO, ",""))-2)&".","")} | H15: G4789002 - Comércio varejista de plantas e flores naturais | I15: =_xlfn.XLOOKUP(J15,'3056'!$D:$D,'3056'!$C:$C,0,0) -> 26.941.265/0001-88 | J15: S B NAVES | K15: {=MAX(IF(J15='3056'!$D:$D,'3056'!$I:$I))} -> 46049 | L15: =IF(COUNTIFS('3056'!$D:$D,'A3056'!J15,'3056'!$I:$I,'A3056'!K15,'3056'!$F:$F,'A3056'!$L$7)>=1,1,0) -> 1 | M15: =IF(COUNTIFS('3056'!$D:$D,'A3056'!J15,'3056'!$I:$I,'A3056'!K15,'3056'!$F:$F,'A3056'!$M$7)>=1,1,0) -> 0 | N15: =IF(COUNTIFS('3056'!$D:$D,'A3056'!J15,'3056'!$I:$I,'A3056'!K15,'3056'!$F:$F,'A3056'!$N$7)>=1,1,0) -> 0 | Q15: =IF(AND(O15="Sim")*OR(P15="Não",P15="Não se aplica",P15=""),"Verificar","Ok") -> Ok | U15: =IF(AND(R15="Sim",T15="Siim"),"Ok",IF(AND(S15="Sim")*OR(T15="Não",T15="Não se aplica",T15=""),"Verificar","Ok")) -> Ok | Y15: =IF(AND(V15="Sim",X15="Siim"),"Ok",IF(AND(W15="Sim")*OR(X15="Não",X15="Não se aplica",X15=""),"Verificar","Ok")) -> Ok | AC15: =IF(AND(Z15="Sim",AB15="Siim"),"Ok",IF(AND(AA15="Sim")*OR(AB15="Não",AB15="Não se aplica",AB15=""),"Verificar","Ok")) -> Ok | AG15: =IF(AND(AE15="sim",AF15="Não"),"Verificar","Ok") -> Ok | AI15: =IF(AH15="Não","Verificar","Ok") -> Ok | AJ15: =IF(N15=1,"Sim, precisa de plano cadastrado na PGPC", "Não") -> Não | AM15: =IF(OR(AL15=" ",AL15="Sim"),"Ok",IF(AJ15="Não","Ok","Verificar")) -> Ok | AO15: =IF(AND(Q15="Ok",U15="Ok",Y15="Ok",AC15="Ok",AG15="Ok",AI15="Ok",AM15="Ok"),"Cooperado SEM perguntas a serem evidenciadas","Cooperado COM perguntas a serem evidenciadas") -> Cooperado SEM perguntas a serem evidenciadas
A16: =IFERROR(IF(ROW(_xlfn.XLOOKUP(B16,For_3056!D:D,For_3056!D:D))=1,"",ROW(_xlfn.XLOOKUP(B16,For_3056!D:D,For_3056!D:D))),"") | B16: {=_xlfn.UNIQUE(IF(_xlfn._xlws.FILTER(For_3056!D:D,For_3056!Z:Z="Fornecedor COM perguntas a serem evidenciadas","")="","",_xlfn._xlws.FILTER(For_3056!D:D,For_3056!Z:Z:'For_3056'!Z:Z="Fornecedor COM perguntas a serem evidenciadas","")))} | C16: {=IFERROR(LEFT( IF(INDIRECT("For_3056!N"&A16)="verificar","6, ","")& IF(INDIRECT("For_3056!q"&A16)="verificar","7, ","")& IF(INDIRECT("For_3056!t"&A16)="verificar","8, ","")& IF(INDIRECT("For_3056!w"&A16)="verificar","16, ","")& IF(INDIRECT("For_3056!x"&A16)="não","QUESTIONÁRIO, ",""), LEN( IF(INDIRECT("For_3056!N"&A16)="verificar","6, ","")& IF(INDIRECT("For_3056!q"&A16)="verificar","7, ","")& IF(INDIRECT("For_3056!t"&A16)="verificar","8, ","")& IF(INDIRECT("For_3056!w"&A16)="verificar","16, ","")& IF(INDIRECT("For_3056!x"&A16)="não","QUESTIONÁRIO, ",""))-2)&".","")} | H16: A0115600 - Cultivo de soja | I16: =_xlfn.XLOOKUP(J16,'3056'!$D:$D,'3056'!$C:$C,0,0) -> 275.850.180-53 | J16: DELSO CARAFFINI | K16: {=MAX(IF(J16='3056'!$D:$D,'3056'!$I:$I))} -> 46026 | L16: =IF(COUNTIFS('3056'!$D:$D,'A3056'!J16,'3056'!$I:$I,'A3056'!K16,'3056'!$F:$F,'A3056'!$L$7)>=1,1,0) -> 1 | M16: =IF(COUNTIFS('3056'!$D:$D,'A3056'!J16,'3056'!$I:$I,'A3056'!K16,'3056'!$F:$F,'A3056'!$M$7)>=1,1,0) -> 0 | N16: =IF(COUNTIFS('3056'!$D:$D,'A3056'!J16,'3056'!$I:$I,'A3056'!K16,'3056'!$F:$F,'A3056'!$N$7)>=1,1,0) -> 0 | Q16: =IF(AND(O16="Sim")*OR(P16="Não",P16="Não se aplica",P16=""),"Verificar","Ok") -> Ok | U16: =IF(AND(R16="Sim",T16="Siim"),"Ok",IF(AND(S16="Sim")*OR(T16="Não",T16="Não se aplica",T16=""),"Verificar","Ok")) -> Ok | Y16: =IF(AND(V16="Sim",X16="Siim"),"Ok",IF(AND(W16="Sim")*OR(X16="Não",X16="Não se aplica",X16=""),"Verificar","Ok")) -> Ok | AC16: =IF(AND(Z16="Sim",AB16="Siim"),"Ok",IF(AND(AA16="Sim")*OR(AB16="Não",AB16="Não se aplica",AB16=""),"Verificar","Ok")) -> Ok | AG16: =IF(AND(AE16="sim",AF16="Não"),"Verificar","Ok") -> Ok | AI16: =IF(AH16="Não","Verificar","Ok") -> Ok | AJ16: =IF(N16=1,"Sim, precisa de plano cadastrado na PGPC", "Não") -> Não | AM16: =IF(OR(AL16=" ",AL16="Sim"),"Ok",IF(AJ16="Não","Ok","Verificar")) -> Ok | AO16: =IF(AND(Q16="Ok",U16="Ok",Y16="Ok",AC16="Ok",AG16="Ok",AI16="Ok",AM16="Ok"),"Cooperado SEM perguntas a serem evidenciadas","Cooperado COM perguntas a serem evidenciadas") -> Cooperado SEM perguntas a serem evidenciadas
A17: =IFERROR(IF(ROW(_xlfn.XLOOKUP(B17,For_3056!D:D,For_3056!D:D))=1,"",ROW(_xlfn.XLOOKUP(B17,For_3056!D:D,For_3056!D:D))),"") | B17: {=_xlfn.UNIQUE(IF(_xlfn._xlws.FILTER(For_3056!D:D,For_3056!Z:Z="Fornecedor COM perguntas a serem evidenciadas","")="","",_xlfn._xlws.FILTER(For_3056!D:D,For_3056!Z:Z:'For_3056'!Z:Z="Fornecedor COM perguntas a serem evidenciadas","")))} | C17: {=IFERROR(LEFT( IF(INDIRECT("For_3056!N"&A17)="verificar","6, ","")& IF(INDIRECT("For_3056!q"&A17)="verificar","7, ","")& IF(INDIRECT("For_3056!t"&A17)="verificar","8, ","")& IF(INDIRECT("For_3056!w"&A17)="verificar","16, ","")& IF(INDIRECT("For_3056!x"&A17)="não","QUESTIONÁRIO, ",""), LEN( IF(INDIRECT("For_3056!N"&A17)="verificar","6, ","")& IF(INDIRECT("For_3056!q"&A17)="verificar","7, ","")& IF(INDIRECT("For_3056!t"&A17)="verificar","8, ","")& IF(INDIRECT("For_3056!w"&A17)="verificar","16, ","")& IF(INDIRECT("For_3056!x"&A17)="não","QUESTIONÁRIO, ",""))-2)&".","")} | H17: A0151201 - Criação de bovinos para corte | I17: =_xlfn.XLOOKUP(J17,'3056'!$D:$D,'3056'!$C:$C,0,0) -> 311.401.141-15 | J17: MARGARETH SANTOS BORGES | K17: {=MAX(IF(J17='3056'!$D:$D,'3056'!$I:$I))} -> 46047 | L17: =IF(COUNTIFS('3056'!$D:$D,'A3056'!J17,'3056'!$I:$I,'A3056'!K17,'3056'!$F:$F,'A3056'!$L$7)>=1,1,0) -> 1 | M17: =IF(COUNTIFS('3056'!$D:$D,'A3056'!J17,'3056'!$I:$I,'A3056'!K17,'3056'!$F:$F,'A3056'!$M$7)>=1,1,0) -> 0 | N17: =IF(COUNTIFS('3056'!$D:$D,'A3056'!J17,'3056'!$I:$I,'A3056'!K17,'3056'!$F:$F,'A3056'!$N$7)>=1,1,0) -> 0 | Q17: =IF(AND(O17="Sim")*OR(P17="Não",P17="Não se aplica",P17=""),"Verificar","Ok") -> Ok | U17: =IF(AND(R17="Sim",T17="Siim"),"Ok",IF(AND(S17="Sim")*OR(T17="Não",T17="Não se aplica",T17=""),"Verificar","Ok")) -> Ok | Y17: =IF(AND(V17="Sim",X17="Siim"),"Ok",IF(AND(W17="Sim")*OR(X17="Não",X17="Não se aplica",X17=""),"Verificar","Ok")) -> Ok | AC17: =IF(AND(Z17="Sim",AB17="Siim"),"Ok",IF(AND(AA17="Sim")*OR(AB17="Não",AB17="Não se aplica",AB17=""),"Verificar","Ok")) -> Ok | AG17: =IF(AND(AE17="sim",AF17="Não"),"Verificar","Ok") -> Ok | AI17: =IF(AH17="Não","Verificar","Ok") -> Ok | AJ17: =IF(N17=1,"Sim, precisa de plano cadastrado na PGPC", "Não") -> Não | AM17: =IF(OR(AL17=" ",AL17="Sim"),"Ok",IF(AJ17="Não","Ok","Verificar")) -> Ok | AO17: =IF(AND(Q17="Ok",U17="Ok",Y17="Ok",AC17="Ok",AG17="Ok",AI17="Ok",AM17="Ok"),"Cooperado SEM perguntas a serem evidenciadas","Cooperado COM perguntas a serem evidenciadas") -> Cooperado SEM perguntas a serem evidenciadas
A18: =IFERROR(IF(ROW(_xlfn.XLOOKUP(B18,For_3056!D:D,For_3056!D:D))=1,"",ROW(_xlfn.XLOOKUP(B18,For_3056!D:D,For_3056!D:D))),"") | B18: {=_xlfn.UNIQUE(IF(_xlfn._xlws.FILTER(For_3056!D:D,For_3056!Z:Z="Fornecedor COM perguntas a serem evidenciadas","")="","",_xlfn._xlws.FILTER(For_3056!D:D,For_3056!Z:Z:'For_3056'!Z:Z="Fornecedor COM perguntas a serem evidenciadas","")))} | C18: {=IFERROR(LEFT( IF(INDIRECT("For_3056!N"&A18)="verificar","6, ","")& IF(INDIRECT("For_3056!q"&A18)="verificar","7, ","")& IF(INDIRECT("For_3056!t"&A18)="verificar","8, ","")& IF(INDIRECT("For_3056!w"&A18)="verificar","16, ","")& IF(INDIRECT("For_3056!x"&A18)="não","QUESTIONÁRIO, ",""), LEN( IF(INDIRECT("For_3056!N"&A18)="verificar","6, ","")& IF(INDIRECT("For_3056!q"&A18)="verificar","7, ","")& IF(INDIRECT("For_3056!t"&A18)="verificar","8, ","")& IF(INDIRECT("For_3056!w"&A18)="verificar","16, ","")& IF(INDIRECT("For_3056!x"&A18)="não","QUESTIONÁRIO, ",""))-2)&".","")} | H18: Sem CNAE | I18: =_xlfn.XLOOKUP(J18,'3056'!$D:$D,'3056'!$C:$C,0,0) -> 433.597.601-15 | J18: ORACILDA PEREIRA DE SOUZA | K18: {=MAX(IF(J18='3056'!$D:$D,'3056'!$I:$I))} -> 46048 | L18: =IF(COUNTIFS('3056'!$D:$D,'A3056'!J18,'3056'!$I:$I,'A3056'!K18,'3056'!$F:$F,'A3056'!$L$7)>=1,1,0) -> 0 | M18: =IF(COUNTIFS('3056'!$D:$D,'A3056'!J18,'3056'!$I:$I,'A3056'!K18,'3056'!$F:$F,'A3056'!$M$7)>=1,1,0) -> 0 | N18: =IF(COUNTIFS('3056'!$D:$D,'A3056'!J18,'3056'!$I:$I,'A3056'!K18,'3056'!$F:$F,'A3056'!$N$7)>=1,1,0) -> 1 | Q18: =IF(AND(O18="Sim")*OR(P18="Não",P18="Não se aplica",P18=""),"Verificar","Ok") -> Ok | U18: =IF(AND(R18="Sim",T18="Siim"),"Ok",IF(AND(S18="Sim")*OR(T18="Não",T18="Não se aplica",T18=""),"Verificar","Ok")) -> Ok | Y18: =IF(AND(V18="Sim",X18="Siim"),"Ok",IF(AND(W18="Sim")*OR(X18="Não",X18="Não se aplica",X18=""),"Verificar","Ok")) -> Ok | Z18: Não | AA18: Sim | AB18: Não | AC18: =IF(AND(Z18="Sim",AB18="Siim"),"Ok",IF(AND(AA18="Sim")*OR(AB18="Não",AB18="Não se aplica",AB18=""),"Verificar","Ok")) -> Verificar | AG18: =IF(AND(AE18="sim",AF18="Não"),"Verificar","Ok") -> Ok | AI18: =IF(AH18="Não","Verificar","Ok") -> Ok | AJ18: =IF(N18=1,"Sim, precisa de plano cadastrado na PGPC", "Não") -> Sim, precisa de plano cadastrado na PGPC | AL18: Sim | AM18: =IF(OR(AL18=" ",AL18="Sim"),"Ok",IF(AJ18="Não","Ok","Verificar")) -> Ok | AO18: =IF(AND(Q18="Ok",U18="Ok",Y18="Ok",AC18="Ok",AG18="Ok",AI18="Ok",AM18="Ok"),"Cooperado SEM perguntas a serem evidenciadas","Cooperado COM perguntas a serem evidenciadas") -> Cooperado COM perguntas a serem evidenciadas
A19: =IFERROR(IF(ROW(_xlfn.XLOOKUP(B19,For_3056!D:D,For_3056!D:D))=1,"",ROW(_xlfn.XLOOKUP(B19,For_3056!D:D,For_3056!D:D))),"") | B19: {=_xlfn.UNIQUE(IF(_xlfn._xlws.FILTER(For_3056!D:D,For_3056!Z:Z="Fornecedor COM perguntas a serem evidenciadas","")="","",_xlfn._xlws.FILTER(For_3056!D:D,For_3056!Z:Z:'For_3056'!Z:Z="Fornecedor COM perguntas a serem evidenciadas","")))} | C19: {=IFERROR(LEFT( IF(INDIRECT("For_3056!N"&A19)="verificar","6, ","")& IF(INDIRECT("For_3056!q"&A19)="verificar","7, ","")& IF(INDIRECT("For_3056!t"&A19)="verificar","8, ","")& IF(INDIRECT("For_3056!w"&A19)="verificar","16, ","")& IF(INDIRECT("For_3056!x"&A19)="não","QUESTIONÁRIO, ",""), LEN( IF(INDIRECT("For_3056!N"&A19)="verificar","6, ","")& IF(INDIRECT("For_3056!q"&A19)="verificar","7, ","")& IF(INDIRECT("For_3056!t"&A19)="verificar","8, ","")& IF(INDIRECT("For_3056!w"&A19)="verificar","16, ","")& IF(INDIRECT("For_3056!x"&A19)="não","QUESTIONÁRIO, ",""))-2)&".","")} | H19: A0210101 - Cultivo de eucalipto | I19: =_xlfn.XLOOKUP(J19,'3056'!$D:$D,'3056'!$C:$C,0,0) -> 819.963.141-49 | J19: SILVANIA BARBOSA NAVES | K19: {=MAX(IF(J19='3056'!$D:$D,'3056'!$I:$I))} -> 46049 | L19: =IF(COUNTIFS('3056'!$D:$D,'A3056'!J19,'3056'!$I:$I,'A3056'!K19,'3056'!$F:$F,'A3056'!$L$7)>=1,1,0) -> 0 | M19: =IF(COUNTIFS('3056'!$D:$D,'A3056'!J19,'3056'!$I:$I,'A3056'!K19,'3056'!$F:$F,'A3056'!$M$7)>=1,1,0) -> 0 | N19: =IF(COUNTIFS('3056'!$D:$D,'A3056'!J19,'3056'!$I:$I,'A3056'!K19,'3056'!$F:$F,'A3056'!$N$7)>=1,1,0) -> 1 | Q19: =IF(AND(O19="Sim")*OR(P19="Não",P19="Não se aplica",P19=""),"Verificar","Ok") -> Ok | U19: =IF(AND(R19="Sim",T19="Siim"),"Ok",IF(AND(S19="Sim")*OR(T19="Não",T19="Não se aplica",T19=""),"Verificar","Ok")) -> Ok | Y19: =IF(AND(V19="Sim",X19="Siim"),"Ok",IF(AND(W19="Sim")*OR(X19="Não",X19="Não se aplica",X19=""),"Verificar","Ok")) -> Ok | AC19: =IF(AND(Z19="Sim",AB19="Siim"),"Ok",IF(AND(AA19="Sim")*OR(AB19="Não",AB19="Não se aplica",AB19=""),"Verificar","Ok")) -> Ok | AG19: =IF(AND(AE19="sim",AF19="Não"),"Verificar","Ok") -> Ok | AI19: =IF(AH19="Não","Verificar","Ok") -> Ok | AJ19: =IF(N19=1,"Sim, precisa de plano cadastrado na PGPC", "Não") -> Sim, precisa de plano cadastrado na PGPC | AL19: Sim | AM19: =IF(OR(AL19=" ",AL19="Sim"),"Ok",IF(AJ19="Não","Ok","Verificar")) -> Ok | AO19: =IF(AND(Q19="Ok",U19="Ok",Y19="Ok",AC19="Ok",AG19="Ok",AI19="Ok",AM19="Ok"),"Cooperado SEM perguntas a serem evidenciadas","Cooperado COM perguntas a serem evidenciadas") -> Cooperado SEM perguntas a serem evidenciadas
A20: =IFERROR(IF(ROW(_xlfn.XLOOKUP(B20,For_3056!D:D,For_3056!D:D))=1,"",ROW(_xlfn.XLOOKUP(B20,For_3056!D:D,For_3056!D:D))),"") | B20: {=_xlfn.UNIQUE(IF(_xlfn._xlws.FILTER(For_3056!D:D,For_3056!Z:Z="Fornecedor COM perguntas a serem evidenciadas","")="","",_xlfn._xlws.FILTER(For_3056!D:D,For_3056!Z:Z:'For_3056'!Z:Z="Fornecedor COM perguntas a serem evidenciadas","")))} | C20: {=IFERROR(LEFT( IF(INDIRECT("For_3056!N"&A20)="verificar","6, ","")& IF(INDIRECT("For_3056!q"&A20)="verificar","7, ","")& IF(INDIRECT("For_3056!t"&A20)="verificar","8, ","")& IF(INDIRECT("For_3056!w"&A20)="verificar","16, ","")& IF(INDIRECT("For_3056!x"&A20)="não","QUESTIONÁRIO, ",""), LEN( IF(INDIRECT("For_3056!N"&A20)="verificar","6, ","")& IF(INDIRECT("For_3056!q"&A20)="verificar","7, ","")& IF(INDIRECT("For_3056!t"&A20)="verificar","8, ","")& IF(INDIRECT("For_3056!w"&A20)="verificar","16, ","")& IF(INDIRECT("For_3056!x"&A20)="não","QUESTIONÁRIO, ",""))-2)&".","")} | H20: A0151201 - Criação de bovinos para corte | I20: =_xlfn.XLOOKUP(J20,'3056'!$D:$D,'3056'!$C:$C,0,0) -> 904.062.061-04 | J20: GUILHERME CARVALHO DE CASTRO | K20: {=MAX(IF(J20='3056'!$D:$D,'3056'!$I:$I))} -> 46036 | L20: =IF(COUNTIFS('3056'!$D:$D,'A3056'!J20,'3056'!$I:$I,'A3056'!K20,'3056'!$F:$F,'A3056'!$L$7)>=1,1,0) -> 1 | M20: =IF(COUNTIFS('3056'!$D:$D,'A3056'!J20,'3056'!$I:$I,'A3056'!K20,'3056'!$F:$F,'A3056'!$M$7)>=1,1,0) -> 0 | N20: =IF(COUNTIFS('3056'!$D:$D,'A3056'!J20,'3056'!$I:$I,'A3056'!K20,'3056'!$F:$F,'A3056'!$N$7)>=1,1,0) -> 0 | Q20: =IF(AND(O20="Sim")*OR(P20="Não",P20="Não se aplica",P20=""),"Verificar","Ok") -> Ok | U20: =IF(AND(R20="Sim",T20="Siim"),"Ok",IF(AND(S20="Sim")*OR(T20="Não",T20="Não se aplica",T20=""),"Verificar","Ok")) -> Ok | Y20: =IF(AND(V20="Sim",X20="Siim"),"Ok",IF(AND(W20="Sim")*OR(X20="Não",X20="Não se aplica",X20=""),"Verificar","Ok")) -> Ok | AC20: =IF(AND(Z20="Sim",AB20="Siim"),"Ok",IF(AND(AA20="Sim")*OR(AB20="Não",AB20="Não se aplica",AB20=""),"Verificar","Ok")) -> Ok | AG20: =IF(AND(AE20="sim",AF20="Não"),"Verificar","Ok") -> Ok | AI20: =IF(AH20="Não","Verificar","Ok") -> Ok | AJ20: =IF(N20=1,"Sim, precisa de plano cadastrado na PGPC", "Não") -> Não | AM20: =IF(OR(AL20=" ",AL20="Sim"),"Ok",IF(AJ20="Não","Ok","Verificar")) -> Ok | AO20: =IF(AND(Q20="Ok",U20="Ok",Y20="Ok",AC20="Ok",AG20="Ok",AI20="Ok",AM20="Ok"),"Cooperado SEM perguntas a serem evidenciadas","Cooperado COM perguntas a serem evidenciadas") -> Cooperado SEM perguntas a serem evidenciadas
A21: =IFERROR(IF(ROW(_xlfn.XLOOKUP(B21,For_3056!D:D,For_3056!D:D))=1,"",ROW(_xlfn.XLOOKUP(B21,For_3056!D:D,For_3056!D:D))),"") | B21: {=_xlfn.UNIQUE(IF(_xlfn._xlws.FILTER(For_3056!D:D,For_3056!Z:Z="Fornecedor COM perguntas a serem evidenciadas","")="","",_xlfn._xlws.FILTER(For_3056!D:D,For_3056!Z:Z:'For_3056'!Z:Z="Fornecedor COM perguntas a serem evidenciadas","")))} | C21: {=IFERROR(LEFT( IF(INDIRECT("For_3056!N"&A21)="verificar","6, ","")& IF(INDIRECT("For_3056!q"&A21)="verificar","7, ","")& IF(INDIRECT("For_3056!t"&A21)="verificar","8, ","")& IF(INDIRECT("For_3056!w"&A21)="verificar","16, ","")& IF(INDIRECT("For_3056!x"&A21)="não","QUESTIONÁRIO, ",""), LEN( IF(INDIRECT("For_3056!N"&A21)="verificar","6, ","")& IF(INDIRECT("For_3056!q"&A21)="verificar","7, ","")& IF(INDIRECT("For_3056!t"&A21)="verificar","8, ","")& IF(INDIRECT("For_3056!w"&A21)="verificar","16, ","")& IF(INDIRECT("For_3056!x"&A21)="não","QUESTIONÁRIO, ",""))-2)&".","")} | H21: A0151201 - Criação de bovinos para corte | I21: =_xlfn.XLOOKUP(J21,'3056'!$D:$D,'3056'!$C:$C,0,0) -> 952.096.621-87 | J21: FERNANDO MORAIS DE ASSIS | K21: {=MAX(IF(J21='3056'!$D:$D,'3056'!$I:$I))} -> 46036 | L21: =IF(COUNTIFS('3056'!$D:$D,'A3056'!J21,'3056'!$I:$I,'A3056'!K21,'3056'!$F:$F,'A3056'!$L$7)>=1,1,0) -> 1 | M21: =IF(COUNTIFS('3056'!$D:$D,'A3056'!J21,'3056'!$I:$I,'A3056'!K21,'3056'!$F:$F,'A3056'!$M$7)>=1,1,0) -> 0 | N21: =IF(COUNTIFS('3056'!$D:$D,'A3056'!J21,'3056'!$I:$I,'A3056'!K21,'3056'!$F:$F,'A3056'!$N$7)>=1,1,0) -> 0 | Q21: =IF(AND(O21="Sim")*OR(P21="Não",P21="Não se aplica",P21=""),"Verificar","Ok") -> Ok | U21: =IF(AND(R21="Sim",T21="Siim"),"Ok",IF(AND(S21="Sim")*OR(T21="Não",T21="Não se aplica",T21=""),"Verificar","Ok")) -> Ok | Y21: =IF(AND(V21="Sim",X21="Siim"),"Ok",IF(AND(W21="Sim")*OR(X21="Não",X21="Não se aplica",X21=""),"Verificar","Ok")) -> Ok | AC21: =IF(AND(Z21="Sim",AB21="Siim"),"Ok",IF(AND(AA21="Sim")*OR(AB21="Não",AB21="Não se aplica",AB21=""),"Verificar","Ok")) -> Ok | AG21: =IF(AND(AE21="sim",AF21="Não"),"Verificar","Ok") -> Ok | AI21: =IF(AH21="Não","Verificar","Ok") -> Ok | AJ21: =IF(N21=1,"Sim, precisa de plano cadastrado na PGPC", "Não") -> Não | AM21: =IF(OR(AL21=" ",AL21="Sim"),"Ok",IF(AJ21="Não","Ok","Verificar")) -> Ok | AO21: =IF(AND(Q21="Ok",U21="Ok",Y21="Ok",AC21="Ok",AG21="Ok",AI21="Ok",AM21="Ok"),"Cooperado SEM perguntas a serem evidenciadas","Cooperado COM perguntas a serem evidenciadas") -> Cooperado SEM perguntas a serem evidenciadas
A22: =IFERROR(IF(ROW(_xlfn.XLOOKUP(B22,For_3056!D:D,For_3056!D:D))=1,"",ROW(_xlfn.XLOOKUP(B22,For_3056!D:D,For_3056!D:D))),"") | B22: {=_xlfn.UNIQUE(IF(_xlfn._xlws.FILTER(For_3056!D:D,For_3056!Z:Z="Fornecedor COM perguntas a serem evidenciadas","")="","",_xlfn._xlws.FILTER(For_3056!D:D,For_3056!Z:Z:'For_3056'!Z:Z="Fornecedor COM perguntas a serem evidenciadas","")))} | C22: {=IFERROR(LEFT( IF(INDIRECT("For_3056!N"&A22)="verificar","6, ","")& IF(INDIRECT("For_3056!q"&A22)="verificar","7, ","")& IF(INDIRECT("For_3056!t"&A22)="verificar","8, ","")& IF(INDIRECT("For_3056!w"&A22)="verificar","16, ","")& IF(INDIRECT("For_3056!x"&A22)="não","QUESTIONÁRIO, ",""), LEN( IF(INDIRECT("For_3056!N"&A22)="verificar","6, ","")& IF(INDIRECT("For_3056!q"&A22)="verificar","7, ","")& IF(INDIRECT("For_3056!t"&A22)="verificar","8, ","")& IF(INDIRECT("For_3056!w"&A22)="verificar","16, ","")& IF(INDIRECT("For_3056!x"&A22)="não","QUESTIONÁRIO, ",""))-2)&".","")} | H22: A0115600 - Cultivo de soja | I22: =_xlfn.XLOOKUP(J22,'3056'!$D:$D,'3056'!$C:$C,0,0) -> 961.471.051-91 | J22: ROBSON CARAFFINI | K22: {=MAX(IF(J22='3056'!$D:$D,'3056'!$I:$I))} -> 46026 | L22: =IF(COUNTIFS('3056'!$D:$D,'A3056'!J22,'3056'!$I:$I,'A3056'!K22,'3056'!$F:$F,'A3056'!$L$7)>=1,1,0) -> 1 | M22: =IF(COUNTIFS('3056'!$D:$D,'A3056'!J22,'3056'!$I:$I,'A3056'!K22,'3056'!$F:$F,'A3056'!$M$7)>=1,1,0) -> 0 | N22: =IF(COUNTIFS('3056'!$D:$D,'A3056'!J22,'3056'!$I:$I,'A3056'!K22,'3056'!$F:$F,'A3056'!$N$7)>=1,1,0) -> 0 | Q22: =IF(AND(O22="Sim")*OR(P22="Não",P22="Não se aplica",P22=""),"Verificar","Ok") -> Ok | U22: =IF(AND(R22="Sim",T22="Siim"),"Ok",IF(AND(S22="Sim")*OR(T22="Não",T22="Não se aplica",T22=""),"Verificar","Ok")) -> Ok | Y22: =IF(AND(V22="Sim",X22="Siim"),"Ok",IF(AND(W22="Sim")*OR(X22="Não",X22="Não se aplica",X22=""),"Verificar","Ok")) -> Ok | AC22: =IF(AND(Z22="Sim",AB22="Siim"),"Ok",IF(AND(AA22="Sim")*OR(AB22="Não",AB22="Não se aplica",AB22=""),"Verificar","Ok")) -> Ok | AG22: =IF(AND(AE22="sim",AF22="Não"),"Verificar","Ok") -> Ok | AI22: =IF(AH22="Não","Verificar","Ok") -> Ok | AJ22: =IF(N22=1,"Sim, precisa de plano cadastrado na PGPC", "Não") -> Não | AM22: =IF(OR(AL22=" ",AL22="Sim"),"Ok",IF(AJ22="Não","Ok","Verificar")) -> Ok | AO22: =IF(AND(Q22="Ok",U22="Ok",Y22="Ok",AC22="Ok",AG22="Ok",AI22="Ok",AM22="Ok"),"Cooperado SEM perguntas a serem evidenciadas","Cooperado COM perguntas a serem evidenciadas") -> Cooperado SEM perguntas a serem evidenciadas
A23: =IFERROR(IF(ROW(_xlfn.XLOOKUP(B23,For_3056!D:D,For_3056!D:D))=1,"",ROW(_xlfn.XLOOKUP(B23,For_3056!D:D,For_3056!D:D))),"") | B23: {=_xlfn.UNIQUE(IF(_xlfn._xlws.FILTER(For_3056!D:D,For_3056!Z:Z="Fornecedor COM perguntas a serem evidenciadas","")="","",_xlfn._xlws.FILTER(For_3056!D:D,For_3056!Z:Z:'For_3056'!Z:Z="Fornecedor COM perguntas a serem evidenciadas","")))} | C23: {=IFERROR(LEFT( IF(INDIRECT("For_3056!N"&A23)="verificar","6, ","")& IF(INDIRECT("For_3056!q"&A23)="verificar","7, ","")& IF(INDIRECT("For_3056!t"&A23)="verificar","8, ","")& IF(INDIRECT("For_3056!w"&A23)="verificar","16, ","")& IF(INDIRECT("For_3056!x"&A23)="não","QUESTIONÁRIO, ",""), LEN( IF(INDIRECT("For_3056!N"&A23)="verificar","6, ","")& IF(INDIRECT("For_3056!q"&A23)="verificar","7, ","")& IF(INDIRECT("For_3056!t"&A23)="verificar","8, ","")& IF(INDIRECT("For_3056!w"&A23)="verificar","16, ","")& IF(INDIRECT("For_3056!x"&A23)="não","QUESTIONÁRIO, ",""))-2)&".","")} | H23: A0151201 - Criação de bovinos para corte | I23: =_xlfn.XLOOKUP(J23,'3056'!$D:$D,'3056'!$C:$C,0,0) -> 968.347.731-34 | J23: GUSTAVO CARVALHO DE CASTRO | K23: {=MAX(IF(J23='3056'!$D:$D,'3056'!$I:$I))} -> 46027 | L23: =IF(COUNTIFS('3056'!$D:$D,'A3056'!J23,'3056'!$I:$I,'A3056'!K23,'3056'!$F:$F,'A3056'!$L$7)>=1,1,0) -> 1 | M23: =IF(COUNTIFS('3056'!$D:$D,'A3056'!J23,'3056'!$I:$I,'A3056'!K23,'3056'!$F:$F,'A3056'!$M$7)>=1,1,0) -> 0 | N23: =IF(COUNTIFS('3056'!$D:$D,'A3056'!J23,'3056'!$I:$I,'A3056'!K23,'3056'!$F:$F,'A3056'!$N$7)>=1,1,0) -> 0 | Q23: =IF(AND(O23="Sim")*OR(P23="Não",P23="Não se aplica",P23=""),"Verificar","Ok") -> Ok | U23: =IF(AND(R23="Sim",T23="Siim"),"Ok",IF(AND(S23="Sim")*OR(T23="Não",T23="Não se aplica",T23=""),"Verificar","Ok")) -> Ok | Y23: =IF(AND(V23="Sim",X23="Siim"),"Ok",IF(AND(W23="Sim")*OR(X23="Não",X23="Não se aplica",X23=""),"Verificar","Ok")) -> Ok | Z23: Não | AA23: Sim | AB23: Não | AC23: =IF(AND(Z23="Sim",AB23="Siim"),"Ok",IF(AND(AA23="Sim")*OR(AB23="Não",AB23="Não se aplica",AB23=""),"Verificar","Ok")) -> Verificar | AG23: =IF(AND(AE23="sim",AF23="Não"),"Verificar","Ok") -> Ok | AI23: =IF(AH23="Não","Verificar","Ok") -> Ok | AJ23: =IF(N23=1,"Sim, precisa de plano cadastrado na PGPC", "Não") -> Não | AM23: =IF(OR(AL23=" ",AL23="Sim"),"Ok",IF(AJ23="Não","Ok","Verificar")) -> Ok | AO23: =IF(AND(Q23="Ok",U23="Ok",Y23="Ok",AC23="Ok",AG23="Ok",AI23="Ok",AM23="Ok"),"Cooperado SEM perguntas a serem evidenciadas","Cooperado COM perguntas a serem evidenciadas") -> Cooperado COM perguntas a serem evidenciadas
A24: =IFERROR(IF(ROW(_xlfn.XLOOKUP(B24,For_3056!D:D,For_3056!D:D))=1,"",ROW(_xlfn.XLOOKUP(B24,For_3056!D:D,For_3056!D:D))),"") | B24: {=_xlfn.UNIQUE(IF(_xlfn._xlws.FILTER(For_3056!D:D,For_3056!Z:Z="Fornecedor COM perguntas a serem evidenciadas","")="","",_xlfn._xlws.FILTER(For_3056!D:D,For_3056!Z:Z:'For_3056'!Z:Z="Fornecedor COM perguntas a serem evidenciadas","")))} | C24: {=IFERROR(LEFT( IF(INDIRECT("For_3056!N"&A24)="verificar","6, ","")& IF(INDIRECT("For_3056!q"&A24)="verificar","7, ","")& IF(INDIRECT("For_3056!t"&A24)="verificar","8, ","")& IF(INDIRECT("For_3056!w"&A24)="verificar","16, ","")& IF(INDIRECT("For_3056!x"&A24)="não","QUESTIONÁRIO, ",""), LEN( IF(INDIRECT("For_3056!N"&A24)="verificar","6, ","")& IF(INDIRECT("For_3056!q"&A24)="verificar","7, ","")& IF(INDIRECT("For_3056!t"&A24)="verificar","8, ","")& IF(INDIRECT("For_3056!w"&A24)="verificar","16, ","")& IF(INDIRECT("For_3056!x"&A24)="não","QUESTIONÁRIO, ",""))-2)&".","")} | H24: Q8630504 - Atividade odontológica | I24: =_xlfn.XLOOKUP(J24,'3056'!$D:$D,'3056'!$C:$C,0,0) -> 993.081.261-04 | J24: GABRIELA CARVALHO DE CASTRO ASSIS | K24: {=MAX(IF(J24='3056'!$D:$D,'3056'!$I:$I))} -> 46040 | L24: =IF(COUNTIFS('3056'!$D:$D,'A3056'!J24,'3056'!$I:$I,'A3056'!K24,'3056'!$F:$F,'A3056'!$L$7)>=1,1,0) -> 1 | M24: =IF(COUNTIFS('3056'!$D:$D,'A3056'!J24,'3056'!$I:$I,'A3056'!K24,'3056'!$F:$F,'A3056'!$M$7)>=1,1,0) -> 0 | N24: =IF(COUNTIFS('3056'!$D:$D,'A3056'!J24,'3056'!$I:$I,'A3056'!K24,'3056'!$F:$F,'A3056'!$N$7)>=1,1,0) -> 0 | Q24: =IF(AND(O24="Sim")*OR(P24="Não",P24="Não se aplica",P24=""),"Verificar","Ok") -> Ok | U24: =IF(AND(R24="Sim",T24="Siim"),"Ok",IF(AND(S24="Sim")*OR(T24="Não",T24="Não se aplica",T24=""),"Verificar","Ok")) -> Ok | Y24: =IF(AND(V24="Sim",X24="Siim"),"Ok",IF(AND(W24="Sim")*OR(X24="Não",X24="Não se aplica",X24=""),"Verificar","Ok")) -> Ok | AC24: =IF(AND(Z24="Sim",AB24="Siim"),"Ok",IF(AND(AA24="Sim")*OR(AB24="Não",AB24="Não se aplica",AB24=""),"Verificar","Ok")) -> Ok | AG24: =IF(AND(AE24="sim",AF24="Não"),"Verificar","Ok") -> Ok | AI24: =IF(AH24="Não","Verificar","Ok") -> Ok | AJ24: =IF(N24=1,"Sim, precisa de plano cadastrado na PGPC", "Não") -> Não | AM24: =IF(OR(AL24=" ",AL24="Sim"),"Ok",IF(AJ24="Não","Ok","Verificar")) -> Ok | AO24: =IF(AND(Q24="Ok",U24="Ok",Y24="Ok",AC24="Ok",AG24="Ok",AI24="Ok",AM24="Ok"),"Cooperado SEM perguntas a serem evidenciadas","Cooperado COM perguntas a serem evidenciadas") -> Cooperado SEM perguntas a serem evidenciadas
I25: =_xlfn.XLOOKUP(J25,'3056'!$D:$D,'3056'!$C:$C,0,0) -> 0 | K25: {=MAX(IF(J25='3056'!$D:$D,'3056'!$I:$I))} -> 0 | L25: =IF(COUNTIFS('3056'!$D:$D,'A3056'!J25,'3056'!$I:$I,'A3056'!K25,'3056'!$F:$F,'A3056'!$L$7)>=1,1,0) -> 0 | M25: =IF(COUNTIFS('3056'!$D:$D,'A3056'!J25,'3056'!$I:$I,'A3056'!K25,'3056'!$F:$F,'A3056'!$M$7)>=1,1,0) -> 0 | N25: =IF(COUNTIFS('3056'!$D:$D,'A3056'!J25,'3056'!$I:$I,'A3056'!K25,'3056'!$F:$F,'A3056'!$N$7)>=1,1,0) -> 0 | Q25: =IF(AND(O25="Sim")*OR(P25="Não",P25="Não se aplica",P25=""),"Verificar","Ok") -> Ok | U25: =IF(AND(R25="Sim",T25="Siim"),"Ok",IF(AND(S25="Sim")*OR(T25="Não",T25="Não se aplica",T25=""),"Verificar","Ok")) -> Ok | Y25: =IF(AND(V25="Sim",X25="Siim"),"Ok",IF(AND(W25="Sim")*OR(X25="Não",X25="Não se aplica",X25=""),"Verificar","Ok")) -> Ok | AC25: =IF(AND(Z25="Sim",AB25="Siim"),"Ok",IF(AND(AA25="Sim")*OR(AB25="Não",AB25="Não se aplica",AB25=""),"Verificar","Ok")) -> Ok | AG25: =IF(AND(AE25="sim",AF25="Não"),"Verificar","Ok") -> Ok | AI25: =IF(AH25="Não","Verificar","Ok") -> Ok | AJ25: =IF(N25=1,"Sim, precisa de plano cadastrado na PGPC", "Não") -> Não | AM25: =IF(OR(AL25=" ",AL25="Sim"),"Ok",IF(AJ25="Não","Ok","Verificar")) -> Ok | AO25: =IF(AND(Q25="Ok",U25="Ok",Y25="Ok",AC25="Ok",AG25="Ok",AI25="Ok",AM25="Ok"),"Cooperado SEM perguntas a serem evidenciadas","Cooperado COM perguntas a serem evidenciadas") -> Cooperado SEM perguntas a serem evidenciadas
B26: Fornecedores que se encontram na Lista Suja do MTE | I26: =_xlfn.XLOOKUP(J26,'3056'!$D:$D,'3056'!$C:$C,0,0) -> 0 | K26: {=MAX(IF(J26='3056'!$D:$D,'3056'!$I:$I))} -> 0 | L26: =IF(COUNTIFS('3056'!$D:$D,'A3056'!J26,'3056'!$I:$I,'A3056'!K26,'3056'!$F:$F,'A3056'!$L$7)>=1,1,0) -> 0 | M26: =IF(COUNTIFS('3056'!$D:$D,'A3056'!J26,'3056'!$I:$I,'A3056'!K26,'3056'!$F:$F,'A3056'!$M$7)>=1,1,0) -> 0 | N26: =IF(COUNTIFS('3056'!$D:$D,'A3056'!J26,'3056'!$I:$I,'A3056'!K26,'3056'!$F:$F,'A3056'!$N$7)>=1,1,0) -> 0 | Q26: =IF(AND(O26="Sim")*OR(P26="Não",P26="Não se aplica",P26=""),"Verificar","Ok") -> Ok | U26: =IF(AND(R26="Sim",T26="Siim"),"Ok",IF(AND(S26="Sim")*OR(T26="Não",T26="Não se aplica",T26=""),"Verificar","Ok")) -> Ok | Y26: =IF(AND(V26="Sim",X26="Siim"),"Ok",IF(AND(W26="Sim")*OR(X26="Não",X26="Não se aplica",X26=""),"Verificar","Ok")) -> Ok | AC26: =IF(AND(Z26="Sim",AB26="Siim"),"Ok",IF(AND(AA26="Sim")*OR(AB26="Não",AB26="Não se aplica",AB26=""),"Verificar","Ok")) -> Ok | AG26: =IF(AND(AE26="sim",AF26="Não"),"Verificar","Ok") -> Ok | AI26: =IF(AH26="Não","Verificar","Ok") -> Ok | AJ26: =IF(N26=1,"Sim, precisa de plano cadastrado na PGPC", "Não") -> Não | AM26: =IF(OR(AL26=" ",AL26="Sim"),"Ok",IF(AJ26="Não","Ok","Verificar")) -> Ok | AO26: =IF(AND(Q26="Ok",U26="Ok",Y26="Ok",AC26="Ok",AG26="Ok",AI26="Ok",AM26="Ok"),"Cooperado SEM perguntas a serem evidenciadas","Cooperado COM perguntas a serem evidenciadas") -> Cooperado SEM perguntas a serem evidenciadas
B27: CNPJ | C27: RAZÃO SOCIAL | I27: =_xlfn.XLOOKUP(J27,'3056'!$D:$D,'3056'!$C:$C,0,0) -> 0 | K27: {=MAX(IF(J27='3056'!$D:$D,'3056'!$I:$I))} -> 0 | L27: =IF(COUNTIFS('3056'!$D:$D,'A3056'!J27,'3056'!$I:$I,'A3056'!K27,'3056'!$F:$F,'A3056'!$L$7)>=1,1,0) -> 0 | M27: =IF(COUNTIFS('3056'!$D:$D,'A3056'!J27,'3056'!$I:$I,'A3056'!K27,'3056'!$F:$F,'A3056'!$M$7)>=1,1,0) -> 0 | N27: =IF(COUNTIFS('3056'!$D:$D,'A3056'!J27,'3056'!$I:$I,'A3056'!K27,'3056'!$F:$F,'A3056'!$N$7)>=1,1,0) -> 0 | Q27: =IF(AND(O27="Sim")*OR(P27="Não",P27="Não se aplica",P27=""),"Verificar","Ok") -> Ok | U27: =IF(AND(R27="Sim",T27="Siim"),"Ok",IF(AND(S27="Sim")*OR(T27="Não",T27="Não se aplica",T27=""),"Verificar","Ok")) -> Ok | Y27: =IF(AND(V27="Sim",X27="Siim"),"Ok",IF(AND(W27="Sim")*OR(X27="Não",X27="Não se aplica",X27=""),"Verificar","Ok")) -> Ok | AC27: =IF(AND(Z27="Sim",AB27="Siim"),"Ok",IF(AND(AA27="Sim")*OR(AB27="Não",AB27="Não se aplica",AB27=""),"Verificar","Ok")) -> Ok | AG27: =IF(AND(AE27="sim",AF27="Não"),"Verificar","Ok") -> Ok | AI27: =IF(AH27="Não","Verificar","Ok") -> Ok | AJ27: =IF(N27=1,"Sim, precisa de plano cadastrado na PGPC", "Não") -> Não | AM27: =IF(OR(AL27=" ",AL27="Sim"),"Ok",IF(AJ27="Não","Ok","Verificar")) -> Ok | AO27: =IF(AND(Q27="Ok",U27="Ok",Y27="Ok",AC27="Ok",AG27="Ok",AI27="Ok",AM27="Ok"),"Cooperado SEM perguntas a serem evidenciadas","Cooperado COM perguntas a serem evidenciadas") -> Cooperado SEM perguntas a serem evidenciadas
A28: 1 | B28: {=_xlfn._xlws.FILTER(For_3056!D:E,For_3056!J:J="SIM","")} | I28: =_xlfn.XLOOKUP(J28,'3056'!$D:$D,'3056'!$C:$C,0,0) -> 0 | K28: {=MAX(IF(J28='3056'!$D:$D,'3056'!$I:$I))} -> 0 | L28: =IF(COUNTIFS('3056'!$D:$D,'A3056'!J28,'3056'!$I:$I,'A3056'!K28,'3056'!$F:$F,'A3056'!$L$7)>=1,1,0) -> 0 | M28: =IF(COUNTIFS('3056'!$D:$D,'A3056'!J28,'3056'!$I:$I,'A3056'!K28,'3056'!$F:$F,'A3056'!$M$7)>=1,1,0) -> 0 | N28: =IF(COUNTIFS('3056'!$D:$D,'A3056'!J28,'3056'!$I:$I,'A3056'!K28,'3056'!$F:$F,'A3056'!$N$7)>=1,1,0) -> 0 | Q28: =IF(AND(O28="Sim")*OR(P28="Não",P28="Não se aplica",P28=""),"Verificar","Ok") -> Ok | U28: =IF(AND(R28="Sim",T28="Siim"),"Ok",IF(AND(S28="Sim")*OR(T28="Não",T28="Não se aplica",T28=""),"Verificar","Ok")) -> Ok | Y28: =IF(AND(V28="Sim",X28="Siim"),"Ok",IF(AND(W28="Sim")*OR(X28="Não",X28="Não se aplica",X28=""),"Verificar","Ok")) -> Ok | AC28: =IF(AND(Z28="Sim",AB28="Siim"),"Ok",IF(AND(AA28="Sim")*OR(AB28="Não",AB28="Não se aplica",AB28=""),"Verificar","Ok")) -> Ok | AG28: =IF(AND(AE28="sim",AF28="Não"),"Verificar","Ok") -> Ok | AI28: =IF(AH28="Não","Verificar","Ok") -> Ok | AJ28: =IF(N28=1,"Sim, precisa de plano cadastrado na PGPC", "Não") -> Não | AM28: =IF(OR(AL28=" ",AL28="Sim"),"Ok",IF(AJ28="Não","Ok","Verificar")) -> Ok | AO28: =IF(AND(Q28="Ok",U28="Ok",Y28="Ok",AC28="Ok",AG28="Ok",AI28="Ok",AM28="Ok"),"Cooperado SEM perguntas a serem evidenciadas","Cooperado COM perguntas a serem evidenciadas") -> Cooperado SEM perguntas a serem evidenciadas
A29: 2 | B29: A Central não apresenta fornecedores cadastrados na Lista Suja do MTE | I29: =_xlfn.XLOOKUP(J29,'3056'!$D:$D,'3056'!$C:$C,0,0) -> 0 | K29: {=MAX(IF(J29='3056'!$D:$D,'3056'!$I:$I))} -> 0 | L29: =IF(COUNTIFS('3056'!$D:$D,'A3056'!J29,'3056'!$I:$I,'A3056'!K29,'3056'!$F:$F,'A3056'!$L$7)>=1,1,0) -> 0 | M29: =IF(COUNTIFS('3056'!$D:$D,'A3056'!J29,'3056'!$I:$I,'A3056'!K29,'3056'!$F:$F,'A3056'!$M$7)>=1,1,0) -> 0 | N29: =IF(COUNTIFS('3056'!$D:$D,'A3056'!J29,'3056'!$I:$I,'A3056'!K29,'3056'!$F:$F,'A3056'!$N$7)>=1,1,0) -> 0 | Q29: =IF(AND(O29="Sim")*OR(P29="Não",P29="Não se aplica",P29=""),"Verificar","Ok") -> Ok | U29: =IF(AND(R29="Sim",T29="Siim"),"Ok",IF(AND(S29="Sim")*OR(T29="Não",T29="Não se aplica",T29=""),"Verificar","Ok")) -> Ok | Y29: =IF(AND(V29="Sim",X29="Siim"),"Ok",IF(AND(W29="Sim")*OR(X29="Não",X29="Não se aplica",X29=""),"Verificar","Ok")) -> Ok | AC29: =IF(AND(Z29="Sim",AB29="Siim"),"Ok",IF(AND(AA29="Sim")*OR(AB29="Não",AB29="Não se aplica",AB29=""),"Verificar","Ok")) -> Ok | AG29: =IF(AND(AE29="sim",AF29="Não"),"Verificar","Ok") -> Ok | AI29: =IF(AH29="Não","Verificar","Ok") -> Ok | AJ29: =IF(N29=1,"Sim, precisa de plano cadastrado na PGPC", "Não") -> Não | AM29: =IF(OR(AL29=" ",AL29="Sim"),"Ok",IF(AJ29="Não","Ok","Verificar")) -> Ok | AO29: =IF(AND(Q29="Ok",U29="Ok",Y29="Ok",AC29="Ok",AG29="Ok",AI29="Ok",AM29="Ok"),"Cooperado SEM perguntas a serem evidenciadas","Cooperado COM perguntas a serem evidenciadas") -> Cooperado SEM perguntas a serem evidenciadas
A30: 3 | I30: =_xlfn.XLOOKUP(J30,'3056'!$D:$D,'3056'!$C:$C,0,0) -> 0 | K30: {=MAX(IF(J30='3056'!$D:$D,'3056'!$I:$I))} -> 0 | L30: =IF(COUNTIFS('3056'!$D:$D,'A3056'!J30,'3056'!$I:$I,'A3056'!K30,'3056'!$F:$F,'A3056'!$L$7)>=1,1,0) -> 0 | M30: =IF(COUNTIFS('3056'!$D:$D,'A3056'!J30,'3056'!$I:$I,'A3056'!K30,'3056'!$F:$F,'A3056'!$M$7)>=1,1,0) -> 0 | N30: =IF(COUNTIFS('3056'!$D:$D,'A3056'!J30,'3056'!$I:$I,'A3056'!K30,'3056'!$F:$F,'A3056'!$N$7)>=1,1,0) -> 0 | Q30: =IF(AND(O30="Sim")*OR(P30="Não",P30="Não se aplica",P30=""),"Verificar","Ok") -> Ok | U30: =IF(AND(R30="Sim",T30="Siim"),"Ok",IF(AND(S30="Sim")*OR(T30="Não",T30="Não se aplica",T30=""),"Verificar","Ok")) -> Ok | Y30: =IF(AND(V30="Sim",X30="Siim"),"Ok",IF(AND(W30="Sim")*OR(X30="Não",X30="Não se aplica",X30=""),"Verificar","Ok")) -> Ok | AC30: =IF(AND(Z30="Sim",AB30="Siim"),"Ok",IF(AND(AA30="Sim")*OR(AB30="Não",AB30="Não se aplica",AB30=""),"Verificar","Ok")) -> Ok | AG30: =IF(AND(AE30="sim",AF30="Não"),"Verificar","Ok") -> Ok | AI30: =IF(AH30="Não","Verificar","Ok") -> Ok | AJ30: =IF(N30=1,"Sim, precisa de plano cadastrado na PGPC", "Não") -> Não | AM30: =IF(OR(AL30=" ",AL30="Sim"),"Ok",IF(AJ30="Não","Ok","Verificar")) -> Ok | AO30: =IF(AND(Q30="Ok",U30="Ok",Y30="Ok",AC30="Ok",AG30="Ok",AI30="Ok",AM30="Ok"),"Cooperado SEM perguntas a serem evidenciadas","Cooperado COM perguntas a serem evidenciadas") -> Cooperado SEM perguntas a serem evidenciadas
A31: 4 | I31: =_xlfn.XLOOKUP(J31,'3056'!$D:$D,'3056'!$C:$C,0,0) -> 0 | K31: {=MAX(IF(J31='3056'!$D:$D,'3056'!$I:$I))} -> 0 | L31: =IF(COUNTIFS('3056'!$D:$D,'A3056'!J31,'3056'!$I:$I,'A3056'!K31,'3056'!$F:$F,'A3056'!$L$7)>=1,1,0) -> 0 | M31: =IF(COUNTIFS('3056'!$D:$D,'A3056'!J31,'3056'!$I:$I,'A3056'!K31,'3056'!$F:$F,'A3056'!$M$7)>=1,1,0) -> 0 | N31: =IF(COUNTIFS('3056'!$D:$D,'A3056'!J31,'3056'!$I:$I,'A3056'!K31,'3056'!$F:$F,'A3056'!$N$7)>=1,1,0) -> 0 | Q31: =IF(AND(O31="Sim")*OR(P31="Não",P31="Não se aplica",P31=""),"Verificar","Ok") -> Ok | U31: =IF(AND(R31="Sim",T31="Siim"),"Ok",IF(AND(S31="Sim")*OR(T31="Não",T31="Não se aplica",T31=""),"Verificar","Ok")) -> Ok | Y31: =IF(AND(V31="Sim",X31="Siim"),"Ok",IF(AND(W31="Sim")*OR(X31="Não",X31="Não se aplica",X31=""),"Verificar","Ok")) -> Ok | AC31: =IF(AND(Z31="Sim",AB31="Siim"),"Ok",IF(AND(AA31="Sim")*OR(AB31="Não",AB31="Não se aplica",AB31=""),"Verificar","Ok")) -> Ok | AG31: =IF(AND(AE31="sim",AF31="Não"),"Verificar","Ok") -> Ok | AI31: =IF(AH31="Não","Verificar","Ok") -> Ok | AJ31: =IF(N31=1,"Sim, precisa de plano cadastrado na PGPC", "Não") -> Não | AM31: =IF(OR(AL31=" ",AL31="Sim"),"Ok",IF(AJ31="Não","Ok","Verificar")) -> Ok | AO31: =IF(AND(Q31="Ok",U31="Ok",Y31="Ok",AC31="Ok",AG31="Ok",AI31="Ok",AM31="Ok"),"Cooperado SEM perguntas a serem evidenciadas","Cooperado COM perguntas a serem evidenciadas") -> Cooperado SEM perguntas a serem evidenciadas
A32: 5 | I32: =_xlfn.XLOOKUP(J32,'3056'!$D:$D,'3056'!$C:$C,0,0) -> 0 | K32: {=MAX(IF(J32='3056'!$D:$D,'3056'!$I:$I))} -> 0 | L32: =IF(COUNTIFS('3056'!$D:$D,'A3056'!J32,'3056'!$I:$I,'A3056'!K32,'3056'!$F:$F,'A3056'!$L$7)>=1,1,0) -> 0 | M32: =IF(COUNTIFS('3056'!$D:$D,'A3056'!J32,'3056'!$I:$I,'A3056'!K32,'3056'!$F:$F,'A3056'!$M$7)>=1,1,0) -> 0 | N32: =IF(COUNTIFS('3056'!$D:$D,'A3056'!J32,'3056'!$I:$I,'A3056'!K32,'3056'!$F:$F,'A3056'!$N$7)>=1,1,0) -> 0 | Q32: =IF(AND(O32="Sim")*OR(P32="Não",P32="Não se aplica",P32=""),"Verificar","Ok") -> Ok | U32: =IF(AND(R32="Sim",T32="Siim"),"Ok",IF(AND(S32="Sim")*OR(T32="Não",T32="Não se aplica",T32=""),"Verificar","Ok")) -> Ok | Y32: =IF(AND(V32="Sim",X32="Siim"),"Ok",IF(AND(W32="Sim")*OR(X32="Não",X32="Não se aplica",X32=""),"Verificar","Ok")) -> Ok | AC32: =IF(AND(Z32="Sim",AB32="Siim"),"Ok",IF(AND(AA32="Sim")*OR(AB32="Não",AB32="Não se aplica",AB32=""),"Verificar","Ok")) -> Ok | AG32: =IF(AND(AE32="sim",AF32="Não"),"Verificar","Ok") -> Ok | AI32: =IF(AH32="Não","Verificar","Ok") -> Ok | AJ32: =IF(N32=1,"Sim, precisa de plano cadastrado na PGPC", "Não") -> Não | AM32: =IF(OR(AL32=" ",AL32="Sim"),"Ok",IF(AJ32="Não","Ok","Verificar")) -> Ok | AO32: =IF(AND(Q32="Ok",U32="Ok",Y32="Ok",AC32="Ok",AG32="Ok",AI32="Ok",AM32="Ok"),"Cooperado SEM perguntas a serem evidenciadas","Cooperado COM perguntas a serem evidenciadas") -> Cooperado SEM perguntas a serem evidenciadas
A33: 6 | I33: =_xlfn.XLOOKUP(J33,'3056'!$D:$D,'3056'!$C:$C,0,0) -> 0 | K33: {=MAX(IF(J33='3056'!$D:$D,'3056'!$I:$I))} -> 0 | L33: =IF(COUNTIFS('3056'!$D:$D,'A3056'!J33,'3056'!$I:$I,'A3056'!K33,'3056'!$F:$F,'A3056'!$L$7)>=1,1,0) -> 0 | M33: =IF(COUNTIFS('3056'!$D:$D,'A3056'!J33,'3056'!$I:$I,'A3056'!K33,'3056'!$F:$F,'A3056'!$M$7)>=1,1,0) -> 0 | N33: =IF(COUNTIFS('3056'!$D:$D,'A3056'!J33,'3056'!$I:$I,'A3056'!K33,'3056'!$F:$F,'A3056'!$N$7)>=1,1,0) -> 0 | Q33: =IF(AND(O33="Sim")*OR(P33="Não",P33="Não se aplica",P33=""),"Verificar","Ok") -> Ok | U33: =IF(AND(R33="Sim",T33="Siim"),"Ok",IF(AND(S33="Sim")*OR(T33="Não",T33="Não se aplica",T33=""),"Verificar","Ok")) -> Ok | Y33: =IF(AND(V33="Sim",X33="Siim"),"Ok",IF(AND(W33="Sim")*OR(X33="Não",X33="Não se aplica",X33=""),"Verificar","Ok")) -> Ok | AC33: =IF(AND(Z33="Sim",AB33="Siim"),"Ok",IF(AND(AA33="Sim")*OR(AB33="Não",AB33="Não se aplica",AB33=""),"Verificar","Ok")) -> Ok | AG33: =IF(AND(AE33="sim",AF33="Não"),"Verificar","Ok") -> Ok | AI33: =IF(AH33="Não","Verificar","Ok") -> Ok | AJ33: =IF(N33=1,"Sim, precisa de plano cadastrado na PGPC", "Não") -> Não | AM33: =IF(OR(AL33=" ",AL33="Sim"),"Ok",IF(AJ33="Não","Ok","Verificar")) -> Ok | AO33: =IF(AND(Q33="Ok",U33="Ok",Y33="Ok",AC33="Ok",AG33="Ok",AI33="Ok",AM33="Ok"),"Cooperado SEM perguntas a serem evidenciadas","Cooperado COM perguntas a serem evidenciadas") -> Cooperado SEM perguntas a serem evidenciadas
A34: 7 | I34: =_xlfn.XLOOKUP(J34,'3056'!$D:$D,'3056'!$C:$C,0,0) -> 0 | K34: {=MAX(IF(J34='3056'!$D:$D,'3056'!$I:$I))} -> 0 | L34: =IF(COUNTIFS('3056'!$D:$D,'A3056'!J34,'3056'!$I:$I,'A3056'!K34,'3056'!$F:$F,'A3056'!$L$7)>=1,1,0) -> 0 | M34: =IF(COUNTIFS('3056'!$D:$D,'A3056'!J34,'3056'!$I:$I,'A3056'!K34,'3056'!$F:$F,'A3056'!$M$7)>=1,1,0) -> 0 | N34: =IF(COUNTIFS('3056'!$D:$D,'A3056'!J34,'3056'!$I:$I,'A3056'!K34,'3056'!$F:$F,'A3056'!$N$7)>=1,1,0) -> 0 | Q34: =IF(AND(O34="Sim")*OR(P34="Não",P34="Não se aplica",P34=""),"Verificar","Ok") -> Ok | U34: =IF(AND(R34="Sim",T34="Siim"),"Ok",IF(AND(S34="Sim")*OR(T34="Não",T34="Não se aplica",T34=""),"Verificar","Ok")) -> Ok | Y34: =IF(AND(V34="Sim",X34="Siim"),"Ok",IF(AND(W34="Sim")*OR(X34="Não",X34="Não se aplica",X34=""),"Verificar","Ok")) -> Ok | AC34: =IF(AND(Z34="Sim",AB34="Siim"),"Ok",IF(AND(AA34="Sim")*OR(AB34="Não",AB34="Não se aplica",AB34=""),"Verificar","Ok")) -> Ok | AG34: =IF(AND(AE34="sim",AF34="Não"),"Verificar","Ok") -> Ok | AI34: =IF(AH34="Não","Verificar","Ok") -> Ok | AJ34: =IF(N34=1,"Sim, precisa de plano cadastrado na PGPC", "Não") -> Não | AM34: =IF(OR(AL34=" ",AL34="Sim"),"Ok",IF(AJ34="Não","Ok","Verificar")) -> Ok | AO34: =IF(AND(Q34="Ok",U34="Ok",Y34="Ok",AC34="Ok",AG34="Ok",AI34="Ok",AM34="Ok"),"Cooperado SEM perguntas a serem evidenciadas","Cooperado COM perguntas a serem evidenciadas") -> Cooperado SEM perguntas a serem evidenciadas
A35: 8 | I35: =_xlfn.XLOOKUP(J35,'3056'!$D:$D,'3056'!$C:$C,0,0) -> 0 | K35: {=MAX(IF(J35='3056'!$D:$D,'3056'!$I:$I))} -> 0 | L35: =IF(COUNTIFS('3056'!$D:$D,'A3056'!J35,'3056'!$I:$I,'A3056'!K35,'3056'!$F:$F,'A3056'!$L$7)>=1,1,0) -> 0 | M35: =IF(COUNTIFS('3056'!$D:$D,'A3056'!J35,'3056'!$I:$I,'A3056'!K35,'3056'!$F:$F,'A3056'!$M$7)>=1,1,0) -> 0 | N35: =IF(COUNTIFS('3056'!$D:$D,'A3056'!J35,'3056'!$I:$I,'A3056'!K35,'3056'!$F:$F,'A3056'!$N$7)>=1,1,0) -> 0 | Q35: =IF(AND(O35="Sim")*OR(P35="Não",P35="Não se aplica",P35=""),"Verificar","Ok") -> Ok | U35: =IF(AND(R35="Sim",T35="Siim"),"Ok",IF(AND(S35="Sim")*OR(T35="Não",T35="Não se aplica",T35=""),"Verificar","Ok")) -> Ok | Y35: =IF(AND(V35="Sim",X35="Siim"),"Ok",IF(AND(W35="Sim")*OR(X35="Não",X35="Não se aplica",X35=""),"Verificar","Ok")) -> Ok | AC35: =IF(AND(Z35="Sim",AB35="Siim"),"Ok",IF(AND(AA35="Sim")*OR(AB35="Não",AB35="Não se aplica",AB35=""),"Verificar","Ok")) -> Ok | AG35: =IF(AND(AE35="sim",AF35="Não"),"Verificar","Ok") -> Ok | AI35: =IF(AH35="Não","Verificar","Ok") -> Ok | AJ35: =IF(N35=1,"Sim, precisa de plano cadastrado na PGPC", "Não") -> Não | AM35: =IF(OR(AL35=" ",AL35="Sim"),"Ok",IF(AJ35="Não","Ok","Verificar")) -> Ok | AO35: =IF(AND(Q35="Ok",U35="Ok",Y35="Ok",AC35="Ok",AG35="Ok",AI35="Ok",AM35="Ok"),"Cooperado SEM perguntas a serem evidenciadas","Cooperado COM perguntas a serem evidenciadas") -> Cooperado SEM perguntas a serem evidenciadas
A36: 9 | I36: =_xlfn.XLOOKUP(J36,'3056'!$D:$D,'3056'!$C:$C,0,0) -> 0 | K36: {=MAX(IF(J36='3056'!$D:$D,'3056'!$I:$I))} -> 0 | L36: =IF(COUNTIFS('3056'!$D:$D,'A3056'!J36,'3056'!$I:$I,'A3056'!K36,'3056'!$F:$F,'A3056'!$L$7)>=1,1,0) -> 0 | M36: =IF(COUNTIFS('3056'!$D:$D,'A3056'!J36,'3056'!$I:$I,'A3056'!K36,'3056'!$F:$F,'A3056'!$M$7)>=1,1,0) -> 0 | N36: =IF(COUNTIFS('3056'!$D:$D,'A3056'!J36,'3056'!$I:$I,'A3056'!K36,'3056'!$F:$F,'A3056'!$N$7)>=1,1,0) -> 0 | Q36: =IF(AND(O36="Sim")*OR(P36="Não",P36="Não se aplica",P36=""),"Verificar","Ok") -> Ok | U36: =IF(AND(R36="Sim",T36="Siim"),"Ok",IF(AND(S36="Sim")*OR(T36="Não",T36="Não se aplica",T36=""),"Verificar","Ok")) -> Ok | Y36: =IF(AND(V36="Sim",X36="Siim"),"Ok",IF(AND(W36="Sim")*OR(X36="Não",X36="Não se aplica",X36=""),"Verificar","Ok")) -> Ok | AC36: =IF(AND(Z36="Sim",AB36="Siim"),"Ok",IF(AND(AA36="Sim")*OR(AB36="Não",AB36="Não se aplica",AB36=""),"Verificar","Ok")) -> Ok | AG36: =IF(AND(AE36="sim",AF36="Não"),"Verificar","Ok") -> Ok | AI36: =IF(AH36="Não","Verificar","Ok") -> Ok | AJ36: =IF(N36=1,"Sim, precisa de plano cadastrado na PGPC", "Não") -> Não | AM36: =IF(OR(AL36=" ",AL36="Sim"),"Ok",IF(AJ36="Não","Ok","Verificar")) -> Ok | AO36: =IF(AND(Q36="Ok",U36="Ok",Y36="Ok",AC36="Ok",AG36="Ok",AI36="Ok",AM36="Ok"),"Cooperado SEM perguntas a serem evidenciadas","Cooperado COM perguntas a serem evidenciadas") -> Cooperado SEM perguntas a serem evidenciadas
